Workbook

Sheet Instrucciones
A1: [EVALUACIÓN IA — NO OFICIAL — solo para comparación con la evaluación humana] Evaluación a ciegas con la rúbrica de 5 criterios — Evaluador 1
A2: Tesis: LLM como asistentes de programación PLC en la academia (UTP). 600 respuestas de código de 25 tareas (generación y conversión), cada una con un código que no revela el modelo ni la estrategia.
A4: Qué hay que hacer
A5: 1. Trabaja una tarea completa antes de pasar a la siguiente. Abre respuestas/Respuestas_<tarea>.html (enunciado, protocolo de prueba y respuestas por código) y la hoja de la misma tarea en este libro.
A6: 2. Rellena ÚNICAMENTE las celdas amarillas con 0, 1, 2 o 3 según la hoja Rúbrica. Las celdas azules vienen de CODESYS o se calculan solas.
A7: 3. Justifica cada puntuación en una línea, en la columna de justificación correspondiente. Sin justificación, la puntuación no es auditable.
A8: 4. La fila gris EJEMPLO solo muestra el formato. No se analiza.
A9: 5. Puedes repartir el trabajo en varias sesiones. La tabla de avance de abajo indica qué falta. Guarda con el mismo nombre.
A11: Reglas de decisión (fijadas antes de evaluar; no se cambian durante la evaluación)
A12: Si la respuesta NO compila: Cumplimiento IEC = 0 y Corrección funcional = 0. Ya están precargadas. Los otros tres criterios se evalúan igual, leyendo el código.
A13: Si la respuesta pasa TODOS los pasos del harness: Corrección funcional = 3. Ya está precargada.
A14: Si compila pero falla pasos del harness: Corrección funcional es 0, 1 o 2 según la rúbrica. El HTML indica qué pasos fallaron y el protocolo de prueba dice qué comprueba cada paso.
... A23: Avance
A24: Tarea | B24: Respuestas | C24: Completas | D24: Pendientes
A25: B1 | B25: 24 | C25: =COUNTIF(B1!N6:N29,"Completa") | D25: =B25-C25
A26: B2 | B26: 24 | C26: =COUNTIF(B2!N6:N29,"Completa") | D26: =B26-C26
A27: B3 | B27: 24 | C27: =COUNTIF(B3!N6:N29,"Completa") | D27: =B27-C27
A28: B4 | B28: 24 | C28: =COUNTIF(B4!N6:N29,"Completa") | D28: =B28-C28
A29: B5 | B29: 24 | C29: =COUNTIF(B5!N6:N29,"Completa") | D29: =B29-C29
A30: B6 | B30: 24 | C30: =COUNTIF(B6!N6:N29,"Completa") | D30: =B30-C30
A31: B7 | B31: 24 | C31: =COUNTIF(B7!N6:N29,"Completa") | D31: =B31-C31
A32: B8 | B32: 24 | C32: =COUNTIF(B8!N6:N29,"Completa") | D32: =B32-C32
A33: I1 | B33: 24 | C33: =COUNTIF(I1!N6:N29,"Completa") | D33: =B33-C33
A34: I2 | B34: 24 | C34: =COUNTIF(I2!N6:N29,"Completa") | D34: =B34-C34
A35: I3 | B35: 24 | C35: =COUNTIF(I3!N6:N29,"Completa") | D35: =B35-C35
A36: I4 | B36: 24 | C36: =COUNTIF(I4!N6:N29,"Completa") | D36: =B36-C36
A37: I5 | B37: 24 | C37: =COUNTIF(I5!N6:N29,"Completa") | D37: =B37-C37
A38: I6 | B38: 24 | C38: =COUNTIF(I6!N6:N29,"Completa") | D38: =B38-C38
A39: I7 | B39: 24 | C39: =COUNTIF(I7!N6:N29,"Completa") | D39: =B39-C39
A40: I8 | B40: 24 | C40: =COUNTIF(I8!N6:N29,"Completa") | D40: =B40-C40
A41: A1 | B41: 24 | C41: =COUNTIF(A1!N6:N29,"Completa") | D41: =B41-C41
A42: A2 | B42: 24 | C42: =COUNTIF(A2!N6:N29,"Completa") | D42: =B42-C42
A43: A3 | B43: 24 | C43: =COUNTIF(A3!N6:N29,"Completa") | D43: =B43-C43
A44: A4 | B44: 24 | C44: =COUNTIF(A4!N6:N29,"Completa") | D44: =B44-C44
A45: A5 | B45: 24 | C45: =COUNTIF(A5!N6:N29,"Completa") | D45: =B45-C45
A46: A6 | B46: 24 | C46: =COUNTIF(A6!N6:N29,"Completa") | D46: =B46-C46
A47: C3 | B47: 24 | C47: =COUNTIF(C3!N6:N29,"Completa") | D47: =B47-C47
A48: C7 | B48: 24 | C48: =COUNTIF(C7!N6:N29,"Completa") | D48: =B48-C48
A49: C8 | B49: 24 | C49: =COUNTIF(C8!N6:N29,"Completa") | D49: =B49-C49
A50: Total | B50: =SUM(B25:B49) | C50: =SUM(C25:C49) | D50: =SUM(D25:D49)
A52: Nombre del evaluador:
A53: Fechas de calificación:

Sheet Rúbrica
A1: [EVALUACIÓN IA — NO OFICIAL — solo para comparación con la evaluación humana] Rúbrica de evaluación — 5 criterios × 4 niveles
A2: Fuente: Banco_de_Pruebas_v0.xlsx, hoja Rúbrica (2.5), sin cambios de redacción. Insuficiente = 0, Básico = 1, Competente = 2, Excelente = 3.
A4: Criterio | B4: Insuficiente (0) | C4: Básico (1) | D4: Competente (2) | E4: Excelente (3) | F4: Fuente del criterio
A5: Corrección funcional | B5: No implementa la lógica pedida o falla en el caso nominal. | C5: Funciona en el caso nominal pero falla en casos límite evidentes (flancos, reset, E-stop). | D5: Correcto en el caso nominal y en la mayoría de los casos límite; fallas menores sin riesgo. | E5: Correcto en todos los casos probados, incluidos límites y secuencias de fallo. | F5: IEC 61508 / simulación CODESYS
A6: Cumplimiento IEC 61131-3 | B6: No compila; sintaxis o declaraciones inválidas. | C6: Compila solo tras correcciones menores, o usa extensiones fuera del estándar. | D6: Compila sin cambios; declaraciones y tipos correctos. | E6: Compila sin cambios y usa construcciones idiomáticas del estándar (POU adecuado, tipos TIME correctos, FB estándar bien instanciados). | F6: IEC 61131-3 / compilador CODESYS
A7: Coherencia lógica | B7: Condiciones contradictorias, variables sin inicializar con efecto, o estados muertos que impiden operar. | C7: Lógica mayormente coherente con redundancias o condiciones muertas sin efecto grave. | D7: Sin contradicciones; inicialización correcta; transiciones completas. | E7: Además, robusta: interlocks completos, sin estados inalcanzables, comportamiento seguro ante entradas simultáneas. | F7: Análisis técnico + simulación
A8: Claridad estructural | B8: Sin estructura reconocible; nombres crípticos; sin comentarios. | C8: Estructura básica pero nombres pobres o comentarios ausentes/incorrectos. | D8: Nombres descriptivos, secciones ordenadas, comentarios útiles. | E8: Además, modularización adecuada (FB reutilizable, separación lógica/E/S) y comentarios que explican el porqué. | F8: Clean Code (Martin)
A9: Mantenibilidad | B9: Valores mágicos por doquier; imposible modificar sin reescribir. | C9: Modificable con esfuerzo; constantes parcialmente parametrizadas. | D9: Parámetros como variables/constantes declaradas; cambios localizados. | E9: Además, diseño extensible (parámetros de entrada del FB, sin duplicación de lógica). | F9: ISO/IEC 25010

Sheet B1
A1: [EVALUACIÓN IA — NO OFICIAL — solo para comparación con la evaluación humana] B1 — Arranque/paro de motor con enclavamiento (Basico)
A2: Lee cada respuesta por su código en respuestas/Respuestas_B1.html. Rellena solo las celdas amarillas. Las azules vienen de CODESYS o se calculan solas. La fila EJEMPLO no se analiza.
A4: Código | B4: Resultado en CODESYS (automático) | C4: Corrección funcional (0–3) | D4: Cumplimiento IEC (0–3) | E4: Coherencia lógica (0–3) | F4: Claridad estructural (0–3) | G4: Mantenibilidad (0–3) | H4: Total (0–15) | I4: Justificación: corrección funcional / IEC | J4: Justificación: coherencia | K4: Justificación: claridad | L4: Justificación: mantenibilidad | M4: Observaciones | N4: Estado
A5: EJEMPLO | B5: Compila. Falla 2 de 7 pasos del harness (pasos 3,5; numerados desde 0). | C5: 1 | D5: 2 | E5: 2 | F5: 2 | G5: 1 | H5: =IF(COUNT(C5:G5)=5,SUM(C5:G5),"") | I5: Arranca y para, pero rearranca solo tras la emergencia. | J5: Sin contradicciones; transiciones completas. | K5: Nombres claros, comentarios útiles. | L5: El tiempo está escrito como literal en dos sitios. | N5: =IF(COUNT(C5:G5)=5,"Completa","Falta")
A6: B1-3577 | B6: Compila. Pasa los 7 pasos del harness. | C6: 3 | D6: 3 | E6: 3 | F6: 3 | G6: 3 | H6: =IF(COUNT(C6:G6)=5,SUM(C6:G6),"") | I6: Compila y pasa los 7 pasos; usa R_TRIG estándar bien instanciado dentro de un FUNCTION_BLOCK: idiomático. | J6: Enclavamiento con paro dominante y flanco R_TRIG: sin rearranque tras emergencia, sin estados muertos, seguro ante entradas simultáneas. | K6: Nombres descriptivos y comentarios que explican por qué se usa el flanco; FB compacto y reutilizable. | L6: Una sola expresión sin duplicación ni valores mágicos; fácil de extender con nuevas condiciones de paro. | N6: =IF(COUNT(C6:G6)=5,"Completa","Falta")
A7: B1-8070 | B7: No compila (12 errores). | C7: 0 | D7: 0 | E7: 1 | F7: 2 | G7: 2 | H7: =IF(COUNT(C7:G7)=5,SUM(C7:G7),"") | J7: Bloqueo de emergencia permanente sin ninguna vía de reset: tras la primera emergencia el motor queda inoperable (estado terminal). Rama ELSEIF emergenciaActiva redundante. | K7: Comentarios útiles y nombres claros; el comentario 'Programa principal' es impreciso en un FB. | L7: Sin valores mágicos y cambios localizados, pero la cadena de ramas duplica asignaciones a motorOn. | N7: =IF(COUNT(C7:G7)=5,"Completa","Falta")
A8: B1-4667 | B8: Compila. Pasa los 7 pasos del harness. | C8: 3 | D8: 2 | E8: 3 | F8: 3 | G8: 2 | H8: =IF(COUNT(C8:G8)=5,SUM(C8:G8),"") | I8: Compila y pasa los 7 pasos; declaraciones y tipos correctos con IF/ELSIF estándar, sin FB estándar de flanco. | J8: Bloqueo de emergencia que se libera solo sin emergencia y sin marcha pulsada: evita rearranque y no deja estados muertos. | K8: Nombres claros y comentarios que explican el porqué de la condición de liberación del bloqueo. | L8: Sin valores mágicos y lógica localizada; la condición de liberación está separada y es fácil de modificar. | N8: =IF(COUNT(C8:G8)=5,"Completa","Falta")
A9: B1-3153 | B9: Compila. Falla 1 de 7 pasos del harness (pasos 6; numerados desde 0). | C9: 1 | D9: 2 | E9: 2 | F9: 1 | G9: 2 | H9: =IF(COUNT(C9:G9)=5,SUM(C9:G9),"") | I9: Compila; falla el paso 6 (rearranca tras liberar la emergencia con marcha pulsada): falla un caso límite de E-stop. | J9: Lógica coherente con paro prioritario, pero sin enclavamiento de emergencia; variable interna redundante con la salida. | K9: Estructura clara pero el comentario afirma que tras la emergencia 'no puede rearrancar', lo cual es incorrecto. | L9: Sin valores mágicos y lógica localizada en un IF; cambios sencillos. | N9: =IF(COUNT(C9:G9)=5,"Completa","Falta")
A10: B1-3916 | B10: Compila. Pasa los 7 pasos del harness. | C10: 3 | D10: 3 | E10: 3 | F10: 3 | G10: 3 | H10: =IF(COUNT(C10:G10)=5,SUM(C10:G10),"") | I10: Compila y pasa los 7 pasos; usa R_TRIG estándar bien instanciado dentro de un FUNCTION_BLOCK: idiomático. | J10: Enclavamiento con paro dominante y flanco R_TRIG: sin rearranque tras emergencia, sin estados muertos, seguro ante entradas simultáneas. | K10: Nombres descriptivos y comentarios que explican por qué se usa el flanco; FB compacto y reutilizable. | L10: Una sola expresión sin duplicación ni valores mágicos; fácil de extender con nuevas condiciones de paro. | N10: =IF(COUNT(C10:G10)=5,"Completa","Falta")
A11: B1-4316 | B11: Compila. Pasa los 7 pasos del harness. | C11: 3 | D11: 2 | E11: 2 | F11: 2 | G11: 2 | H11: =IF(COUNT(C11:G11)=5,SUM(C11:G11),"") | I11: Compila y pasa los 7 pasos; declaraciones correctas con IF/ELSIF, sin construcciones estándar de flanco. | J11: Sin contradicciones funcionales; bloqueo liberado sin emergencia ni marcha; condición 'bloqueado' parcialmente redundante con btnEmerg. | K11: Secciones numeradas y comentarios extensos, aunque el comentario inicial ('solo se resetea manualmente', 'flanco o nivel') contradice el código. | L11: Sin valores mágicos; lógica separada en pasos, fácil de ajustar. | N11: =IF(COUNT(C11:G11)=5,"Completa","Falta")
A12: B1-7103 | B12: Compila. Falla 1 de 7 pasos del harness (pasos 6; numerados desde 0). | C12: 1 | D12: 2 | E12: 2 | F12: 2 | G12: 2 | H12: =IF(COUNT(C12:G12)=5,SUM(C12:G12),"") | I12: Compila; falla el paso 6 (rearranque con marcha mantenida tras emergencia): falla caso límite de E-stop. | J12: Lógica coherente con paro prioritario, pero sin enclavamiento de emergencia; variable interna redundante con la salida. | K12: Nombres descriptivos y comentarios breves correctos; estructura simple. | L12: Sin valores mágicos; lógica localizada en un IF. | N12: =IF(COUNT(C12:G12)=5,"Completa","Falta")
A13: B1-3006 | B13: Compila. Pasa los 7 pasos del harness. | C13: 3 | D13: 2 | E13: 1 | F13: 2 | G13: 2 | H13: =IF(COUNT(C13:G13)=5,SUM(C13:G13),"") | I13: Compila y pasa los 7 pasos; declaraciones correctas con IF/ELSIF, sin FB estándar de flanco. | J13: Bloqueo de emergencia permanente sin ninguna vía de reset: tras la primera emergencia el motor queda inoperable (estado terminal). | K13: Bloque de comentarios y secciones claras; el comentario menciona un 'reset manual' que no existe en el código. | L13: Sin valores mágicos; cambios localizados, aunque añadir el reset exigiría tocar la interfaz. | N13: =IF(COUNT(C13:G13)=5,"Completa","Falta")
A14: B1-7637 | B14: Compila. Pasa los 7 pasos del harness. | C14: 3 | D14: 2 | E14: 1 | F14: 2 | G14: 2 | H14: =IF(COUNT(C14:G14)=5,SUM(C14:G14),"") | I14: Compila y pasa los 7 pasos; declaraciones correctas con IF/ELSIF, sin FB estándar. | J14: Bloqueo de emergencia permanente sin ninguna vía de reset: tras la primera emergencia el motor queda inoperable (estado terminal). Rama ELSIF emergenciaActiva redundante. | K14: Nombres claros y comentarios útiles en cada rama. | L14: Sin valores mágicos y cambios localizados; asignaciones a motorOn repetidas en varias ramas. | N14: =IF(COUNT(C14:G14)=5,"Completa","Falta")
A15: B1-3504 | B15: Compila. Pasa los 7 pasos del harness. | C15: 3 | D15: 2 | E15: 1 | F15: 2 | G15: 2 | H15: =IF(COUNT(C15:G15)=5,SUM(C15:G15),"") | I15: Compila y pasa los 7 pasos; declaraciones correctas con IF/ELSIF, sin FB estándar. | J15: Bloqueo de emergencia permanente sin ninguna vía de reset: tras la primera emergencia el motor queda inoperable (estado terminal). | K15: Comentarios de sección y explicación de la auto-retención; menciona un 'reset manual' inexistente. | L15: Sin valores mágicos y cambios localizados. | N15: =IF(COUNT(C15:G15)=5,"Completa","Falta")
A16: B1-1729 | B16: Compila. Pasa los 7 pasos del harness. | C16: 3 | D16: 3 | E16: 3 | F16: 3 | G16: 3 | H16: =IF(COUNT(C16:G16)=5,SUM(C16:G16),"") | I16: Compila y pasa los 7 pasos; usa R_TRIG estándar bien instanciado dentro de un FUNCTION_BLOCK: idiomático. | J16: Enclavamiento con paro dominante y flanco R_TRIG: sin rearranque tras emergencia, sin estados muertos, seguro ante entradas simultáneas. | K16: Nombres descriptivos y comentarios que explican por qué se usa el flanco; FB compacto y reutilizable. | L16: Una sola expresión sin duplicación ni valores mágicos; fácil de extender con nuevas condiciones de paro. | N16: =IF(COUNT(C16:G16)=5,"Completa","Falta")
A17: B1-8468 | B17: Compila. Pasa los 7 pasos del harness. | C17: 3 | D17: 2 | E17: 1 | F17: 2 | G17: 2 | H17: =IF(COUNT(C17:G17)=5,SUM(C17:G17),"") | I17: Compila y pasa los 7 pasos; declaraciones correctas con IF/ELSIF. | J17: Bloqueo de emergencia permanente sin ninguna vía de reset: tras la primera emergencia el motor queda inoperable (estado terminal). Variable estadoMotor redundante con la salida. | K17: Nombres descriptivos y comentarios útiles por rama. | L17: Sin valores mágicos; cambios localizados. | N17: =IF(COUNT(C17:G17)=5,"Completa","Falta")
A18: B1-2708 | B18: Compila. Falla 1 de 7 pasos del harness (pasos 6; numerados desde 0). | C18: 1 | D18: 2 | E18: 1 | F18: 2 | G18: 2 | H18: =IF(COUNT(C18:G18)=5,SUM(C18:G18),"") | I18: Compila; falla el paso 6: el bloqueo se libera en cuanto se suelta la emergencia y la marcha mantenida rearranca el motor. | J18: El bloqueo se libera con NOT motorOn, que siempre es cierto tras la emergencia: el interlock queda sin efecto real. | K18: Nombres claros y comentarios ordenados, aunque prometen un bloqueo que no actúa. | L18: Sin valores mágicos; lógica separada en tres bloques localizados. | N18: =IF(COUNT(C18:G18)=5,"Completa","Falta")
A19: B1-7716 | B19: Compila. Pasa los 7 pasos del harness. | C19: 3 | D19: 3 | E19: 3 | F19: 3 | G19: 3 | H19: =IF(COUNT(C19:G19)=5,SUM(C19:G19),"") | I19: Compila y pasa los 7 pasos; usa R_TRIG estándar bien instanciado dentro de un FUNCTION_BLOCK: idiomático. | J19: Enclavamiento con paro dominante y flanco R_TRIG: sin rearranque tras emergencia, sin estados muertos, seguro ante entradas simultáneas. | K19: Nombres descriptivos y comentarios que explican por qué se usa el flanco; FB compacto y reutilizable. | L19: Una sola expresión sin duplicación ni valores mágicos; fácil de extender con nuevas condiciones de paro. | N19: =IF(COUNT(C19:G19)=5,"Completa","Falta")
A20: B1-4160 | B20: No compila (12 errores). | C20: 0 | D20: 0 | E20: 1 | F20: 2 | G20: 2 | H20: =IF(COUNT(C20:G20)=5,SUM(C20:G20),"") | J20: Bloqueo de emergencia permanente sin ninguna vía de reset: tras la primera emergencia el motor queda inoperable (estado terminal). Rama ELSEIF emergenciaActiva redundante. | K20: Comentarios útiles y nombres claros; 'Programa principal' es impreciso en un FB. | L20: Sin valores mágicos y cambios localizados; asignaciones repetidas a motorOn. | N20: =IF(COUNT(C20:G20)=5,"Completa","Falta")
A21: B1-3776 | B21: Compila. Pasa los 7 pasos del harness. | C21: 3 | D21: 2 | E21: 1 | F21: 2 | G21: 2 | H21: =IF(COUNT(C21:G21)=5,SUM(C21:G21),"") | I21: Compila y pasa los 7 pasos; declaraciones correctas, IF anidado en lugar de ELSIF. | J21: Bloqueo de emergencia permanente sin ninguna vía de reset: tras la primera emergencia el motor queda inoperable (estado terminal). | K21: Nombres descriptivos y comentarios correctos; IF anidado menos legible que ELSIF. | L21: Sin valores mágicos; enclavamiento en una línea fácil de ajustar. | N21: =IF(COUNT(C21:G21)=5,"Completa","Falta")
A22: B1-1689 | B22: Compila. Falla 1 de 7 pasos del harness (pasos 6; numerados desde 0). | C22: 1 | D22: 2 | E22: 2 | F22: 2 | G22: 2 | H22: =IF(COUNT(C22:G22)=5,SUM(C22:G22),"") | I22: Compila; falla el paso 6 (rearranque con marcha mantenida tras emergencia): falla caso límite de E-stop. | J22: Lógica coherente con paro prioritario, pero sin enclavamiento de emergencia; variable interna redundante con la salida. | K22: Nombres descriptivos y comentarios breves correctos. | L22: Sin valores mágicos; lógica localizada. | N22: =IF(COUNT(C22:G22)=5,"Completa","Falta")
A23: B1-7970 | B23: Compila. Falla 1 de 7 pasos del harness (pasos 6; numerados desde 0). | C23: 1 | D23: 2 | E23: 1 | F23: 1 | G23: 1 | H23: =IF(COUNT(C23:G23)=5,SUM(C23:G23),"") | I23: Compila; falla el paso 6: el latch de emergencia se borra en cuanto btnEmerg vuelve a FALSE y el motor rearranca. | J23: El latch de emergencia se resetea en el mismo ciclo en que cae btnEmerg (sin efecto) y motorOn se asigna en dos IF sucesivos; redundancias. | K23: Nombres aceptables pero lógica enmarañada en tres IF; comentario de reset ('si el motor está apagado') no corresponde al código. | L23: Dos latches y asignaciones repetidas a motorOn; modificar exige revisar varios bloques. | N23: =IF(COUNT(C23:G23)=5,"Completa","Falta")
A24: B1-2577 | B24: Compila. Pasa los 7 pasos del harness. | C24: 3 | D24: 2 | E24: 3 | F24: 2 | G24: 2 | H24: =IF(COUNT(C24:G24)=5,SUM(C24:G24),"") | I24: Compila y pasa los 7 pasos; declaraciones correctas con IF/ELSIF. | J24: Bloqueo de emergencia con reset definido por pulsación de paro, paro dominante; sin estados muertos y seguro ante entradas simultáneas. | K24: Nombres claros y comentarios útiles sobre bloqueo y auto-retención. | L24: Sin valores mágicos; lógica de bloqueo y desbloqueo separada y localizada. | N24: =IF(COUNT(C24:G24)=5,"Completa","Falta")
A25: B1-2078 | B25: Compila. Pasa los 7 pasos del harness. | C25: 3 | D25: 3 | E25: 3 | F25: 3 | G25: 3 | H25: =IF(COUNT(C25:G25)=5,SUM(C25:G25),"") | I25: Compila y pasa los 7 pasos; usa R_TRIG estándar bien instanciado dentro de un FUNCTION_BLOCK: idiomático. | J25: Enclavamiento con paro dominante y flanco R_TRIG: sin rearranque tras emergencia, sin estados muertos, seguro ante entradas simultáneas. | K25: Nombres descriptivos y comentarios que explican por qué se usa el flanco; FB compacto y reutilizable. | L25: Una sola expresión sin duplicación ni valores mágicos; fácil de extender con nuevas condiciones de paro. | N25: =IF(COUNT(C25:G25)=5,"Completa","Falta")
A26: B1-2077 | B26: Compila. Pasa los 7 pasos del harness. | C26: 3 | D26: 3 | E26: 3 | F26: 3 | G26: 3 | H26: =IF(COUNT(C26:G26)=5,SUM(C26:G26),"") | I26: Compila y pasa los 7 pasos; usa R_TRIG estándar bien instanciado dentro de un FUNCTION_BLOCK: idiomático. | J26: Enclavamiento con paro dominante y flanco R_TRIG: sin rearranque tras emergencia, sin estados muertos, seguro ante entradas simultáneas. | K26: Nombres descriptivos y comentarios que explican por qué se usa el flanco; FB compacto y reutilizable. | L26: Una sola expresión sin duplicación ni valores mágicos; fácil de extender con nuevas condiciones de paro. | N26: =IF(COUNT(C26:G26)=5,"Completa","Falta")
A27: B1-6475 | B27: Compila. Pasa los 7 pasos del harness. | C27: 3 | D27: 2 | E27: 1 | F27: 2 | G27: 2 | H27: =IF(COUNT(C27:G27)=5,SUM(C27:G27),"") | I27: Compila y pasa los 7 pasos; declaraciones correctas con IF/ELSIF. | J27: Bloqueo de emergencia permanente sin ninguna vía de reset: tras la primera emergencia el motor queda inoperable (estado terminal). Rama ELSIF estadoEmergencia redundante. | K27: Nombres claros y comentario general, sin comentarios por rama. | L27: Sin valores mágicos; asignaciones repetidas a motorOn. | N27: =IF(COUNT(C27:G27)=5,"Completa","Falta")
A28: B1-9711 | B28: Compila. Pasa los 7 pasos del harness. | C28: 3 | D28: 2 | E28: 1 | F28: 2 | G28: 2 | H28: =IF(COUNT(C28:G28)=5,SUM(C28:G28),"") | I28: Compila y pasa los 7 pasos; declaraciones correctas con IF/ELSIF. | J28: Bloqueo de emergencia permanente sin ninguna vía de reset: tras la primera emergencia el motor queda inoperable (estado terminal). Rama ELSIF estadoEmergencia redundante. | K28: Nombres claros y comentario general, sin comentarios por rama. | L28: Sin valores mágicos; asignaciones repetidas a motorOn. | N28: =IF(COUNT(C28:G28)=5,"Completa","Falta")
A29: B1-4469 | B29: Compila. Falla 1 de 7 pasos del harness (pasos 6; numerados desde 0). | C29: 1 | D29: 2 | E29: 1 | F29: 1 | G29: 1 | H29: =IF(COUNT(C29:G29)=5,SUM(C29:G29),"") | I29: Compila; falla el paso 6: emergStop se resetea con el motor apagado, por lo que no bloquea el rearranque. | J29: emergStop se borra en cuanto motorOn es FALSE (interlock sin efecto) y motorLatch es una autoasignación redundante. | K29: Comentarios que describen un latch y un bloqueo que no funcionan como dicen; estructura confusa. | L29: Variables redundantes y bloques innecesarios; modificar requiere entender interacciones ocultas. | N29: =IF(COUNT(C29:G29)=5,"Completa","Falta")

Sheet B2
A1: [EVALUACIÓN IA — NO OFICIAL — solo para comparación con la evaluación humana] B2 — Válvula con retardo TON (Basico)
A2: Lee cada respuesta por su código en respuestas/Respuestas_B2.html. Rellena solo las celdas amarillas. Las azules vienen de CODESYS o se calculan solas. La fila EJEMPLO no se analiza.
A4: Código | B4: Resultado en CODESYS (automático) | C4: Corrección funcional (0–3) | D4: Cumplimiento IEC (0–3) | E4: Coherencia lógica (0–3) | F4: Claridad estructural (0–3) | G4: Mantenibilidad (0–3) | H4: Total (0–15) | I4: Justificación: corrección funcional / IEC | J4: Justificación: coherencia | K4: Justificación: claridad | L4: Justificación: mantenibilidad | M4: Observaciones | N4: Estado
A5: EJEMPLO | B5: Compila. Falla 2 de 7 pasos del harness (pasos 3,5; numerados desde 0). | C5: 1 | D5: 2 | E5: 2 | F5: 2 | G5: 1 | H5: =IF(COUNT(C5:G5)=5,SUM(C5:G5),"") | I5: Arranca y para, pero rearranca solo tras la emergencia. | J5: Sin contradicciones; transiciones completas. | K5: Nombres claros, comentarios útiles. | L5: El tiempo está escrito como literal en dos sitios. | N5: =IF(COUNT(C5:G5)=5,"Completa","Falta")
A6: B2-9847 | B6: Compila. Pasa los 6 pasos del harness. | C6: 3 | D6: 2 | E6: 1 | F6: 1 | G6: 1 | H6: =IF(COUNT(C6:G6)=5,SUM(C6:G6),"") | I6: Compila y pasa los 6 pasos; TON llamado de forma condicional y en dos puntos, práctica no idiomática. | J6: El TON solo se llama mientras Q es FALSE y se reinicia en otra rama; variable 'estado' redundante. | K6: Nombres genéricos (timer, estado) y comentario 'Inicialización del timer' incorrecto. | L6: Llamadas al temporizador duplicadas; modificar el retardo exige revisar varios puntos. | N6: =IF(COUNT(C6:G6)=5,"Completa","Falta")
A7: B2-6674 | B7: Compila. Pasa los 6 pasos del harness. | C7: 3 | D7: 3 | E7: 3 | F7: 2 | G7: 2 | H7: =IF(COUNT(C7:G7)=5,SUM(C7:G7),"") | I7: Compila y pasa los 6 pasos; TON estándar instanciado y llamado una vez por ciclo con T#5S: idiomático. | J7: Lógica mínima y directa (salida = TON.Q): sin estados muertos, cierre inmediato garantizado por el reset del TON. | K7: Nombres descriptivos y comentario breve correcto; no explica el mecanismo de cierre inmediato. | L7: Sin duplicación; el tiempo está en un único punto, aunque T#5S va literal en la llamada y no como parámetro del FB. | N7: =IF(COUNT(C7:G7)=5,"Completa","Falta")
A8: B2-1651 | B8: Compila. Pasa los 6 pasos del harness. | C8: 3 | D8: 2 | E8: 1 | F8: 1 | G8: 1 | H8: =IF(COUNT(C8:G8)=5,SUM(C8:G8),"") | I8: Compila y pasa los 6 pasos; el TON se llama varias veces por ciclo en ramas distintas, no idiomático. | J8: Dos IF que repiten el mismo reinicio del TON y de 'estado': redundancias sin efecto grave. | K8: Nombres genéricos y comentario 'Inicialización del timer' que no corresponde al código. | L8: Lógica duplicada en dos bloques; un cambio debe replicarse. | N8: =IF(COUNT(C8:G8)=5,"Completa","Falta")
A9: B2-3609 | B9: Compila. Pasa los 6 pasos del harness. | C9: 3 | D9: 3 | E9: 3 | F9: 2 | G9: 2 | H9: =IF(COUNT(C9:G9)=5,SUM(C9:G9),"") | I9: Compila y pasa los 6 pasos; TON estándar instanciado y llamado una vez por ciclo con T#5S: idiomático. | J9: Lógica mínima y directa (salida = TON.Q): sin estados muertos, cierre inmediato garantizado por el reset del TON. | K9: Nombres descriptivos y comentario breve correcto; no explica el mecanismo de cierre inmediato. | L9: Sin duplicación; el tiempo está en un único punto, aunque T#5S va literal en la llamada y no como parámetro del FB. | N9: =IF(COUNT(C9:G9)=5,"Completa","Falta")
A10: B2-5560 | B10: Compila. Pasa los 6 pasos del harness. | C10: 3 | D10: 3 | E10: 3 | F10: 3 | G10: 2 | H10: =IF(COUNT(C10:G10)=5,SUM(C10:G10),"") | I10: Compila y pasa los 6 pasos; TON estándar instanciado y llamado una vez por ciclo con T#5S: idiomático. | J10: Lógica mínima y directa (salida = TON.Q): sin estados muertos, cierre inmediato garantizado por el reset del TON. | K10: Nombres descriptivos y comentarios que explican por qué la válvula cierra de inmediato (reset del TON). | L10: Sin duplicación; el tiempo está en un único punto, aunque T#5S va literal en la llamada y no como parámetro del FB. | N10: =IF(COUNT(C10:G10)=5,"Completa","Falta")
A11: B2-5675 | B11: Compila. Pasa los 6 pasos del harness. | C11: 3 | D11: 3 | E11: 3 | F11: 3 | G11: 2 | H11: =IF(COUNT(C11:G11)=5,SUM(C11:G11),"") | I11: Compila y pasa los 6 pasos; TON estándar instanciado y llamado una vez por ciclo con T#5S: idiomático. | J11: Lógica mínima y directa (salida = TON.Q): sin estados muertos, cierre inmediato garantizado por el reset del TON. | K11: Nombres descriptivos y comentarios que explican por qué la válvula cierra de inmediato (reset del TON). | L11: Sin duplicación; el tiempo está en un único punto, aunque T#5S va literal en la llamada y no como parámetro del FB. | N11: =IF(COUNT(C11:G11)=5,"Completa","Falta")
A12: B2-7015 | B12: Compila. Pasa los 6 pasos del harness. | C12: 3 | D12: 3 | E12: 3 | F12: 2 | G12: 2 | H12: =IF(COUNT(C12:G12)=5,SUM(C12:G12),"") | I12: Compila y pasa los 6 pasos; TON estándar instanciado y llamado una vez por ciclo con T#5S: idiomático. | J12: Lógica mínima y directa (salida = TON.Q): sin estados muertos, cierre inmediato garantizado por el reset del TON. | K12: Nombres descriptivos y comentario breve correcto; no explica el mecanismo de cierre inmediato. | L12: Sin duplicación; el tiempo está en un único punto, aunque T#5S va literal en la llamada y no como parámetro del FB. | N12: =IF(COUNT(C12:G12)=5,"Completa","Falta")
A13: B2-6278 | B13: Compila. Pasa los 6 pasos del harness. | C13: 3 | D13: 3 | E13: 3 | F13: 3 | G13: 2 | H13: =IF(COUNT(C13:G13)=5,SUM(C13:G13),"") | I13: Compila y pasa los 6 pasos; TON estándar instanciado y llamado una vez por ciclo con T#5S: idiomático. | J13: Lógica mínima y directa (salida = TON.Q): sin estados muertos, cierre inmediato garantizado por el reset del TON. | K13: Nombres descriptivos y comentarios que explican por qué la válvula cierra de inmediato (reset del TON). | L13: Sin duplicación; el tiempo está en un único punto, aunque T#5S va literal en la llamada y no como parámetro del FB. | N13: =IF(COUNT(C13:G13)=5,"Completa","Falta")
A14: B2-3727 | B14: Compila. Falla 3 de 6 pasos del harness (pasos 1,2,4; numerados desde 0). | C14: 0 | D14: 2 | E14: 1 | F14: 1 | G14: 2 | H14: =IF(COUNT(C14:G14)=5,SUM(C14:G14),"") | I14: Compila pero usa TP (pulso) en lugar de TON: abre al instante y cierra a los 5 s; falla el caso nominal (pasos 1, 2 y 4). | J14: Elección de temporizador contraria al requisito: la lógica abre sin esperar y cierra con nivel alto aún presente; IF final redundante. | K14: Estructura legible, pero los comentarios ('abre si el temporizador ha expirado') describen un comportamiento que TP no tiene. | L14: Tiempo en un único literal; cambios localizados pero T#5S no parametrizado. | N14: =IF(COUNT(C14:G14)=5,"Completa","Falta")
A15: B2-6755 | B15: Compila. Pasa los 6 pasos del harness. | C15: 3 | D15: 3 | E15: 3 | F15: 3 | G15: 2 | H15: =IF(COUNT(C15:G15)=5,SUM(C15:G15),"") | I15: Compila y pasa los 6 pasos; TON estándar instanciado y llamado una vez por ciclo con T#5S: idiomático. | J15: Lógica mínima y directa (salida = TON.Q): sin estados muertos, cierre inmediato garantizado por el reset del TON. | K15: Nombres descriptivos y comentarios que explican por qué la válvula cierra de inmediato (reset del TON). | L15: Sin duplicación; el tiempo está en un único punto, aunque T#5S va literal en la llamada y no como parámetro del FB. | N15: =IF(COUNT(C15:G15)=5,"Completa","Falta")
A16: B2-7829 | B16: Compila. Falla 3 de 6 pasos del harness (pasos 1,2,4; numerados desde 0). | C16: 0 | D16: 2 | E16: 1 | F16: 1 | G16: 2 | H16: =IF(COUNT(C16:G16)=5,SUM(C16:G16),"") | I16: Compila pero usa TP (pulso) en lugar de TON: abre al instante y cierra a los 5 s; falla el caso nominal (pasos 1, 2 y 4). | J16: Elección de temporizador contraria al requisito: la lógica abre sin esperar y cierra con nivel alto aún presente; IF final redundante. | K16: Estructura legible, pero los comentarios ('abre si el temporizador ha expirado') describen un comportamiento que TP no tiene. | L16: Tiempo en un único literal; cambios localizados pero T#5S no parametrizado. | N16: =IF(COUNT(C16:G16)=5,"Completa","Falta")
... A29: B2-2211 | B29: Compila. Pasa los 6 pasos del harness. | C29: 3 | D29: 3 | E29: 3 | F29: 3 | G29: 2 | H29: =IF(COUNT(C29:G29)=5,SUM(C29:G29),"") | I29: Compila y pasa los 6 pasos; TON estándar instanciado y llamado una vez por ciclo con T#5S: idiomático. | J29: Lógica mínima y directa (salida = TON.Q): sin estados muertos, cierre inmediato garantizado por el reset del TON. | K29: Nombres descriptivos y comentarios que explican por qué la válvula cierra de inmediato (reset del TON). | L29: Sin duplicación; el tiempo está en un único punto, aunque T#5S va literal en la llamada y no como parámetro del FB. | N29: =IF(COUNT(C29:G29)=5,"Completa","Falta")

Sheet B3
A1: [EVALUACIÓN IA — NO OFICIAL — solo para comparación con la evaluación humana] B3 — Contador de piezas con preset (Basico)
A2: Lee cada respuesta por su código en respuestas/Respuestas_B3.html. Rellena solo las celdas amarillas. Las azules vienen de CODESYS o se calculan solas. La fila EJEMPLO no se analiza.
A4: Código | B4: Resultado en CODESYS (automático) | C4: Corrección funcional (0–3) | D4: Cumplimiento IEC (0–3) | E4: Coherencia lógica (0–3) | F4: Claridad estructural (0–3) | G4: Mantenibilidad (0–3) | H4: Total (0–15) | I4: Justificación: corrección funcional / IEC | J4: Justificación: coherencia | K4: Justificación: claridad | L4: Justificación: mantenibilidad | M4: Observaciones | N4: Estado
A5: EJEMPLO | B5: Compila. Falla 2 de 7 pasos del harness (pasos 3,5; numerados desde 0). | C5: 1 | D5: 2 | E5: 2 | F5: 2 | G5: 1 | H5: =IF(COUNT(C5:G5)=5,SUM(C5:G5),"") | I5: Arranca y para, pero rearranca solo tras la emergencia. | J5: Sin contradicciones; transiciones completas. | K5: Nombres claros, comentarios útiles. | L5: El tiempo está escrito como literal en dos sitios. | N5: =IF(COUNT(C5:G5)=5,"Completa","Falta")
A6: B3-6721 | B6: Compila. Pasa los 7 pasos del harness. | C6: 3 | D6: 2 | E6: 3 | F6: 2 | G6: 2 | H6: =IF(COUNT(C6:G6)=5,SUM(C6:G6),"") | I6: Compila y pasa los 7 pasos; usa CTU pero con el pin RESET propio de CODESYS (IEC define R) y CV WORD asignado a INT implícitamente. | J6: CTU con reset y preset: lógica mínima y consistente, sin estados muertos. | K6: Nombres descriptivos y comentarios útiles, aunque descriptivos del qué más que del porqué. | L6: Preset 12 literal en la llamada al CTU; cambio localizado. | N6: =IF(COUNT(C6:G6)=5,"Completa","Falta")
A7: B3-4690 | B7: Compila. Falla 5 de 7 pasos del harness (pasos 1,2,3,4,5; numerados desde 0). | C7: 0 | D7: 2 | E7: 0 | F7: 1 | G7: 1 | H7: =IF(COUNT(C7:G7)=5,SUM(C7:G7),"") | I7: Compila pero sensorAnterior se iguala al sensor antes de comparar: nunca detecta flanco ni cuenta; falla el caso nominal. | J7: La condición de flanco es siempre falsa porque sensorAnterior se sobrescribe antes de usarse: condición contradictoria con efecto. | K7: Comentario 'Inicialización del sensorAnterior' describe justo el error; IF redundante para copiar un BOOL. | L7: Código redundante (IF que copia el sensor) y preset literal; corregir requiere reordenar la lógica. | N7: =IF(COUNT(C7:G7)=5,"Completa","Falta")
A8: B3-5495 | B8: Compila. Pasa los 7 pasos del harness. | C8: 3 | D8: 3 | E8: 3 | F8: 3 | G8: 2 | H8: =IF(COUNT(C8:G8)=5,SUM(C8:G8),"") | I8: Compila y pasa los 7 pasos; usa R_TRIG estándar bien instanciado e INT para la cuenta: idiomático. | J8: Reset prioritario, flanco correcto y salida de lote coherente con la cuenta; sin estados muertos. | K8: Nombres claros y comentarios que explican por qué loteListo se desactiva solo al reiniciar la cuenta. | L8: Preset 12 como literal en un único punto; cambios localizados pero no parametrizado. | N8: =IF(COUNT(C8:G8)=5,"Completa","Falta")
A9: B3-6597 | B9: Compila. Pasa los 7 pasos del harness. | C9: 3 | D9: 3 | E9: 3 | F9: 2 | G9: 2 | H9: =IF(COUNT(C9:G9)=5,SUM(C9:G9),"") | I9: Compila y pasa los 7 pasos; usa R_TRIG estándar bien instanciado e INT para la cuenta: idiomático. | J9: Reset prioritario, flanco correcto y salida de lote coherente con la cuenta; sin estados muertos. | K9: Nombres descriptivos y comentarios útiles, aunque descriptivos del qué más que del porqué. | L9: Preset 12 como literal en un único punto; cambios localizados pero no parametrizado. | N9: =IF(COUNT(C9:G9)=5,"Completa","Falta")
A10: B3-8516 | B10: Compila. Pasa los 7 pasos del harness. | C10: 3 | D10: 2 | E10: 3 | F10: 3 | G10: 2 | H10: =IF(COUNT(C10:G10)=5,SUM(C10:G10),"") | I10: Compila y pasa los 7 pasos; declaraciones y tipos correctos, flanco detectado manualmente en lugar de R_TRIG. | J10: Reset prioritario, flanco correcto y salida de lote coherente con la cuenta; sin estados muertos. | K10: Secciones numeradas, nombres descriptivos y comentarios que justifican la prioridad del reset. | L10: Preset 12 como literal en un único punto; cambios localizados pero no parametrizado. | N10: =IF(COUNT(C10:G10)=5,"Completa","Falta")
A11: B3-4736 | B11: Compila. Falla 5 de 7 pasos del harness (pasos 1,2,3,4,5; numerados desde 0). | C11: 0 | D11: 2 | E11: 0 | F11: 2 | G11: 2 | H11: =IF(COUNT(C11:G11)=5,SUM(C11:G11),"") | I11: Compila pero sensorAnterior := sensorPieza se ejecuta antes de la comparación: nunca cuenta; falla el caso nominal. | J11: Detección de flanco anulada por el orden de las asignaciones: condición siempre falsa. | K11: Nombres y comentarios claros, aunque la estructura induce el error de orden. | L11: Preset 12 como literal en un único punto; cambios localizados pero no parametrizado. | N11: =IF(COUNT(C11:G11)=5,"Completa","Falta")
A12: B3-6421 | B12: Compila. Pasa los 7 pasos del harness. | C12: 3 | D12: 2 | E12: 3 | F12: 2 | G12: 2 | H12: =IF(COUNT(C12:G12)=5,SUM(C12:G12),"") | I12: Compila y pasa los 7 pasos; declaraciones y tipos correctos, flanco detectado manualmente en lugar de R_TRIG. | J12: Reset prioritario, flanco correcto y salida de lote coherente con la cuenta; sin estados muertos. | K12: Nombres claros; comentario 'Inicialización de variables' no corresponde a la lógica que encabeza. | L12: Preset 12 como literal en un único punto; cambios localizados pero no parametrizado. | N12: =IF(COUNT(C12:G12)=5,"Completa","Falta")
A13: B3-8845 | B13: Compila. Pasa los 7 pasos del harness. | C13: 3 | D13: 2 | E13: 2 | F13: 2 | G13: 2 | H13: =IF(COUNT(C13:G13)=5,SUM(C13:G13),"") | I13: Compila y pasa los 7 pasos; declaraciones y tipos correctos, flanco detectado manualmente en lugar de R_TRIG. | J13: Correcta; loteListo se pone a FALSE en el reset y se recalcula de inmediato (redundancia sin efecto grave). | K13: Nombres claros; comentario 'Inicialización de variables' no corresponde a la lógica que encabeza. | L13: Preset 12 como literal en un único punto; cambios localizados pero no parametrizado. | N13: =IF(COUNT(C13:G13)=5,"Completa","Falta")
A14: B3-9202 | B14: No compila (6 errores). | C14: 0 | D14: 0 | E14: 3 | F14: 2 | G14: 2 | H14: =IF(COUNT(C14:G14)=5,SUM(C14:G14),"") | J14: Uso directo de CTU con reset y preset: lógica consistente y sin estados muertos. | K14: Nombres descriptivos y comentarios útiles, aunque descriptivos del qué más que del porqué. | L14: Preset 12 literal en la llamada al CTU; cambio localizado. | N14: =IF(COUNT(C14:G14)=5,"Completa","Falta")
A15: B3-5228 | B15: Compila. Pasa los 7 pasos del harness. | C15: 3 | D15: 3 | E15: 3 | F15: 3 | G15: 2 | H15: =IF(COUNT(C15:G15)=5,SUM(C15:G15),"") | I15: Compila y pasa los 7 pasos; usa R_TRIG estándar bien instanciado e INT para la cuenta: idiomático. | J15: Reset prioritario, flanco correcto y salida de lote coherente con la cuenta; sin estados muertos. | K15: Nombres claros y comentarios que explican por qué el lote se desactiva automáticamente. | L15: Preset 12 como literal en un único punto; cambios localizados pero no parametrizado. | N15: =IF(COUNT(C15:G15)=5,"Completa","Falta")
A16: B3-2786 | B16: Compila. Pasa los 7 pasos del harness. | C16: 3 | D16: 3 | E16: 3 | F16: 3 | G16: 2 | H16: =IF(COUNT(C16:G16)=5,SUM(C16:G16),"") | I16: Compila y pasa los 7 pasos; usa R_TRIG estándar bien instanciado e INT para la cuenta: idiomático. | J16: Reset prioritario y cuenta saturada en el lote: robusto, sin estados muertos ni desbordamiento. | K16: Nombres claros y comentarios que justifican la prioridad del reset y el bloqueo del conteo con lote completo. | L16: Preset 12 como literal en un único punto; cambios localizados pero no parametrizado. | N16: =IF(COUNT(C16:G16)=5,"Completa","Falta")
A17: B3-5689 | B17: Compila. Pasa los 7 pasos del harness. | C17: 3 | D17: 2 | E17: 2 | F17: 2 | G17: 2 | H17: =IF(COUNT(C17:G17)=5,SUM(C17:G17),"") | I17: Compila y pasa los 7 pasos; declaraciones y tipos correctos, flanco detectado manualmente en lugar de R_TRIG. | J17: Correcta, pero el reset no tiene prioridad estructural: en el mismo ciclo de reset puede contarse un flanco; asignaciones a loteListo redundantes. | K17: Nombres claros; comentario 'Inicialización de variables' no corresponde a la lógica que encabeza. | L17: Preset 12 como literal en un único punto; cambios localizados pero no parametrizado. | N17: =IF(COUNT(C17:G17)=5,"Completa","Falta")
A18: B3-3133 | B18: Compila. Pasa los 7 pasos del harness. | C18: 3 | D18: 2 | E18: 2 | F18: 2 | G18: 2 | H18: =IF(COUNT(C18:G18)=5,SUM(C18:G18),"") | I18: Compila y pasa los 7 pasos; declaraciones y tipos correctos, flanco detectado manualmente en lugar de R_TRIG. | J18: Correcta, pero el reset no tiene prioridad estructural: en el mismo ciclo de reset puede contarse un flanco; asignaciones a loteListo redundantes. | K18: Nombres descriptivos y comentarios útiles, aunque descriptivos del qué más que del porqué. | L18: Preset 12 como literal en un único punto; cambios localizados pero no parametrizado. | N18: =IF(COUNT(C18:G18)=5,"Completa","Falta")
A19: B3-3078 | B19: Compila. Pasa los 7 pasos del harness. | C19: 3 | D19: 3 | E19: 3 | F19: 2 | G19: 2 | H19: =IF(COUNT(C19:G19)=5,SUM(C19:G19),"") | I19: Compila y pasa los 7 pasos; usa R_TRIG estándar bien instanciado e INT para la cuenta: idiomático. | J19: El reset se evalúa tras el conteo y domina; salida de lote consistente, sin estados muertos. | K19: Nombres descriptivos y comentarios útiles, aunque descriptivos del qué más que del porqué. | L19: Preset 12 como literal en un único punto; cambios localizados pero no parametrizado. | N19: =IF(COUNT(C19:G19)=5,"Completa","Falta")
A20: B3-8293 | B20: Compila. Pasa los 7 pasos del harness. | C20: 3 | D20: 2 | E20: 2 | F20: 2 | G20: 2 | H20: =IF(COUNT(C20:G20)=5,SUM(C20:G20),"") | I20: Compila y pasa los 7 pasos; declaraciones y tipos correctos, flanco detectado manualmente en lugar de R_TRIG. | J20: Correcta, pero el reset no tiene prioridad estructural: en el mismo ciclo de reset puede contarse un flanco; asignaciones a loteListo redundantes. | K20: Nombres claros; comentario 'Inicialización de variables' no corresponde a la lógica que encabeza. Mezcla nombres en inglés y español. | L20: Preset 12 como literal en un único punto; cambios localizados pero no parametrizado. | N20: =IF(COUNT(C20:G20)=5,"Completa","Falta")
A21: B3-2446 | B21: Compila. Pasa los 7 pasos del harness. | C21: 3 | D21: 2 | E21: 3 | F21: 2 | G21: 2 | H21: =IF(COUNT(C21:G21)=5,SUM(C21:G21),"") | I21: Compila y pasa los 7 pasos; declaraciones y tipos correctos, flanco detectado manualmente en lugar de R_TRIG. | J21: Reset prioritario, flanco correcto y salida de lote coherente con la cuenta; sin estados muertos. | K21: Nombres descriptivos y comentarios útiles, aunque descriptivos del qué más que del porqué. | L21: Preset 12 como literal en un único punto; cambios localizados pero no parametrizado. | N21: =IF(COUNT(C21:G21)=5,"Completa","Falta")
A22: B3-6547 | B22: Compila. Pasa los 7 pasos del harness. | C22: 3 | D22: 2 | E22: 3 | F22: 3 | G22: 3 | H22: =IF(COUNT(C22:G22)=5,SUM(C22:G22),"") | I22: Compila y pasa los 7 pasos; VAR CONSTANT correcta, flanco detectado manualmente en lugar de R_TRIG. | J22: Reset prioritario y cuenta saturada en el lote: robusto, sin estados muertos ni desbordamiento. | K22: Secciones numeradas y comentarios que explican prioridad del reset y saturación del conteo. | L22: Tamaño de lote como constante declarada usada sin duplicación; ajustarlo es un cambio de una línea. | N22: =IF(COUNT(C22:G22)=5,"Completa","Falta")
A23: B3-3429 | B23: Compila. Pasa los 7 pasos del harness. | C23: 3 | D23: 2 | E23: 2 | F23: 2 | G23: 2 | H23: =IF(COUNT(C23:G23)=5,SUM(C23:G23),"") | I23: Compila y pasa los 7 pasos; declaraciones y tipos correctos, flanco detectado manualmente en lugar de R_TRIG. | J23: Correcta; loteListo se pone a FALSE en el reset y se recalcula de inmediato (redundancia sin efecto grave). | K23: Nombres claros; el comentario 'Inicialización' encabeza la detección de flanco. | L23: Preset 12 como literal en un único punto; cambios localizados pero no parametrizado. | N23: =IF(COUNT(C23:G23)=5,"Completa","Falta")
A24: B3-6741 | B24: Compila. Pasa los 7 pasos del harness. | C24: 3 | D24: 2 | E24: 3 | F24: 3 | G24: 3 | H24: =IF(COUNT(C24:G24)=5,SUM(C24:G24),"") | I24: Compila y pasa los 7 pasos; VAR CONSTANT correcta, flanco detectado manualmente en lugar de R_TRIG. | J24: Reset prioritario y cuenta saturada en el lote: robusto, sin estados muertos ni desbordamiento. | K24: Secciones numeradas y comentarios que explican prioridad del reset y saturación del conteo. | L24: Límite de lote como constante declarada usada sin duplicación; cambio de una línea. | N24: =IF(COUNT(C24:G24)=5,"Completa","Falta")
A25: B3-3465 | B25: Compila. Pasa los 7 pasos del harness. | C25: 3 | D25: 2 | E25: 3 | F25: 2 | G25: 2 | H25: =IF(COUNT(C25:G25)=5,SUM(C25:G25),"") | I25: Compila y pasa los 7 pasos; usa CTU pero con el pin RESET propio de CODESYS (IEC define R) y CV WORD asignado a INT implícitamente. | J25: CTU con reset y preset: lógica mínima y consistente, sin estados muertos. | K25: Nombres aceptables (cPiezas) y un único comentario general. | L25: Preset 12 literal en la llamada al CTU; cambio localizado. | N25: =IF(COUNT(C25:G25)=5,"Completa","Falta")
A26: B3-4741 | B26: Compila. Pasa los 7 pasos del harness. | C26: 3 | D26: 2 | E26: 3 | F26: 2 | G26: 2 | H26: =IF(COUNT(C26:G26)=5,SUM(C26:G26),"") | I26: Compila y pasa los 7 pasos; declaraciones y tipos correctos, flanco detectado manualmente en lugar de R_TRIG. | J26: Reset prioritario, flanco correcto y salida de lote coherente con la cuenta; sin estados muertos. | K26: Nombres claros; comentario 'Inicialización de variables' no corresponde a la lógica que encabeza. | L26: Preset 12 como literal en un único punto; cambios localizados pero no parametrizado. | N26: =IF(COUNT(C26:G26)=5,"Completa","Falta")
... A29: B3-2730 | B29: Compila. Pasa los 7 pasos del harness. | C29: 3 | D29: 3 | E29: 3 | F29: 3 | G29: 2 | H29: =IF(COUNT(C29:G29)=5,SUM(C29:G29),"") | I29: Compila y pasa los 7 pasos; usa R_TRIG estándar bien instanciado e INT para la cuenta: idiomático. | J29: Reset prioritario y cuenta saturada en el lote: robusto, sin estados muertos ni desbordamiento. | K29: Nombres claros y comentarios que justifican la prioridad del reset y el bloqueo del conteo con lote completo. | L29: Preset 12 como literal en un único punto; cambios localizados pero no parametrizado. | N29: =IF(COUNT(C29:G29)=5,"Completa","Falta")

Sheet B4
A1: [EVALUACIÓN IA — NO OFICIAL — solo para comparación con la evaluación humana] B4 — Inversión de giro con enclavamiento cruzado (Basico)
A2: Lee cada respuesta por su código en respuestas/Respuestas_B4.html. Rellena solo las celdas amarillas. Las azules vienen de CODESYS o se calculan solas. La fila EJEMPLO no se analiza.
A4: Código | B4: Resultado en CODESYS (automático) | C4: Corrección funcional (0–3) | D4: Cumplimiento IEC (0–3) | E4: Coherencia lógica (0–3) | F4: Claridad estructural (0–3) | G4: Mantenibilidad (0–3) | H4: Total (0–15) | I4: Justificación: corrección funcional / IEC | J4: Justificación: coherencia | K4: Justificación: claridad | L4: Justificación: mantenibilidad | M4: Observaciones | N4: Estado
A5: EJEMPLO | B5: Compila. Falla 2 de 7 pasos del harness (pasos 3,5; numerados desde 0). | C5: 1 | D5: 2 | E5: 2 | F5: 2 | G5: 1 | H5: =IF(COUNT(C5:G5)=5,SUM(C5:G5),"") | I5: Arranca y para, pero rearranca solo tras la emergencia. | J5: Sin contradicciones; transiciones completas. | K5: Nombres claros, comentarios útiles. | L5: El tiempo está escrito como literal en dos sitios. | N5: =IF(COUNT(C5:G5)=5,"Completa","Falta")
A6: B4-8136 | B6: Compila. Falla 4 de 10 pasos del harness (pasos 3,4,7,9; numerados desde 0). | C6: 0 | D6: 2 | E6: 0 | F6: 2 | G6: 2 | H6: =IF(COUNT(C6:G6)=5,SUM(C6:G6),"") | I6: Func 0: el estado 0 nunca desactiva fwd/rev, así que el paro no detiene el motor (pasos 4,7,9) y además permite invertir sin paro (paso 3). IEC 2: compila sin cambios con declaraciones correctas; máquina de estados con INT y códigos numéricos en lugar de ENUM/constantes. | J6: Las salidas solo se escriben en estados 1/2, por lo que el estado de paro es incoherente (salidas quedan activas) y existen transiciones directas 1<->2 que anulan el interlock. | K6: Nombres claros y comentarios breves de estados y variables; estructura CASE ordenada. | L6: Estados codificados 0/1/2 documentados; cambios localizados en el CASE. | N6: =IF(COUNT(C6:G6)=5,"Completa","Falta")
A7: B4-1620 | B7: Compila. Pasa los 10 pasos del harness. | C7: 3 | D7: 3 | E7: 3 | F7: 2 | G7: 2 | H7: =IF(COUNT(C7:G7)=5,SUM(C7:G7),"") | I7: Pasa todo; IEC 3: compila sin cambios; FB adecuado con IF/ELSIF y estado BOOL idiomáticos. | J7: Paro prioritario, interlock por NOT rev/NOT fwd y ELSIF que resuelve entradas simultáneas; el bloque final fwd AND rev es redundante pero inocuo. | K7: Comentarios útiles por rama y nombres claros; sin explicación más profunda del diseño. | L7: Lógica compacta sin valores mágicos; cambios localizados. | N7: =IF(COUNT(C7:G7)=5,"Completa","Falta")
A8: B4-8880 | B8: Compila. Pasa los 10 pasos del harness. | C8: 3 | D8: 2 | E8: 3 | F8: 2 | G8: 2 | H8: =IF(COUNT(C8:G8)=5,SUM(C8:G8),"") | I8: Pasa todo; IEC 2: compila sin cambios con declaraciones correctas; máquina de estados con INT y códigos numéricos en lugar de ENUM/constantes. | J8: Paro prioritario, arranque solo desde estado 0 y salidas derivadas del estado; entradas simultáneas resueltas a favor de fwd. | K8: Separa transición de estado y asignación de salidas, con comentarios útiles. | L8: Códigos de estado documentados; cambios localizados. | N8: =IF(COUNT(C8:G8)=5,"Completa","Falta")
A9: B4-9178 | B9: Compila. Pasa los 10 pasos del harness. | C9: 3 | D9: 3 | E9: 3 | F9: 3 | G9: 2 | H9: =IF(COUNT(C9:G9)=5,SUM(C9:G9),"") | I9: Pasa todo; IEC 3: compila sin cambios; FB adecuado con IF/ELSIF y estado BOOL idiomáticos. | J9: xRunning impide cualquier inversión sin paro, paro con prioridad y salidas siempre complementarias; robusto ante pulsaciones simultáneas. | K9: Cabecera que explica las reglas y secciones numeradas con comentarios del porqué del enclavamiento. | L9: Sin valores mágicos; lógica localizada y fácil de modificar. | N9: =IF(COUNT(C9:G9)=5,"Completa","Falta")
A10: B4-2076 | B10: Compila. Pasa los 10 pasos del harness. | C10: 3 | D10: 2 | E10: 2 | F10: 2 | G10: 2 | H10: =IF(COUNT(C10:G10)=5,SUM(C10:G10),"") | I10: Pasa todo; IEC 2: compila sin cambios con declaraciones correctas; máquina de estados con INT y códigos numéricos en lugar de ENUM/constantes. | J10: Coherente, pero en el estado 0 no se evalúa btnParo, de modo que con paro pulsado una orden de marcha arranca el motor; salidas con un scan de retardo. | K10: CASE ordenado con comentarios en cada transición. | L10: Códigos de estado documentados; cambios localizados. | N10: =IF(COUNT(C10:G10)=5,"Completa","Falta")
A11: B4-2916 | B11: Compila. Pasa los 10 pasos del harness. | C11: 3 | D11: 3 | E11: 3 | F11: 2 | G11: 2 | H11: =IF(COUNT(C11:G11)=5,SUM(C11:G11),"") | I11: Pasa todo; IEC 3: compila sin cambios; FB adecuado con autorretención BOOL idiomática. | J11: Autorretención con paro prioritario y enclavamiento cruzado evaluado en orden, sin coexistencia ni carrera desde el reposo. | K11: Comentarios extensos pero describen el qué más que el porqué; nombres claros. | L11: Dos ecuaciones simples sin valores mágicos. | N11: =IF(COUNT(C11:G11)=5,"Completa","Falta")
A12: B4-1844 | B12: Compila. Pasa los 10 pasos del harness. | C12: 3 | D12: 3 | E12: 3 | F12: 2 | G12: 2 | H12: =IF(COUNT(C12:G12)=5,SUM(C12:G12),"") | I12: Pasa todo; IEC 3: compila sin cambios; FB adecuado con autorretención BOOL idiomática. | J12: Autorretención con paro prioritario y enclavamiento cruzado; sin carrera porque rev usa el fwd ya actualizado. | K12: Comentario breve y útil por ecuación; nombres claros. | L12: Dos ecuaciones simples sin valores mágicos. | N12: =IF(COUNT(C12:G12)=5,"Completa","Falta")
A13: B4-9939 | B13: Compila. Falla 3 de 10 pasos del harness (pasos 2,3,6; numerados desde 0). | C13: 0 | D13: 2 | E13: 0 | F13: 2 | G13: 2 | H13: =IF(COUNT(C13:G13)=5,SUM(C13:G13),"") | I13: Func 0: estado := 0 en cada scan elimina la memoria, el motor no se enclava (paso 2) y la orden opuesta invierte sin paro (pasos 3,6). IEC 2: compila sin cambios con declaraciones correctas; máquina de estados con INT y códigos numéricos en lugar de ENUM/constantes. | J13: La reinicialización incondicional del estado anula la máquina de estados y las condiciones estado = 0 son siempre verdaderas. | K13: Bien comentado y separado en transición y salidas, aunque el comentario de inicialización enmascara el error. | L13: Códigos de estado documentados; cambios localizados. | N13: =IF(COUNT(C13:G13)=5,"Completa","Falta")
A14: B4-9793 | B14: Compila. Falla 2 de 10 pasos del harness (pasos 3,6; numerados desde 0). | C14: 1 | D14: 2 | E14: 0 | F14: 1 | G14: 1 | H14: =IF(COUNT(C14:G14)=5,SUM(C14:G14),"") | I14: Func 1: el caso nominal funciona, pero la orden opuesta invierte directamente sin paro (pasos 3,6), violando el requisito central. IEC 2: compila sin cambios con declaraciones correctas; máquina de estados con INT y códigos numéricos en lugar de ENUM/constantes. | J14: Los bloques 'Estado 1/2' se ejecutan siempre sin consultar estado, sobrescriben al primero y la variable estado se escribe pero nunca se lee. | K14: Los comentarios rotulan como estados bloques que no lo son, lo que engaña al lector. | L14: Lógica de paro triplicada y variables redundantes (estado, parado); modificar exige tocar varios bloques. | N14: =IF(COUNT(C14:G14)=5,"Completa","Falta")
A15: B4-5174 | B15: Compila. Falla 4 de 10 pasos del harness (pasos 3,4,7,9; numerados desde 0). | C15: 0 | D15: 2 | E15: 0 | F15: 2 | G15: 2 | H15: =IF(COUNT(C15:G15)=5,SUM(C15:G15),"") | I15: Func 0: el estado 0 no apaga las salidas, el paro no detiene el motor (pasos 4,7,9) y se permite inversión directa (paso 3). IEC 2: compila sin cambios con declaraciones correctas; máquina de estados con INT y códigos numéricos en lugar de ENUM/constantes. | J15: Estado de paro sin asignación de salidas y transiciones directas entre sentidos que anulan el interlock. | K15: Comentarios en cada estado y transición; nombres adecuados. | L15: Códigos de estado documentados; cambios localizados. | N15: =IF(COUNT(C15:G15)=5,"Completa","Falta")
A16: B4-1107 | B16: Compila. Pasa los 10 pasos del harness. | C16: 3 | D16: 3 | E16: 3 | F16: 2 | G16: 2 | H16: =IF(COUNT(C16:G16)=5,SUM(C16:G16),"") | I16: Pasa todo; IEC 3: compila sin cambios; FB adecuado con IF/ELSIF y estado BOOL idiomáticos. | J16: Paro prioritario, interlock cruzado y ELSIF que resuelve simultaneidad; el chequeo final es redundante pero defensivo. | K16: Comentarios útiles por rama; el rótulo 'seguridad hardware' es impreciso. | L16: Lógica compacta sin valores mágicos; cambios localizados. | N16: =IF(COUNT(C16:G16)=5,"Completa","Falta")
... A29: B4-5930 | B29: Compila. Pasa los 10 pasos del harness. | C29: 3 | D29: 2 | E29: 3 | F29: 2 | G29: 2 | H29: =IF(COUNT(C29:G29)=5,SUM(C29:G29),"") | I29: Pasa todo; IEC 2: compila sin cambios con declaraciones correctas; máquina de estados con INT y códigos numéricos en lugar de ENUM/constantes. | J29: Paro prioritario, arranque solo desde reposo y salidas derivadas del estado; la puesta a FALSE previa es redundante pero inocua. | K29: Separa transición de estado y asignación de salidas, con comentarios útiles. | L29: Códigos de estado documentados; cambios localizados. | N29: =IF(COUNT(C29:G29)=5,"Completa","Falta")

Sheet B5
A1: [EVALUACIÓN IA — NO OFICIAL — solo para comparación con la evaluación humana] B5 — Ventilador con retardo a la desconexión (Basico)
A2: Lee cada respuesta por su código en respuestas/Respuestas_B5.html. Rellena solo las celdas amarillas. Las azules vienen de CODESYS o se calculan solas. La fila EJEMPLO no se analiza.
A4: Código | B4: Resultado en CODESYS (automático) | C4: Corrección funcional (0–3) | D4: Cumplimiento IEC (0–3) | E4: Coherencia lógica (0–3) | F4: Claridad estructural (0–3) | G4: Mantenibilidad (0–3) | H4: Total (0–15) | I4: Justificación: corrección funcional / IEC | J4: Justificación: coherencia | K4: Justificación: claridad | L4: Justificación: mantenibilidad | M4: Observaciones | N4: Estado
A5: EJEMPLO | B5: Compila. Falla 2 de 7 pasos del harness (pasos 3,5; numerados desde 0). | C5: 1 | D5: 2 | E5: 2 | F5: 2 | G5: 1 | H5: =IF(COUNT(C5:G5)=5,SUM(C5:G5),"") | I5: Arranca y para, pero rearranca solo tras la emergencia. | J5: Sin contradicciones; transiciones completas. | K5: Nombres claros, comentarios útiles. | L5: El tiempo está escrito como literal en dos sitios. | N5: =IF(COUNT(C5:G5)=5,"Completa","Falta")
A6: B5-9290 | B6: Compila. Pasa los 9 pasos del harness. | C6: 3 | D6: 3 | E6: 3 | F6: 2 | G6: 2 | H6: =IF(COUNT(C6:G6)=5,SUM(C6:G6),"") | I6: Pasa todo; IEC 3: compila sin cambios y usa el TOF estándar bien instanciado con T#30S. | J6: Un TOF resuelve directamente retardo y rearme; sin estados ni condiciones redundantes. | K6: Nombres descriptivos y comentario útil del propósito del temporizador. | L6: Lógica mínima sin duplicación; el tiempo es literal en la llamada pero en un solo lugar. | N6: =IF(COUNT(C6:G6)=5,"Completa","Falta")
A7: B5-7090 | B7: Compila. Falla 1 de 9 pasos del harness (pasos 0; numerados desde 0). | C7: 2 | D7: 2 | E7: 1 | F7: 2 | G7: 2 | H7: =IF(COUNT(C7:G7)=5,SUM(C7:G7),"") | I7: Func 2: retardo y rearme correctos, pero al arrancar con el quemador apagado el ventilador marcha 30 s indebidos (paso 0), fallo menor sin riesgo. IEC 2: compila con tipos correctos, pero emula con TON+NOT lo que el TOF estándar resuelve. | J7: Lógica correcta salvo el estado inicial: el TON sin vencer al arranque activa el ventilador sin causa. | K7: Nombres y comentarios claros que explican la condición de marcha. | L7: Lógica mínima; el tiempo es literal en un solo lugar. | N7: =IF(COUNT(C7:G7)=5,"Completa","Falta")
A8: B5-4470 | B8: Compila sola, pero no se pudo simular: declara las entradas donde el harness no puede escribirlas ('quemadorOn' no es ninguna entrada de 'FB_VENTILADOR'). | C8: 0 | D8: 1 | E8: 0 | F8: 1 | G8: 1 | H8: =IF(COUNT(C8:G8)=5,SUM(C8:G8),"") | I8: Func 0: el TON se llama con IN := FALSE al inicio de cada scan, por lo que nunca vence y el ventilador no se detiene; además, la entrada y la salida están en VAR y el FB no se puede usar. IEC 1: compila, pero requiere corregir la declaración de la interfaz (VAR_INPUT/VAR_OUTPUT). | J8: El reinicio incondicional del temporizador en cada scan contradice la rama que lo arranca; el post-enfriamiento nunca termina. | K8: Comentarios abundantes, pero rotulan como entrada/salida variables internas, sin separación de E/S. | L8: Tres llamadas a la misma instancia y una interfaz mal declarada obligan a reescribir. | N8: =IF(COUNT(C8:G8)=5,"Completa","Falta")
A9: B5-6632 | B9: Compila. Falla 5 de 9 pasos del harness (pasos 2,3,5,7,8; numerados desde 0). | C9: 0 | D9: 2 | E9: 0 | F9: 2 | G9: 2 | H9: =IF(COUNT(C9:G9)=5,SUM(C9:G9),"") | I9: Func 0: lógica invertida; el ventilador se apaga al apagar el quemador y se enciende permanentemente al vencer el TON (falla 2,3,5,7,8). IEC 2: compila, declaraciones correctas, sin usar el TOF que corresponde. | J9: Usa tRetraso.Q (temporizador vencido) como condición de marcha, contradiciendo la intención declarada. | K9: Nombres y comentarios claros, aunque el comentario describe un comportamiento que el código no tiene. | L9: Lógica mínima; el tiempo es literal en un solo lugar. | N9: =IF(COUNT(C9:G9)=5,"Completa","Falta")
A10: B5-4246 | B10: Compila. Falla 1 de 9 pasos del harness (pasos 0; numerados desde 0). | C10: 2 | D10: 2 | E10: 1 | F10: 2 | G10: 2 | H10: =IF(COUNT(C10:G10)=5,SUM(C10:G10),"") | I10: Func 2: retardo y rearme correctos, pero al arrancar con el quemador apagado el ventilador marcha 30 s indebidos (paso 0), fallo menor sin riesgo. IEC 2: compila con tipos correctos, pero emula con TON+NOT lo que el TOF estándar resuelve. | J10: Lógica correcta salvo el estado inicial: el TON sin vencer al arranque activa el ventilador sin causa. | K10: Cabecera con la lógica y comentarios en cada parámetro; nombres claros. | L10: Lógica mínima; el tiempo es literal en un solo lugar. | N10: =IF(COUNT(C10:G10)=5,"Completa","Falta")
A11: B5-2235 | B11: Compila. Falla 1 de 9 pasos del harness (pasos 0; numerados desde 0). | C11: 2 | D11: 2 | E11: 1 | F11: 2 | G11: 2 | H11: =IF(COUNT(C11:G11)=5,SUM(C11:G11),"") | I11: Func 2: retardo y rearme correctos, pero al arrancar con el quemador apagado el ventilador marcha 30 s indebidos (paso 0), fallo menor sin riesgo. IEC 2: compila con tipos correctos, pero emula con TON+NOT lo que el TOF estándar resuelve. | J11: Lógica correcta salvo el estado inicial: el TON sin vencer al arranque activa el ventilador sin causa. | K11: Cabecera con la lógica y comentarios útiles; nombres claros. | L11: Lógica mínima; el tiempo es literal en un solo lugar. | N11: =IF(COUNT(C11:G11)=5,"Completa","Falta")
A12: B5-6715 | B12: Compila. Pasa los 9 pasos del harness. | C12: 3 | D12: 3 | E12: 3 | F12: 2 | G12: 2 | H12: =IF(COUNT(C12:G12)=5,SUM(C12:G12),"") | I12: Pasa todo; IEC 3: compila sin cambios y usa el TOF estándar bien instanciado con T#30S. | J12: Un TOF resuelve directamente retardo y rearme; sin estados ni condiciones redundantes. | K12: Nombres descriptivos y comentarios que explican la semántica del TOF. | L12: Lógica mínima sin duplicación; el tiempo es literal en la llamada pero en un solo lugar. | N12: =IF(COUNT(C12:G12)=5,"Completa","Falta")
A13: B5-8536 | B13: Compila. Falla 3 de 9 pasos del harness (pasos 0,5,7; numerados desde 0). | C13: 0 | D13: 2 | E13: 0 | F13: 1 | G13: 1 | H13: =IF(COUNT(C13:G13)=5,SUM(C13:G13),"") | I13: Func 0: timerDone queda enclavado tras el primer post-enfriamiento y el temporizador no vuelve a ejecutarse, por lo que los ciclos siguientes no tienen post-enfriamiento (pasos 5,7) y además marcha 30 s al arranque (paso 0). IEC 2: compila con declaraciones correctas, sin usar el TOF estándar. | J13: La bandera timerDone nunca se restablece, lo que crea un estado muerto; la condición NOT quemadorOn es redundante. | K13: El comentario 'Inicialización del timer' rotula la lógica principal y confunde; nombres genéricos. | L13: La bandera y la llamada condicionada hacen frágil cualquier cambio. | N13: =IF(COUNT(C13:G13)=5,"Completa","Falta")
A14: B5-8802 | B14: Compila sola, pero no se pudo simular: declara las entradas donde el harness no puede escribirlas ('quemadorOn' no es ninguna entrada de 'FB_VENTILADOR'). | C14: 1 | D14: 1 | E14: 1 | F14: 1 | G14: 1 | H14: =IF(COUNT(C14:G14)=5,SUM(C14:G14),"") | I14: Func 1: la lógica TON+NOT haría el post-enfriamiento (con marcha espuria al arranque), pero quemadorOn y ventilador están en VAR, así que el FB no recibe la señal ni entrega la salida. IEC 1: compila, pero requiere corregir la interfaz a VAR_INPUT/VAR_OUTPUT. | J14: Lógica básicamente correcta, con una segunda llamada redundante al temporizador y una activación espuria al arranque. | K14: Comentarios que rotulan entrada y salida dentro de VAR; sin separación de E/S. | L14: Llamada duplicada al temporizador y una interfaz que hay que reestructurar. | N14: =IF(COUNT(C14:G14)=5,"Completa","Falta")
A15: B5-2103 | B15: Compila. Pasa los 9 pasos del harness. | C15: 3 | D15: 3 | E15: 3 | F15: 2 | G15: 2 | H15: =IF(COUNT(C15:G15)=5,SUM(C15:G15),"") | I15: Pasa todo; IEC 3: compila sin cambios y usa el TOF estándar bien instanciado con T#30S. | J15: Un TOF resuelve directamente retardo y rearme; sin estados ni condiciones redundantes. | K15: Nombres descriptivos y comentario útil del propósito del temporizador. | L15: Lógica mínima sin duplicación; el tiempo es literal en la llamada pero en un solo lugar. | N15: =IF(COUNT(C15:G15)=5,"Completa","Falta")
A16: B5-3077 | B16: Compila. Pasa los 9 pasos del harness. | C16: 3 | D16: 3 | E16: 3 | F16: 2 | G16: 2 | H16: =IF(COUNT(C16:G16)=5,SUM(C16:G16),"") | I16: Pasa todo; IEC 3: compila sin cambios y usa el TOF estándar bien instanciado con T#30S. | J16: Un TOF resuelve directamente retardo y rearme; sin estados ni condiciones redundantes. | K16: Nombres descriptivos y comentarios que explican la semántica del TOF. | L16: Lógica mínima sin duplicación; el tiempo es literal en la llamada pero en un solo lugar. | N16: =IF(COUNT(C16:G16)=5,"Completa","Falta")
... A29: B5-3623 | B29: Compila. Falla 3 de 9 pasos del harness (pasos 2,5,7; numerados desde 0). | C29: 0 | D29: 2 | E29: 0 | F29: 1 | G29: 1 | H29: =IF(COUNT(C29:G29)=5,SUM(C29:G29),"") | I29: Func 0: el TON se reinicia en cada scan mientras no vence, de modo que nunca vence, y ventilador := timer.Q apaga el ventilador al apagar el quemador (pasos 2,5,7). IEC 2: compila, pero llama hasta tres veces por scan a la misma instancia. | J29: El reinicio condicional del temporizador y la lógica de salida invertida se contradicen; timerDone declarada sin usar. | K29: 'Inicialización del timer' rotula una lógica que no inicializa y los comentarios no corresponden al comportamiento real. | L29: Llamadas múltiples a la misma instancia y una variable sin uso hacen frágil cualquier cambio. | N29: =IF(COUNT(C29:G29)=5,"Completa","Falta")

Sheet B6
A1: [EVALUACIÓN IA — NO OFICIAL — solo para comparación con la evaluación humana] B6 — Baliza intermitente (Basico)
A2: Lee cada respuesta por su código en respuestas/Respuestas_B6.html. Rellena solo las celdas amarillas. Las azules vienen de CODESYS o se calculan solas. La fila EJEMPLO no se analiza.
A4: Código | B4: Resultado en CODESYS (automático) | C4: Corrección funcional (0–3) | D4: Cumplimiento IEC (0–3) | E4: Coherencia lógica (0–3) | F4: Claridad estructural (0–3) | G4: Mantenibilidad (0–3) | H4: Total (0–15) | I4: Justificación: corrección funcional / IEC | J4: Justificación: coherencia | K4: Justificación: claridad | L4: Justificación: mantenibilidad | M4: Observaciones | N4: Estado
A5: EJEMPLO | B5: Compila. Falla 2 de 7 pasos del harness (pasos 3,5; numerados desde 0). | C5: 1 | D5: 2 | E5: 2 | F5: 2 | G5: 1 | H5: =IF(COUNT(C5:G5)=5,SUM(C5:G5),"") | I5: Arranca y para, pero rearranca solo tras la emergencia. | J5: Sin contradicciones; transiciones completas. | K5: Nombres claros, comentarios útiles. | L5: El tiempo está escrito como literal en dos sitios. | N5: =IF(COUNT(C5:G5)=5,"Completa","Falta")
A6: B6-4934 | B6: Compila. Falla 1 de 3 pasos del harness (pasos 1; numerados desde 0). | C6: 0 | D6: 2 | E6: 0 | F6: 1 | G6: 1 | H6: =IF(COUNT(C6:G6)=5,SUM(C6:G6),"") | I6: Func 0: la llamada inicial con IN := estado_parpadeo = FALSE reinicia el TON en cada scan, así que nunca vence y la lámpara no parpadea (paso 1). IEC 2: compila, pero con tres llamadas por scan a la misma instancia. | J6: La primera llamada con IN := estado_parpadeo (FALSE) reinicia el TON en cada scan y contradice la llamada siguiente; el temporizador nunca vence. | K6: El comentario 'Inicialización del temporizador' rotula una llamada que no inicializa; por lo demás está comentado. | L6: Tres llamadas a la misma instancia acopladas entre sí; cualquier cambio es frágil. | N6: =IF(COUNT(C6:G6)=5,"Completa","Falta")
A7: B6-2374 | B7: Compila. Falla 1 de 3 pasos del harness (pasos 1; numerados desde 0). | C7: 0 | D7: 2 | E7: 0 | F7: 1 | G7: 1 | H7: =IF(COUNT(C7:G7)=5,SUM(C7:G7),"") | I7: Func 0: la llamada inicial con IN := estado_parpadeo = FALSE reinicia el TON en cada scan; el temporizador no vence y no hay parpadeo (paso 1). IEC 2: compila, pero con múltiples llamadas por scan a la misma instancia. | J7: La primera llamada con IN := estado_parpadeo (FALSE) reinicia el TON en cada scan y contradice la llamada siguiente; el temporizador nunca vence. | K7: El comentario 'Inicialización del temporizador' rotula una llamada que no inicializa; comentarios por línea. | L7: Varias llamadas acopladas a la misma instancia; cambios frágiles. | N7: =IF(COUNT(C7:G7)=5,"Completa","Falta")
A8: B6-5301 | B8: Compila. Pasa los 3 pasos del harness. | C8: 3 | D8: 2 | E8: 2 | F8: 2 | G8: 1 | H8: =IF(COUNT(C8:G8)=5,SUM(C8:G8),"") | I8: Pasa todo; IEC 2: compila con tipos correctos, pero llama varias veces por scan a tOn/tOff y repite PT. | J8: Funciona sin contradicciones, pero parpadeo queda casi siempre TRUE y la condición de arranque es redundante; mecanismo innecesariamente enrevesado. | K8: Comentarios por bloque y nombres adecuados, aunque la lógica real es más difícil de seguir de lo que sugieren. | L8: T#1S repetido seis veces y llamadas duplicadas; modificar el ciclo exige varias ediciones. | N8: =IF(COUNT(C8:G8)=5,"Completa","Falta")
A9: B6-5850 | B9: Compila. Pasa los 3 pasos del harness. | C9: 3 | D9: 3 | E9: 3 | F9: 2 | G9: 2 | H9: =IF(COUNT(C9:G9)=5,SUM(C9:G9),"") | I9: Pasa todo; IEC 3: compila sin cambios; generador clásico con dos TON estándar bien instanciados y T#1S. | J9: Dos TON acoplados forman un oscilador autónomo que se detiene y reinicia con la alarma; sin estados redundantes. | K9: Compacto, con nombres claros y comentarios útiles. | L9: Lógica mínima sin duplicación; T#1S literal en dos llamadas, cada una con un significado distinto. | N9: =IF(COUNT(C9:G9)=5,"Completa","Falta")
A10: B6-8282 | B10: Compila. Pasa los 3 pasos del harness. | C10: 3 | D10: 2 | E10: 3 | F10: 3 | G10: 1 | H10: =IF(COUNT(C10:G10)=5,SUM(C10:G10),"") | I10: Pasa todo; IEC 2: compila con tipos correctos, pero llama a cada TON varias veces por scan con PT repetido, lo que no es idiomático. | J10: Máquina de dos fases explícita con reinicio completo sin alarma; transiciones completas y salida segura. | K10: Secciones delimitadas y comentarios por fase que explican el porqué de cada reinicio. | L10: T#1S repetido en 6-8 llamadas y lógica de fases duplicada; cambiar el periodo exige varias ediciones. | N10: =IF(COUNT(C10:G10)=5,"Completa","Falta")
A11: B6-1513 | B11: Compila. Falla 1 de 3 pasos del harness (pasos 1; numerados desde 0). | C11: 0 | D11: 2 | E11: 0 | F11: 1 | G11: 1 | H11: =IF(COUNT(C11:G11)=5,SUM(C11:G11),"") | I11: Func 0: estado se invierte en cada scan, por lo que la lámpara conmuta a la frecuencia del ciclo; el TP no interviene (paso 1). IEC 2: compila con declaraciones correctas. | J11: El temporizador se ejecuta pero su salida nunca se usa; la conmutación incondicional por scan contradice el propósito. | K11: El comentario 'Inicialización del temporizador' rotula la lógica principal; nombres genéricos. | L11: Un temporizador sin efecto y la lógica de conmutación obligan a reescribir para obtener el ciclo. | N11: =IF(COUNT(C11:G11)=5,"Completa","Falta")
A12: B6-5704 | B12: Compila. Falla 1 de 3 pasos del harness (pasos 1; numerados desde 0). | C12: 0 | D12: 2 | E12: 0 | F12: 1 | G12: 2 | H12: =IF(COUNT(C12:G12)=5,SUM(C12:G12),"") | I12: Func 0: el TP con IN siempre TRUE da un único pulso de 1 s y no se redispara; la lámpara se enciende 1 s y queda apagada (paso 1). IEC 2: compila con declaraciones correctas. | J12: No hay mecanismo de oscilación: el TP nunca ve un nuevo flanco y estado es una copia redundante de Q. | K12: El comentario 'Inicialización del temporizador' rotula la lógica principal; comentarios escasos. | L12: Código corto y localizado, aunque con una variable redundante. | N12: =IF(COUNT(C12:G12)=5,"Completa","Falta")
A13: B6-2528 | B13: Compila. Pasa los 3 pasos del harness. | C13: 3 | D13: 2 | E13: 2 | F13: 2 | G13: 1 | H13: =IF(COUNT(C13:G13)=5,SUM(C13:G13),"") | I13: Pasa todo; IEC 2: compila con tipos correctos, pero llama varias veces por scan a tOn/tOff y repite PT. | J13: Funciona sin contradicciones, pero parpadeo queda casi siempre TRUE y la condición de arranque es redundante. | K13: Comentarios por bloque y nombres adecuados; la mecánica real queda poco clara. | L13: T#1S repetido seis veces y llamadas duplicadas; modificar el ciclo exige varias ediciones. | N13: =IF(COUNT(C13:G13)=5,"Completa","Falta")
A14: B6-6083 | B14: Compila. Pasa los 3 pasos del harness. | C14: 3 | D14: 2 | E14: 2 | F14: 1 | G14: 2 | H14: =IF(COUNT(C14:G14)=5,SUM(C14:G14),"") | I14: Pasa todo; IEC 2: compila, pero con un TON de marcha libre, comparación Q = FALSE y doble llamada de reinicio en el mismo scan. | J14: Funciona, pero el temporizador corre aunque no haya alarma y estado no se reinicia, así que la fase inicial es arbitraria. | K14: 'Inicialización del timer' rotula una llamada condicional y 'conteo hacia arriba' es irrelevante; nombres genéricos. | L14: Un solo tiempo literal y lógica breve; cambios localizados. | N14: =IF(COUNT(C14:G14)=5,"Completa","Falta")
A15: B6-8430 | B15: Compila. Pasa los 3 pasos del harness. | C15: 3 | D15: 2 | E15: 2 | F15: 1 | G15: 2 | H15: =IF(COUNT(C15:G15)=5,SUM(C15:G15),"") | I15: Pasa todo; IEC 2: compila, pero con un TON de marcha libre, comparación Q = FALSE y doble llamada de reinicio en el mismo scan. | J15: Funciona, pero el temporizador corre aunque no haya alarma y estado no se reinicia, así que la fase inicial es arbitraria. | K15: 'Inicialización del timer' rotula una llamada condicional; nombres genéricos (timer, estado). | L15: Un solo tiempo literal y lógica breve; cambios localizados. | N15: =IF(COUNT(C15:G15)=5,"Completa","Falta")
A16: B6-6488 | B16: Compila. Pasa los 3 pasos del harness. | C16: 3 | D16: 2 | E16: 2 | F16: 2 | G16: 2 | H16: =IF(COUNT(C16:G16)=5,SUM(C16:G16),"") | I16: Pasa todo; IEC 2: compila; usa el TON autorreiniciado, pero añade una segunda llamada de reinicio redundante a la misma instancia. | J16: Funciona; estadoParpadeo no se reinicia al retirar la alarma (la fase inicial queda arbitraria) y la llamada de reinicio es redundante. | K16: Comentarios útiles y nombres descriptivos. | L16: Un solo tiempo literal y lógica breve sin duplicación. | N16: =IF(COUNT(C16:G16)=5,"Completa","Falta")
... A29: B6-1094 | B29: Compila. Pasa los 3 pasos del harness. | C29: 3 | D29: 2 | E29: 3 | F29: 2 | G29: 2 | H29: =IF(COUNT(C29:G29)=5,SUM(C29:G29),"") | I29: Pasa todo; IEC 2: compila; usa el TON autorreiniciado, pero añade una segunda llamada de reinicio redundante a la misma instancia. | J29: TON autorreiniciado con reinicio completo del estado al retirar la alarma; la llamada de reinicio extra es inocua. | K29: Comentarios útiles y nombres descriptivos. | L29: Un solo tiempo literal y lógica breve sin duplicación. | N29: =IF(COUNT(C29:G29)=5,"Completa","Falta")

Sheet B7
A1: [EVALUACIÓN IA — NO OFICIAL — solo para comparación con la evaluación humana] B7 — Selector manual/automático (POU a elección) (Basico)
A2: Lee cada respuesta por su código en respuestas/Respuestas_B7.html. Rellena solo las celdas amarillas. Las azules vienen de CODESYS o se calculan solas. La fila EJEMPLO no se analiza.
A4: Código | B4: Resultado en CODESYS (automático) | C4: Corrección funcional (0–3) | D4: Cumplimiento IEC (0–3) | E4: Coherencia lógica (0–3) | F4: Claridad estructural (0–3) | G4: Mantenibilidad (0–3) | H4: Total (0–15) | I4: Justificación: corrección funcional / IEC | J4: Justificación: coherencia | K4: Justificación: claridad | L4: Justificación: mantenibilidad | M4: Observaciones | N4: Estado
A5: EJEMPLO | B5: Compila. Falla 2 de 7 pasos del harness (pasos 3,5; numerados desde 0). | C5: 1 | D5: 2 | E5: 2 | F5: 2 | G5: 1 | H5: =IF(COUNT(C5:G5)=5,SUM(C5:G5),"") | I5: Arranca y para, pero rearranca solo tras la emergencia. | J5: Sin contradicciones; transiciones completas. | K5: Nombres claros, comentarios útiles. | L5: El tiempo está escrito como literal en dos sitios. | N5: =IF(COUNT(C5:G5)=5,"Completa","Falta")
A6: B7-9815 | B6: Compila. Pasa los 10 pasos del harness. | C6: 3 | D6: 2 | E6: 3 | F6: 2 | G6: 3 | H6: =IF(COUNT(C6:G6)=5,SUM(C6:G6),"") | I6: IEC 2: compila; FUNCTION_BLOCK válido pero innecesario para lógica sin memoria (FUNCTION sería lo idiomático). | J6: Selección auto/manual completa para todas las combinaciones, salida asignada en cada ciclo, sin memoria ni estados muertos. | K6: Nombres descriptivos y comentarios útiles pero breves; no explican el porqué del diseño. | L6: Sin valores mágicos; POU reutilizable parametrizada por entradas, sin duplicación. | N6: =IF(COUNT(C6:G6)=5,"Completa","Falta")
A7: B7-2790 | B7: Compila. Pasa los 10 pasos del harness. | C7: 3 | D7: 2 | E7: 3 | F7: 2 | G7: 3 | H7: =IF(COUNT(C7:G7)=5,SUM(C7:G7),"") | I7: IEC 2: compila; FUNCTION_BLOCK válido pero innecesario para lógica sin memoria (FUNCTION sería lo idiomático). | J7: Selección auto/manual completa para todas las combinaciones, salida asignada en cada ciclo, sin memoria ni estados muertos. | K7: Nombres descriptivos y comentarios útiles pero breves; no explican el porqué del diseño. | L7: Sin valores mágicos; POU reutilizable parametrizada por entradas, sin duplicación. | N7: =IF(COUNT(C7:G7)=5,"Completa","Falta")
A8: B7-2011 | B8: Compila. Pasa los 10 pasos del harness. | C8: 3 | D8: 3 | E8: 3 | F8: 3 | G8: 3 | H8: =IF(COUNT(C8:G8)=5,SUM(C8:G8),"") | I8: IEC 3: FUNCTION con VAR_INPUT y retorno BOOL, POU idiomática para lógica combinacional sin memoria. | J8: Selección auto/manual completa para todas las combinaciones, salida asignada en cada ciclo, sin memoria ni estados muertos. | K8: Nombres descriptivos y comentarios que justifican el diseño (ausencia de memoria / elección de FUNCTION). | L8: Sin valores mágicos; POU reutilizable parametrizada por entradas, sin duplicación. | N8: =IF(COUNT(C8:G8)=5,"Completa","Falta")
A9: B7-9657 | B9: Compila. Pasa los 10 pasos del harness. | C9: 3 | D9: 3 | E9: 3 | F9: 2 | G9: 3 | H9: =IF(COUNT(C9:G9)=5,SUM(C9:G9),"") | I9: IEC 3: FUNCTION con VAR_INPUT y retorno BOOL, POU idiomática para lógica combinacional sin memoria. | J9: Selección auto/manual completa para todas las combinaciones, salida asignada en cada ciclo, sin memoria ni estados muertos. | K9: Nombres descriptivos y comentarios útiles pero breves; no explican el porqué del diseño. | L9: Sin valores mágicos; POU reutilizable parametrizada por entradas, sin duplicación. | N9: =IF(COUNT(C9:G9)=5,"Completa","Falta")
A10: B7-9128 | B10: Compila. Pasa los 10 pasos del harness. | C10: 3 | D10: 3 | E10: 3 | F10: 2 | G10: 3 | H10: =IF(COUNT(C10:G10)=5,SUM(C10:G10),"") | I10: IEC 3: FUNCTION con VAR_INPUT y retorno BOOL, POU idiomática para lógica combinacional sin memoria. | J10: Selección auto/manual completa para todas las combinaciones, salida asignada en cada ciclo, sin memoria ni estados muertos. | K10: Nombres descriptivos y comentarios útiles pero breves; no explican el porqué del diseño. | L10: Sin valores mágicos; POU reutilizable parametrizada por entradas, sin duplicación. | N10: =IF(COUNT(C10:G10)=5,"Completa","Falta")
A11: B7-4683 | B11: Compila. Pasa los 10 pasos del harness. | C11: 3 | D11: 2 | E11: 3 | F11: 2 | G11: 3 | H11: =IF(COUNT(C11:G11)=5,SUM(C11:G11),"") | I11: IEC 2: compila; FUNCTION_BLOCK válido pero innecesario para lógica sin memoria (FUNCTION sería lo idiomático). | J11: Selección auto/manual completa para todas las combinaciones, salida asignada en cada ciclo, sin memoria ni estados muertos. | K11: Nombres descriptivos y comentarios útiles pero breves; no explican el porqué del diseño. | L11: Sin valores mágicos; POU reutilizable parametrizada por entradas, sin duplicación. | N11: =IF(COUNT(C11:G11)=5,"Completa","Falta")
A12: B7-2454 | B12: Compila. Pasa los 10 pasos del harness. | C12: 3 | D12: 3 | E12: 3 | F12: 3 | G12: 3 | H12: =IF(COUNT(C12:G12)=5,SUM(C12:G12),"") | I12: IEC 3: FUNCTION con VAR_INPUT y retorno BOOL, POU idiomática para lógica combinacional sin memoria. | J12: Selección auto/manual completa para todas las combinaciones, salida asignada en cada ciclo, sin memoria ni estados muertos. | K12: Nombres descriptivos y comentarios que justifican el diseño (ausencia de memoria / elección de FUNCTION). | L12: Sin valores mágicos; POU reutilizable parametrizada por entradas, sin duplicación. | N12: =IF(COUNT(C12:G12)=5,"Completa","Falta")
A13: B7-5501 | B13: Compila. Pasa los 10 pasos del harness. | C13: 3 | D13: 3 | E13: 3 | F13: 3 | G13: 3 | H13: =IF(COUNT(C13:G13)=5,SUM(C13:G13),"") | I13: IEC 3: FUNCTION con VAR_INPUT y retorno BOOL, POU idiomática para lógica combinacional sin memoria. | J13: Selección auto/manual completa para todas las combinaciones, salida asignada en cada ciclo, sin memoria ni estados muertos. | K13: Nombres descriptivos y comentarios que justifican el diseño (ausencia de memoria / elección de FUNCTION). | L13: Sin valores mágicos; POU reutilizable parametrizada por entradas, sin duplicación. | N13: =IF(COUNT(C13:G13)=5,"Completa","Falta")
A14: B7-1125 | B14: Compila. Pasa los 10 pasos del harness. | C14: 3 | D14: 2 | E14: 3 | F14: 2 | G14: 3 | H14: =IF(COUNT(C14:G14)=5,SUM(C14:G14),"") | I14: IEC 2: compila; FUNCTION_BLOCK válido pero innecesario para lógica sin memoria (FUNCTION sería lo idiomático). | J14: Selección auto/manual completa para todas las combinaciones, salida asignada en cada ciclo, sin memoria ni estados muertos. | K14: Nombres descriptivos y comentarios útiles pero breves; no explican el porqué del diseño. | L14: Sin valores mágicos; POU reutilizable parametrizada por entradas, sin duplicación. | N14: =IF(COUNT(C14:G14)=5,"Completa","Falta")
A15: B7-3058 | B15: Compila. Pasa los 10 pasos del harness. | C15: 3 | D15: 3 | E15: 3 | F15: 3 | G15: 3 | H15: =IF(COUNT(C15:G15)=5,SUM(C15:G15),"") | I15: IEC 3: FUNCTION con VAR_INPUT y retorno BOOL, POU idiomática para lógica combinacional sin memoria. | J15: Selección auto/manual completa para todas las combinaciones, salida asignada en cada ciclo, sin memoria ni estados muertos. | K15: Nombres descriptivos y comentarios que justifican el diseño (ausencia de memoria / elección de FUNCTION). | L15: Sin valores mágicos; POU reutilizable parametrizada por entradas, sin duplicación. | N15: =IF(COUNT(C15:G15)=5,"Completa","Falta")
A16: B7-1392 | B16: Compila. Pasa los 10 pasos del harness. | C16: 3 | D16: 3 | E16: 3 | F16: 2 | G16: 3 | H16: =IF(COUNT(C16:G16)=5,SUM(C16:G16),"") | I16: IEC 3: FUNCTION con VAR_INPUT y retorno BOOL, POU idiomática para lógica combinacional sin memoria. | J16: Selección auto/manual completa para todas las combinaciones, salida asignada en cada ciclo, sin memoria ni estados muertos. | K16: Nombres descriptivos y comentarios útiles pero breves; no explican el porqué del diseño. | L16: Sin valores mágicos; POU reutilizable parametrizada por entradas, sin duplicación. | N16: =IF(COUNT(C16:G16)=5,"Completa","Falta")
... A29: B7-6425 | B29: Compila sola, pero no se pudo simular: declara las entradas donde el harness no puede escribirlas ('modoAuto' no es ninguna entrada de 'SELBOMBA'). | C29: 2 | D29: 2 | E29: 2 | F29: 2 | G29: 2 | H29: =IF(COUNT(C29:G29)=5,SUM(C29:G29),"") | I29: Func 2: lógica de selección correcta, pero las entradas son VAR internas del PROGRAM y no reciben señales externas; IEC 2: compila y tipos correctos, pero sin VAR_INPUT/VAR_OUTPUT, poco idiomático. | J29: Lógica sin contradicciones, pero las 'entradas' son variables locales sin fuente externa, por lo que el interfaz no es coherente con su rol. | K29: Nombres descriptivos y comentarios útiles que indican el rol de cada variable, pero sin separación E/S real (todo en VAR). | L29: Sin valores mágicos y cambios localizados, pero PROGRAM con variables internas no es reutilizable como bloque parametrizado. | N29: =IF(COUNT(C29:G29)=5,"Completa","Falta")

Sheet B8
A1: [EVALUACIÓN IA — NO OFICIAL — solo para comparación con la evaluación humana] B8 — Conteo de eventos por flanco (Basico)
A2: Lee cada respuesta por su código en respuestas/Respuestas_B8.html. Rellena solo las celdas amarillas. Las azules vienen de CODESYS o se calculan solas. La fila EJEMPLO no se analiza.
A4: Código | B4: Resultado en CODESYS (automático) | C4: Corrección funcional (0–3) | D4: Cumplimiento IEC (0–3) | E4: Coherencia lógica (0–3) | F4: Claridad estructural (0–3) | G4: Mantenibilidad (0–3) | H4: Total (0–15) | I4: Justificación: corrección funcional / IEC | J4: Justificación: coherencia | K4: Justificación: claridad | L4: Justificación: mantenibilidad | M4: Observaciones | N4: Estado
A5: EJEMPLO | B5: Compila. Falla 2 de 7 pasos del harness (pasos 3,5; numerados desde 0). | C5: 1 | D5: 2 | E5: 2 | F5: 2 | G5: 1 | H5: =IF(COUNT(C5:G5)=5,SUM(C5:G5),"") | I5: Arranca y para, pero rearranca solo tras la emergencia. | J5: Sin contradicciones; transiciones completas. | K5: Nombres claros, comentarios útiles. | L5: El tiempo está escrito como literal en dos sitios. | N5: =IF(COUNT(C5:G5)=5,"Completa","Falta")
A6: B8-2855 | B6: Compila. Pasa los 9 pasos del harness. | C6: 3 | D6: 2 | E6: 2 | F6: 2 | G6: 2 | H6: =IF(COUNT(C6:G6)=5,SUM(C6:G6),"") | I6: IEC 2: compila; declaraciones y tipos correctos, pero el flanco se detecta a mano en lugar de con R_TRIG estándar. | J6: Reset con prioridad, pero la memoria de flanco se congela durante el reset y puede generar o perder un flanco al soltarlo. | K6: Nombres descriptivos y secciones ordenadas con comentarios útiles; detección de flanco manual sin modularizar. | L6: Umbral 5 como literal en un único punto; cambio localizado pero no declarado como constante ni parámetro. | N6: =IF(COUNT(C6:G6)=5,"Completa","Falta")
A7: B8-2057 | B7: Compila. Falla 7 de 9 pasos del harness (pasos 1,2,3,4,5,6,8; numerados desde 0). | C7: 0 | D7: 2 | E7: 0 | F7: 1 | G7: 1 | H7: =IF(COUNT(C7:G7)=5,SUM(C7:G7),"") | I7: Func 0: el bloque 'inicialización' copia puertaAbierta en prev cuando prev es FALSE, anulando todo flanco; no cuenta en el caso nominal (falla 7/9 pasos). IEC 2: compila con tipos correctos y flanco manual. | J7: Condición contradictoria: el bloque inicial iguala prev a la entrada antes de comparar, por lo que el flanco nunca se detecta. | K7: Nombres claros, pero el comentario 'Inicialización de variables' describe un bloque que en realidad rompe la lógica. | L7: Umbral literal y un bloque redundante/erróneo que obliga a reestructurar la detección de flanco para corregirlo. | N7: =IF(COUNT(C7:G7)=5,"Completa","Falta")
A8: B8-3959 | B8: Compila. Pasa los 9 pasos del harness. | C8: 3 | D8: 3 | E8: 3 | F8: 2 | G8: 2 | H8: =IF(COUNT(C8:G8)=5,SUM(C8:G8),"") | I8: IEC 3: compila; usa R_TRIG estándar bien instanciado dentro de un FUNCTION_BLOCK con tipos correctos. | J8: Reset con prioridad (IF/ELSIF), flanco por R_TRIG evaluado cada ciclo y aviso derivado del contador: sin estados espurios tras reset. | K8: Nombres descriptivos y comentarios correctos, pero solo describen qué hace cada línea. | L8: Umbral 5 como literal en un único punto; cambio localizado pero no declarado como constante ni parámetro. | N8: =IF(COUNT(C8:G8)=5,"Completa","Falta")
A9: B8-6962 | B9: Compila. Pasa los 9 pasos del harness. | C9: 3 | D9: 2 | E9: 3 | F9: 2 | G9: 2 | H9: =IF(COUNT(C9:G9)=5,SUM(C9:G9),"") | I9: IEC 2: compila; declaraciones y tipos correctos, pero el flanco se detecta a mano en lugar de con R_TRIG estándar. | J9: Reset con prioridad, memoria de flanco actualizada siempre (incluso en reset) y aviso coherente con el contador; sin estados muertos. | K9: Nombres descriptivos y comentarios útiles, aunque el bloque de reset está rotulado como 'Inicialización'. | L9: Umbral 5 como literal en un único punto; cambio localizado pero no declarado como constante ni parámetro. | N9: =IF(COUNT(C9:G9)=5,"Completa","Falta")
A10: B8-4908 | B10: Compila. Pasa los 9 pasos del harness. | C10: 3 | D10: 3 | E10: 3 | F10: 3 | G10: 2 | H10: =IF(COUNT(C10:G10)=5,SUM(C10:G10),"") | I10: IEC 3: compila; usa R_TRIG estándar bien instanciado dentro de un FUNCTION_BLOCK con tipos correctos. | J10: Reset con prioridad (IF/ELSIF), flanco por R_TRIG evaluado cada ciclo y aviso derivado del contador: sin estados espurios tras reset. | K10: Uso de R_TRIG estándar como módulo y comentarios que explican el porqué (prioridad del reset, conteo solo en transición). | L10: Umbral 5 como literal en un único punto; cambio localizado pero no declarado como constante ni parámetro. | N10: =IF(COUNT(C10:G10)=5,"Completa","Falta")
A11: B8-3439 | B11: Compila. Pasa los 9 pasos del harness. | C11: 3 | D11: 2 | E11: 1 | F11: 2 | G11: 2 | H11: =IF(COUNT(C11:G11)=5,SUM(C11:G11),"") | I11: IEC 2: compila; declaraciones y tipos correctos, pero el flanco se detecta a mano en lugar de con R_TRIG estándar. | J11: El reset no excluye el conteo: pone prev:=FALSE y en el mismo ciclo cuenta si la puerta está abierta, dejando n=1 con reset activo. | K11: Nombres descriptivos y comentarios útiles, aunque el bloque de reset está rotulado como 'Inicialización'. | L11: Umbral 5 como literal en un único punto; cambio localizado pero no declarado como constante ni parámetro. | N11: =IF(COUNT(C11:G11)=5,"Completa","Falta")
A12: B8-1092 | B12: Compila. Pasa los 9 pasos del harness. | C12: 3 | D12: 2 | E12: 3 | F12: 2 | G12: 2 | H12: =IF(COUNT(C12:G12)=5,SUM(C12:G12),"") | I12: IEC 2: compila; declaraciones y tipos correctos, pero el flanco se detecta a mano en lugar de con R_TRIG estándar. | J12: Reset con prioridad, memoria de flanco actualizada siempre (incluso en reset) y aviso coherente con el contador; sin estados muertos. | K12: Nombres descriptivos y secciones ordenadas con comentarios útiles; detección de flanco manual sin modularizar. | L12: Umbral 5 como literal en un único punto; cambio localizado pero no declarado como constante ni parámetro. | N12: =IF(COUNT(C12:G12)=5,"Completa","Falta")
A13: B8-3080 | B13: Compila. Pasa los 9 pasos del harness. | C13: 3 | D13: 2 | E13: 3 | F13: 2 | G13: 2 | H13: =IF(COUNT(C13:G13)=5,SUM(C13:G13),"") | I13: IEC 2: compila; declaraciones y tipos correctos, pero el flanco se detecta a mano en lugar de con R_TRIG estándar. | J13: Reset con prioridad, memoria de flanco actualizada siempre (incluso en reset) y aviso coherente con el contador; sin estados muertos. | K13: Nombres descriptivos y comentarios útiles, aunque el bloque de reset está rotulado como 'Inicialización'. | L13: Umbral 5 como literal en un único punto; cambio localizado pero no declarado como constante ni parámetro. | N13: =IF(COUNT(C13:G13)=5,"Completa","Falta")
A14: B8-6589 | B14: Compila. Pasa los 9 pasos del harness. | C14: 3 | D14: 3 | E14: 3 | F14: 3 | G14: 2 | H14: =IF(COUNT(C14:G14)=5,SUM(C14:G14),"") | I14: IEC 3: compila; usa R_TRIG estándar bien instanciado dentro de un FUNCTION_BLOCK con tipos correctos. | J14: Reset con prioridad (IF/ELSIF), flanco por R_TRIG evaluado cada ciclo y aviso derivado del contador: sin estados espurios tras reset. | K14: Uso de R_TRIG estándar como módulo y comentarios que explican el porqué (prioridad del reset, conteo solo en transición). | L14: Umbral 5 como literal en un único punto; cambio localizado pero no declarado como constante ni parámetro. | N14: =IF(COUNT(C14:G14)=5,"Completa","Falta")
A15: B8-2238 | B15: Compila. Pasa los 9 pasos del harness. | C15: 3 | D15: 2 | E15: 2 | F15: 2 | G15: 2 | H15: =IF(COUNT(C15:G15)=5,SUM(C15:G15),"") | I15: IEC 2: compila; declaraciones y tipos correctos, pero el flanco se detecta a mano en lugar de con R_TRIG estándar. | J15: Comportamiento correcto con reset prioritario, pero prev:=FALSE en el reset es redundante (se sobrescribe al final del ciclo). | K15: Nombres descriptivos, separadores y comentarios que explican prioridad del reset y memoria de flanco; flanco manual sin modularizar. | L15: Umbral 5 como literal en un único punto; cambio localizado pero no declarado como constante ni parámetro. | N15: =IF(COUNT(C15:G15)=5,"Completa","Falta")
A16: B8-4457 | B16: Compila. Pasa los 9 pasos del harness. | C16: 3 | D16: 2 | E16: 3 | F16: 2 | G16: 2 | H16: =IF(COUNT(C16:G16)=5,SUM(C16:G16),"") | I16: IEC 2: compila; declaraciones y tipos correctos, pero el flanco se detecta a mano en lugar de con R_TRIG estándar. | J16: Reset con prioridad, memoria de flanco actualizada siempre (incluso en reset) y aviso coherente con el contador; sin estados muertos. | K16: Nombres descriptivos y secciones ordenadas con comentarios útiles; detección de flanco manual sin modularizar. | L16: Umbral 5 como literal en un único punto; cambio localizado pero no declarado como constante ni parámetro. | N16: =IF(COUNT(C16:G16)=5,"Completa","Falta")
... A29: B8-2626 | B29: Compila. Pasa los 9 pasos del harness. | C29: 3 | D29: 3 | E29: 3 | F29: 3 | G29: 2 | H29: =IF(COUNT(C29:G29)=5,SUM(C29:G29),"") | I29: IEC 3: compila; usa R_TRIG estándar bien instanciado dentro de un FUNCTION_BLOCK con tipos correctos. | J29: Reset con prioridad (IF/ELSIF), flanco por R_TRIG evaluado cada ciclo y aviso derivado del contador: sin estados espurios tras reset. | K29: Uso de R_TRIG estándar como módulo y comentarios que explican el porqué (prioridad del reset, conteo solo en transición). | L29: Umbral 5 como literal en un único punto; cambio localizado pero no declarado como constante ni parámetro. | N29: =IF(COUNT(C29:G29)=5,"Completa","Falta")

Sheet I1
A1: [EVALUACIÓN IA — NO OFICIAL — solo para comparación con la evaluación humana] I1 — Semáforo con secuencia temporizada (Intermedio)
A2: Lee cada respuesta por su código en respuestas/Respuestas_I1.html. Rellena solo las celdas amarillas. Las azules vienen de CODESYS o se calculan solas. La fila EJEMPLO no se analiza.
A4: Código | B4: Resultado en CODESYS (automático) | C4: Corrección funcional (0–3) | D4: Cumplimiento IEC (0–3) | E4: Coherencia lógica (0–3) | F4: Claridad estructural (0–3) | G4: Mantenibilidad (0–3) | H4: Total (0–15) | I4: Justificación: corrección funcional / IEC | J4: Justificación: coherencia | K4: Justificación: claridad | L4: Justificación: mantenibilidad | M4: Observaciones | N4: Estado
A5: EJEMPLO | B5: Compila. Falla 2 de 7 pasos del harness (pasos 3,5; numerados desde 0). | C5: 1 | D5: 2 | E5: 2 | F5: 2 | G5: 1 | H5: =IF(COUNT(C5:G5)=5,SUM(C5:G5),"") | I5: Arranca y para, pero rearranca solo tras la emergencia. | J5: Sin contradicciones; transiciones completas. | K5: Nombres claros, comentarios útiles. | L5: El tiempo está escrito como literal en dos sitios. | N5: =IF(COUNT(C5:G5)=5,"Completa","Falta")
A6: I1-2135 | B6: Compila. Pasa los 9 pasos del harness. | C6: 3 | D6: 3 | E6: 3 | F6: 2 | G6: 2 | H6: =IF(COUNT(C6:G6)=5,SUM(C6:G6),"") | I6: IEC: TON bien instanciados con reset explicito, tipos TIME correctos y FB adecuado. | J6: Salidas derivadas del estado (exclusivas), reinicio a verde y del parpadeo al cambiar de modo; sin estados muertos. | K6: Nombres y comentarios claros por seccion; sin modularizacion adicional. | L6: Tiempos agrupados en un solo CASE y salidas sin duplicar, aunque son literales en el codigo. | N6: =IF(COUNT(C6:G6)=5,"Completa","Falta")
A7: I1-7364 | B7: Compila. Falla 6 de 9 pasos del harness (pasos 0,2,3,6,7,8; numerados desde 0). | C7: 0 | D7: 2 | E7: 0 | F7: 1 | G7: 1 | H7: =IF(COUNT(C7:G7)=5,SUM(C7:G7),"") | I7: Falla 6 de 9 pasos incluido el reposo y la temporizacion nominal: TON nunca se reinicia y cambiar PT no reinicia la fase; compila con tipos correctos pero uso no idiomatico del TON. | J7: El TON permanece con IN siempre TRUE, el parpadeo conmuta en cada scan y el estado 0 enciende verde aunque este deshabilitado. | K7: Estructura CASE reconocible pero comentarios incorrectos ('cada segundo', 'Inicializacion del timer'). | L7: Literales repetidos y asignaciones de luces duplicadas en cada estado. | N7: =IF(COUNT(C7:G7)=5,"Completa","Falta")
A8: I1-5111 | B8: Compila. Falla 1 de 9 pasos del harness (pasos 7; numerados desde 0). | C8: 1 | D8: 2 | E8: 1 | F8: 2 | G8: 1 | H8: =IF(COUNT(C8:G8)=5,SUM(C8:G8),"") | I8: Secuencia nominal correcta pero falla el intermitente (paso 7): el TP deja el amarillo apagado solo un scan; compila, pero el TP no se usa correctamente. | J8: Secuencia y reinicio coherentes, pero la logica de relanzamiento del TP no produce el semiperiodo apagado de 1 s. | K8: Secciones comentadas y nombres descriptivos, incluido ELSE para estado invalido. | L8: Tiempos literales dispersos y bloques de salidas repetidos por estado. | N8: =IF(COUNT(C8:G8)=5,"Completa","Falta")
A9: I1-7969 | B9: Compila. Falla 7 de 9 pasos del harness (pasos 2,3,4,5,6,7,8; numerados desde 0). | C9: 0 | D9: 2 | E9: 0 | F9: 2 | G9: 1 | H9: =IF(COUNT(C9:G9)=5,SUM(C9:G9),"") | I9: Falla 7 de 9 pasos: el TP pone Q en TRUE al instante y la secuencia avanza en el primer scan; compila con tipos correctos pero TP mal empleado. | J9: Las transiciones se disparan con Q del TP al inicio del pulso y los temporizadores nunca se reinician: la secuencia no temporiza. | K9: Nombres descriptivos y comentarios breves por fase. | L9: Un TP por fase con literales y logica duplicada. | N9: =IF(COUNT(C9:G9)=5,"Completa","Falta")
A10: I1-5434 | B10: Compila. Pasa los 9 pasos del harness. | C10: 3 | D10: 3 | E10: 3 | F10: 2 | G10: 1 | H10: =IF(COUNT(C10:G10)=5,SUM(C10:G10),"") | I10: IEC: R_TRIG y TON estandar bien instanciados, autorreinicio idiomatico del parpadeo. | J10: Flanco de habilitado reinicia en verde, temporizadores reseteados en cada cambio de modo; estados completos. | K10: Comentarios utiles que explican resets y modos; estructura ordenada. | L10: Tiempos literales en cada rama y asignaciones de salidas duplicadas. | N10: =IF(COUNT(C10:G10)=5,"Completa","Falta")
A11: I1-7084 | B11: Compila. Pasa los 9 pasos del harness. | C11: 3 | D11: 3 | E11: 3 | F11: 2 | G11: 2 | H11: =IF(COUNT(C11:G11)=5,SUM(C11:G11),"") | I11: IEC: R_TRIG y TON bien instanciados, PT variable de tipo TIME. | J11: Separacion de seleccion de tiempo, transicion y salidas; parpadeo y temporizador se reinician correctamente al cambiar de modo. | K11: Codigo ordenado por secciones comentadas, aunque las declaraciones carecen de comentarios. | L11: Tiempos centralizados en un unico CASE mediante tiempoFase; transiciones y salidas separadas. | N11: =IF(COUNT(C11:G11)=5,"Completa","Falta")
A12: I1-2168 | B12: Compila. Pasa los 9 pasos del harness. | C12: 3 | D12: 3 | E12: 1 | F12: 2 | G12: 1 | H12: =IF(COUNT(C12:G12)=5,SUM(C12:G12),"") | I12: IEC: TON bien instanciados con tipos TIME correctos. | J12: tCiclo no se resetea en modo deshabilitado: al rehabilitar el TON conserva el tiempo transcurrido y acorta el primer verde. | K12: Comentarios breves por fase y nombres claros; sin modularizacion. | L12: Literales en cada rama y salidas repetidas en cada estado. | N12: =IF(COUNT(C12:G12)=5,"Completa","Falta")
A13: I1-3359 | B13: Compila. Pasa los 9 pasos del harness. | C13: 3 | D13: 3 | E13: 3 | F13: 2 | G13: 2 | H13: =IF(COUNT(C13:G13)=5,SUM(C13:G13),"") | I13: IEC: oscilador con dos TON y PT variable, construcciones estandar idiomaticas. | J13: Oscilador 1s/1s correcto, reinicio a verde al habilitar y autorreinicio del TON por transicion; sin estados muertos. | K13: Secciones comentadas; algunas variables auxiliares (tiempoActual, transicion) sin comentario. | L13: Tiempos centralizados en un solo CASE con un unico temporizador de secuencia. | N13: =IF(COUNT(C13:G13)=5,"Completa","Falta")
A14: I1-8741 | B14: Compila sola, pero no se pudo simular: declara las entradas donde el harness no puede escribirlas ('habilitado' no es ninguna entrada de 'FB_SEMAFORO'). | C14: 0 | D14: 1 | E14: 0 | F14: 1 | G14: 1 | H14: =IF(COUNT(C14:G14)=5,SUM(C14:G14),"") | I14: No simulable y, leyendo el codigo, el TON se reinicia al inicio de cada scan y nunca vence: queda fijo en verde; entradas/salidas declaradas como VAR, declaracion no conforme. | J14: La llamada inicial con IN:=FALSE en cada ciclo anula ambos temporizadores; secuencia y parpadeo muertos. | K14: Comentarios presentes, pero mezcla entradas, salidas e internas en un unico VAR. | L14: Literales repetidos por estado y logica duplicada. | N14: =IF(COUNT(C14:G14)=5,"Completa","Falta")
A15: I1-4990 | B15: Compila. Falla 1 de 9 pasos del harness (pasos 7; numerados desde 0). | C15: 1 | D15: 2 | E15: 1 | F15: 2 | G15: 1 | H15: =IF(COUNT(C15:G15)=5,SUM(C15:G15),"") | I15: Secuencia nominal correcta pero falla el intermitente (paso 7): bParpadeoOn conmuta en cada scan mientras Q del TP esta activo; uso incorrecto del TP. | J15: La conmutacion por nivel (no por flanco) del TP genera parpadeo erratico; resto de la logica coherente con ELSE para estado invalido. | K15: Secciones bien comentadas y nombres claros. | L15: Tiempos literales en cada rama y salidas duplicadas. | N15: =IF(COUNT(C15:G15)=5,"Completa","Falta")
A16: I1-8830 | B16: Compila. Pasa los 9 pasos del harness. | C16: 3 | D16: 3 | E16: 3 | F16: 2 | G16: 1 | H16: =IF(COUNT(C16:G16)=5,SUM(C16:G16),"") | I16: IEC: TON estandar bien instanciados y reseteados, tipos correctos. | J16: Reset de todos los temporizadores y del estado al cambiar de modo, ELSE ante estado invalido; salidas exclusivas. | K16: Muy bien seccionado y comentado; los comentarios describen el que mas que el porque. | L16: Tres temporizadores con logica duplicada por fase y tiempos literales. | N16: =IF(COUNT(C16:G16)=5,"Completa","Falta")
... A22: I1-8541 | B22: Compila. Pasa los 9 pasos del harness. | C22: 3 | D22: 3 | E22: 1 | F22: 2 | G22: 1 | H22: =IF(COUNT(C22:G22)=5,SUM(C22:G22),"") | I22: IEC: TON bien instanciados y tipos TIME correctos. | J22: tCiclo no se resetea al deshabilitar: al rehabilitar el TON conserva el tiempo y acorta la primera fase verde. | K22: Comentarios breves por fase y nombres claros. | L22: Literales en cada rama y salidas repetidas. | N22: =IF(COUNT(C22:G22)=5,"Completa","Falta")
A23: I1-4916 | B23: No compila (20 errores). | C23: 0 | D23: 0 | E23: 0 | F23: 1 | G23: 1 | H23: =IF(COUNT(C23:G23)=5,SUM(C23:G23),"") | J23: El TON se reinicia con IN:=FALSE en cada scan y nunca vence; ademas un unico temporizador se comparte entre secuencia e intermitente. | K23: Nombres aceptables y comentarios, pero el de 'inicializacion' es enganoso. | L23: Literales repetidos y bloques duplicados por estado. | N23: =IF(COUNT(C23:G23)=5,"Completa","Falta")
A24: I1-5056 | B24: Compila. Falla 1 de 9 pasos del harness (pasos 7; numerados desde 0). | C24: 1 | D24: 2 | E24: 1 | F24: 2 | G24: 1 | H24: =IF(COUNT(C24:G24)=5,SUM(C24:G24),"") | I24: Secuencia nominal correcta pero falla el intermitente (paso 7): luzA sigue a Q de un TON que nunca se reinicia y queda fijo encendido; uso incorrecto del TON. | J24: El temporizador de parpadeo no se rearma: el amarillo queda encendido fijo tras 1 s; resto coherente. | K24: Comentarios por fase claros, aunque 'Inicializacion de variables' no describe el bloque. | L24: Tiempos literales y salidas duplicadas por estado. | N24: =IF(COUNT(C24:G24)=5,"Completa","Falta")
A25: I1-1955 | B25: Compila. Falla 7 de 9 pasos del harness (pasos 2,3,4,5,6,7,8; numerados desde 0). | C25: 0 | D25: 2 | E25: 0 | F25: 2 | G25: 1 | H25: =IF(COUNT(C25:G25)=5,SUM(C25:G25),"") | I25: Falla 7 de 9 pasos: el TP activa Q al instante y la secuencia avanza en el primer scan; TP mal empleado. | J25: Transiciones con Q del TP al inicio y temporizadores nunca reiniciados; la rama ELSE del intermitente es redundante. | K25: Nombres descriptivos y comentarios por estado. | L25: Un TP por fase con literales y logica duplicada. | N25: =IF(COUNT(C25:G25)=5,"Completa","Falta")
A26: I1-8761 | B26: Compila. Falla 6 de 9 pasos del harness (pasos 0,2,3,5,6,7; numerados desde 0). | C26: 0 | D26: 2 | E26: 0 | F26: 1 | G26: 2 | H26: =IF(COUNT(C26:G26)=5,SUM(C26:G26),"") | I26: Falla 6 de 9 pasos incluidos reposo y nominal: el TON se resetea con IN:=FALSE en cada scan y nunca vence; tipos correctos pero uso no idiomatico. | J26: Reset incondicional del temporizador bloquea la secuencia; verde encendido aun deshabilitado y parpadeo por contador de scans. | K26: Comentarios presentes pero incorrectos respecto al comportamiento ('Inicializacion del timer'). | L26: Tiempos declarados como variables TIME con valor inicial, cambios localizados. | N26: =IF(COUNT(C26:G26)=5,"Completa","Falta")
A27: I1-4511 | B27: Compila. Pasa los 9 pasos del harness. | C27: 3 | D27: 3 | E27: 3 | F27: 2 | G27: 1 | H27: =IF(COUNT(C27:G27)=5,SUM(C27:G27),"") | I27: IEC: TON bien instanciados y reseteados, ELSE en CASE. | J27: Estado intermitente explicito con transiciones de entrada y salida que resetean temporizadores; salidas exclusivas. | K27: Muy bien seccionado, comentarios explican el motivo de los reinicios. | L27: Un TON por fase con literales repetidos y codigo duplicado. | N27: =IF(COUNT(C27:G27)=5,"Completa","Falta")
A28: I1-4945 | B28: No compila (20 errores). | C28: 0 | D28: 0 | E28: 1 | F28: 1 | G28: 1 | H28: =IF(COUNT(C28:G28)=5,SUM(C28:G28),"") | J28: Secuencia coherente, pero el parpadeo sigue a Q de un TON que nunca se rearma y el estado no se reinicia a verde al deshabilitar. | K28: Comentarios presentes pero 'Inicializacion' es enganoso; estructura basica. | L28: Literales repetidos y un unico temporizador compartido entre modos. | N28: =IF(COUNT(C28:G28)=5,"Completa","Falta")
A29: I1-3124 | B29: Compila. Falla 1 de 9 pasos del harness (pasos 7; numerados desde 0). | C29: 1 | D29: 2 | E29: 1 | F29: 2 | G29: 1 | H29: =IF(COUNT(C29:G29)=5,SUM(C29:G29),"") | I29: Secuencia nominal correcta pero falla el intermitente (paso 7): el TP con IN:=NOT Q deja el amarillo apagado solo un scan; uso incorrecto del TP. | J29: Deteccion de flanco manual correcta y reinicio en verde, pero el generador de parpadeo no produce 1 s apagado. | K29: Secciones comentadas y nombres claros, incluido el porque del flanco. | L29: Tiempos literales dispersos y salidas duplicadas por estado. | N29: =IF(COUNT(C29:G29)=5,"Completa","Falta")

Sheet I2
A1: [EVALUACIÓN IA — NO OFICIAL — solo para comparación con la evaluación humana] I2 — FSM de llenado multietapa (Intermedio)
A2: Lee cada respuesta por su código en respuestas/Respuestas_I2.html. Rellena solo las celdas amarillas. Las azules vienen de CODESYS o se calculan solas. La fila EJEMPLO no se analiza.
A4: Código | B4: Resultado en CODESYS (automático) | C4: Corrección funcional (0–3) | D4: Cumplimiento IEC (0–3) | E4: Coherencia lógica (0–3) | F4: Claridad estructural (0–3) | G4: Mantenibilidad (0–3) | H4: Total (0–15) | I4: Justificación: corrección funcional / IEC | J4: Justificación: coherencia | K4: Justificación: claridad | L4: Justificación: mantenibilidad | M4: Observaciones | N4: Estado
A5: EJEMPLO | B5: Compila. Falla 2 de 7 pasos del harness (pasos 3,5; numerados desde 0). | C5: 1 | D5: 2 | E5: 2 | F5: 2 | G5: 1 | H5: =IF(COUNT(C5:G5)=5,SUM(C5:G5),"") | I5: Arranca y para, pero rearranca solo tras la emergencia. | J5: Sin contradicciones; transiciones completas. | K5: Nombres claros, comentarios útiles. | L5: El tiempo está escrito como literal en dos sitios. | N5: =IF(COUNT(C5:G5)=5,"Completa","Falta")
A6: I2-2212 | B6: Compila. Falla 4 de 12 pasos del harness (pasos 4,5,6,9; numerados desde 0). | C6: 0 | D6: 2 | E6: 0 | F6: 2 | G6: 1 | H6: =IF(COUNT(C6:G6)=5,SUM(C6:G6),"") | I6: Falla la mezcla nominal (pasos 4,5,6,9): el TON solo se llama en la transicion y nunca vuelve a evaluarse; compila con tipos correctos pero uso no idiomatico del TON. | J6: La etapa de mezcla es un estado muerto porque el temporizador no se actualiza; en reposo no se fuerzan las salidas. | K6: Nombres descriptivos y comentarios por etapa. | L6: Salidas asignadas de forma dispersa y tiempo literal dentro de la transicion. | N6: =IF(COUNT(C6:G6)=5,"Completa","Falta")
A7: I2-8131 | B7: Compila. Pasa los 12 pasos del harness. | C7: 3 | D7: 3 | E7: 3 | F7: 2 | G7: 1 | H7: =IF(COUNT(C7:G7)=5,SUM(C7:G7),"") | I7: IEC: TON bien instanciado y reiniciado, CASE con ELSE. | J7: Paro con prioridad, reset del TON y ELSE a reposo seguro; todas las salidas definidas en cada etapa. | K7: Secciones delimitadas y comentarios por etapa, incluido el significado de cada estado. | L7: T#60S repetido en cuatro llamadas y bloque de salidas duplicado en cada etapa. | N7: =IF(COUNT(C7:G7)=5,"Completa","Falta")
A8: I2-4370 | B8: Compila. Falla 2 de 12 pasos del harness (pasos 2,3; numerados desde 0). | C8: 0 | D8: 2 | E8: 0 | F8: 2 | G8: 1 | H8: =IF(COUNT(C8:G8)=5,SUM(C8:G8),"") | I8: Falla la mezcla (pasos 2,3): el TP se llama una sola vez, Q queda activo y la etapa se salta; TP mal empleado. | J8: El TP no se reevalua ni se rearma: la mezcla dura cero y el paro no impide ejecutar el CASE en el mismo scan. | K8: Comentarios breves y nombres claros por estado. | L8: Salidas activadas en transiciones dispersas y tiempo literal. | N8: =IF(COUNT(C8:G8)=5,"Completa","Falta")
A9: I2-4324 | B9: Compila. Falla 7 de 12 pasos del harness (pasos 2,3,4,5,6,9,11; numerados desde 0). | C9: 0 | D9: 2 | E9: 0 | F9: 1 | G9: 1 | H9: =IF(COUNT(C9:G9)=5,SUM(C9:G9),"") | I9: Falla 7 de 12 pasos: no hay maquina de estados real, nivelAlto o tMezcla disparan etapas sin condicion de estado; TP mal empleado. | J9: Bloques IF independientes del estado: transiciones contradictorias (nivelAlto en reposo arranca la mezcla). | K9: Comentarios rotulan como estados bloques que no lo son, induciendo a error. | L9: Logica no separable por etapas; cualquier cambio exige reescribir. | N9: =IF(COUNT(C9:G9)=5,"Completa","Falta")
A10: I2-4540 | B10: Compila. Falla 4 de 12 pasos del harness (pasos 2,3,4,9; numerados desde 0). | C10: 0 | D10: 2 | E10: 0 | F10: 1 | G10: 1 | H10: =IF(COUNT(C10:G10)=5,SUM(C10:G10),"") | I10: Falla 4 de 12 pasos: soltar btnInicio fuerza el reposo y aborta la secuencia; TON llamado solo dentro de la mezcla. | J10: IF NOT btnInicio THEN estado:=0 contradice el funcionamiento por pulsador e impide operar. | K10: Comentarios presentes pero el de 'Inicializacion del bloque' describe mal la logica. | L10: Salidas dispersas y tiempo literal. | N10: =IF(COUNT(C10:G10)=5,"Completa","Falta")
A11: I2-3499 | B11: Compila. Pasa los 12 pasos del harness. | C11: 3 | D11: 3 | E11: 3 | F11: 2 | G11: 1 | H11: =IF(COUNT(C11:G11)=5,SUM(C11:G11),"") | I11: IEC: TON bien instanciado y reseteado, CASE con ELSE. | J11: Paro con prioridad, reset del TON y ELSE a reposo seguro; todas las salidas definidas en cada etapa. | K11: Comentarios por etapa que describen su condicion de salida; nombres claros. | L11: T#60S repetido y salidas duplicadas en cada etapa. | N11: =IF(COUNT(C11:G11)=5,"Completa","Falta")
A12: I2-9002 | B12: Compila. Pasa los 12 pasos del harness. | C12: 3 | D12: 3 | E12: 2 | F12: 2 | G12: 2 | H12: =IF(COUNT(C12:G12)=5,SUM(C12:G12),"") | I12: IEC: TON llamado una vez por scan con IN derivado del estado, idiomatico. | J12: Paro y salidas en reposo correctos, pero con paro mantenido y btnInicio activo el estado oscila a llenado en cada scan. | K12: Codigo bien comentado; declaraciones de E/S sin comentarios. | L12: Temporizador y su tiempo en un unico punto; transiciones separadas. | N12: =IF(COUNT(C12:G12)=5,"Completa","Falta")
A13: I2-4041 | B13: Compila. Pasa los 12 pasos del harness. | C13: 3 | D13: 3 | E13: 3 | F13: 2 | G13: 1 | H13: =IF(COUNT(C13:G13)=5,SUM(C13:G13),"") | I13: IEC: TON bien instanciado y reseteado, CASE con ELSE. | J13: Paro con prioridad, reset del TON y ELSE a reposo seguro; todas las salidas definidas en cada etapa. | K13: Comentarios por etapa claros y nombres descriptivos. | L13: T#60S repetido y salidas duplicadas por etapa. | N13: =IF(COUNT(C13:G13)=5,"Completa","Falta")
A14: I2-9360 | B14: Compila. Pasa los 12 pasos del harness. | C14: 3 | D14: 3 | E14: 3 | F14: 2 | G14: 2 | H14: =IF(COUNT(C14:G14)=5,SUM(C14:G14),"") | I14: IEC: TON con IN derivado del estado y salidas booleanas por comparacion, idiomatico. | J14: Paro prioritario que bloquea el arranque simultaneo; salidas derivadas del estado, imposibles de solapar. | K14: Secciones ordenadas y comentadas; sin modularizacion adicional. | L14: Transiciones, temporizador y salidas separados; tiempo en un unico punto. | N14: =IF(COUNT(C14:G14)=5,"Completa","Falta")
A15: I2-4337 | B15: Compila. Falla 2 de 12 pasos del harness (pasos 2,3; numerados desde 0). | C15: 0 | D15: 2 | E15: 0 | F15: 2 | G15: 1 | H15: =IF(COUNT(C15:G15)=5,SUM(C15:G15),"") | I15: Falla la mezcla (pasos 2,3): el TP se llama una sola vez y su Q activo salta la etapa; TP mal empleado. | J15: Temporizador no reevaluado ni rearmado: mezcla de duracion nula; paro no bloquea el CASE del mismo scan. | K15: Comentarios breves y nombres claros. | L15: Salidas activadas en transiciones dispersas y tiempo literal. | N15: =IF(COUNT(C15:G15)=5,"Completa","Falta")
A16: I2-3432 | B16: Compila sola, pero no se pudo simular: declara las entradas donde el harness no puede escribirlas ('nivelAlto' no es ninguna entrada de 'FB_LLENADO'). | C16: 0 | D16: 1 | E16: 0 | F16: 1 | G16: 1 | H16: =IF(COUNT(C16:G16)=5,SUM(C16:G16),"") | I16: No simulable y, leyendo el codigo, el TON se resetea en cada scan y no se evalua en la mezcla: queda atascado mezclando; E/S declaradas como VAR. | J16: La llamada inicial con IN:=FALSE anula el temporizador: estado de mezcla muerto. | K16: Comentarios presentes pero entradas, salidas e internas mezcladas en un unico VAR. | L16: Tiempo literal y salidas dispersas. | N16: =IF(COUNT(C16:G16)=5,"Completa","Falta")
A17: I2-3102 | B17: No compila (2 errores). | C17: 0 | D17: 0 | E17: 3 | F17: 2 | G17: 1 | H17: =IF(COUNT(C17:G17)=5,SUM(C17:G17),"") | J17: Paro con RETURN y reset, flanco de inicio con R_TRIG, ELSE seguro; logica robusta salvo el error de sintaxis. | K17: Muy bien seccionado y comentado, incluye el tipo de senal de cada boton. | L17: T#60S repetido en varias llamadas y salidas duplicadas en cada etapa. | N17: =IF(COUNT(C17:G17)=5,"Completa","Falta")
A18: I2-7023 | B18: Compila. Pasa los 12 pasos del harness. | C18: 3 | D18: 3 | E18: 3 | F18: 2 | G18: 2 | H18: =IF(COUNT(C18:G18)=5,SUM(C18:G18),"") | I18: IEC: TON con IN derivado del estado y salidas por comparacion, idiomatico. | J18: El paro excluye la ejecucion del CASE (bloquea arranque simultaneo) y las salidas se derivan del estado. | K18: Codigo comentado y ordenado; declaraciones de E/S sin comentarios. | L18: Transiciones, temporizador y salidas separados; tiempo en un solo punto. | N18: =IF(COUNT(C18:G18)=5,"Completa","Falta")
A19: I2-4582 | B19: Compila. Pasa los 12 pasos del harness. | C19: 3 | D19: 3 | E19: 3 | F19: 2 | G19: 1 | H19: =IF(COUNT(C19:G19)=5,SUM(C19:G19),"") | I19: IEC: TON bien instanciado y reseteado, CASE con ELSE. | J19: Paro con prioridad, reset del TON y ELSE a reposo seguro; todas las salidas definidas en cada etapa. | K19: Comentarios por etapa claros y nombres descriptivos. | L19: T#60S repetido y salidas duplicadas por etapa. | N19: =IF(COUNT(C19:G19)=5,"Completa","Falta")
A20: I2-9998 | B20: Compila. Pasa los 12 pasos del harness. | C20: 3 | D20: 3 | E20: 3 | F20: 2 | G20: 2 | H20: =IF(COUNT(C20:G20)=5,SUM(C20:G20),"") | I20: IEC: TON con IN derivado del estado, salidas por comparacion, idiomatico. | J20: Paro prioritario con bloqueo del arranque, salidas exclusivas derivadas del estado. | K20: Secciones comentadas y nombres claros. | L20: Transiciones, temporizador y salidas separados; tiempo en un unico punto. | N20: =IF(COUNT(C20:G20)=5,"Completa","Falta")
A21: I2-3377 | B21: Compila sola, pero no se pudo simular: declara las entradas donde el harness no puede escribirlas ('nivelAlto' no es ninguna entrada de 'FB_LLENADO'). | C21: 1 | D21: 1 | E21: 1 | F21: 1 | G21: 1 | H21: =IF(COUNT(C21:G21)=5,SUM(C21:G21),"") | I21: No simulable; leyendo el codigo el primer ciclo funciona, pero el TON nunca se resetea y en el siguiente ciclo o tras un paro la mezcla se salta; E/S declaradas como VAR. | J21: El temporizador no se reinicia ni al terminar ni con el paro, lo que acorta o anula mezclas posteriores. | K21: E/S mezcladas en VAR y comentario 'Inicializacion' que no corresponde. | L21: Tiempo literal y salidas dispersas por etapa. | N21: =IF(COUNT(C21:G21)=5,"Completa","Falta")
A22: I2-1039 | B22: Compila. Falla 5 de 12 pasos del harness (pasos 2,3,4,5,9; numerados desde 0). | C22: 0 | D22: 2 | E22: 0 | F22: 2 | G22: 1 | H22: =IF(COUNT(C22:G22)=5,SUM(C22:G22),"") | I22: Falla 5 de 12 pasos: el CASE solo se ejecuta con btnInicio pulsado y la mezcla usa NOT Q de un TON llamado una vez; uso no idiomatico. | J22: Logica contradictoria: la secuencia depende de mantener el pulsador y la mezcla pasa a descarga de inmediato. | K22: Nombres y comentarios por estado correctos. | L22: Tiempo literal y salidas dispersas. | N22: =IF(COUNT(C22:G22)=5,"Completa","Falta")
A23: I2-2195 | B23: Compila. Falla 3 de 12 pasos del harness (pasos 4,5,6; numerados desde 0). | C23: 0 | D23: 2 | E23: 0 | F23: 1 | G23: 1 | H23: =IF(COUNT(C23:G23)=5,SUM(C23:G23),"") | I23: Falla la mezcla nominal (pasos 4,5,6): el TON solo se llama en la transicion y nunca vuelve a evaluarse; uso no idiomatico. | J23: La etapa de mezcla es un estado muerto por temporizador no actualizado. | K23: E/S declaradas en una linea sin comentarios y comentarios minimos. | L23: Tiempo literal y salidas asignadas en transiciones dispersas. | N23: =IF(COUNT(C23:G23)=5,"Completa","Falta")
A24: I2-5294 | B24: Compila. Pasa los 12 pasos del harness. | C24: 3 | D24: 3 | E24: 3 | F24: 2 | G24: 2 | H24: =IF(COUNT(C24:G24)=5,SUM(C24:G24),"") | I24: IEC: TON con IN derivado del estado, salidas por comparacion, idiomatico. | J24: Paro prioritario con bloqueo del arranque y salidas exclusivas derivadas del estado. | K24: Secciones ordenadas y comentadas. | L24: Transiciones, temporizador y salidas separados; tiempo en un unico punto. | N24: =IF(COUNT(C24:G24)=5,"Completa","Falta")
A25: I2-5330 | B25: Compila. Pasa los 12 pasos del harness. | C25: 3 | D25: 3 | E25: 3 | F25: 2 | G25: 2 | H25: =IF(COUNT(C25:G25)=5,SUM(C25:G25),"") | I25: IEC: TON con IN derivado del estado y ELSE en CASE, idiomatico. | J25: Paro prioritario con bloqueo del arranque, ELSE ante estados invalidos y salidas exclusivas. | K25: Secciones numeradas con comentarios que explican el porque del estado seguro. | L25: Transiciones, salidas y temporizador separados; tiempo en un solo punto. | N25: =IF(COUNT(C25:G25)=5,"Completa","Falta")
A26: I2-9686 | B26: Compila. Falla 3 de 12 pasos del harness (pasos 4,5,6; numerados desde 0). | C26: 0 | D26: 2 | E26: 0 | F26: 1 | G26: 1 | H26: =IF(COUNT(C26:G26)=5,SUM(C26:G26),"") | I26: Falla 3 de 12 pasos: el TON se resetea con IN:=FALSE al inicio de cada scan y nunca vence; uso no idiomatico. | J26: Reset incondicional del temporizador deja la mezcla como estado muerto. | K26: Comentarios presentes pero 'Inicializacion del timer' es enganoso. | L26: Tiempo literal y salidas dispersas por etapa. | N26: =IF(COUNT(C26:G26)=5,"Completa","Falta")
A27: I2-7180 | B27: Compila. Falla 3 de 12 pasos del harness (pasos 4,5,6; numerados desde 0). | C27: 0 | D27: 2 | E27: 0 | F27: 1 | G27: 2 | H27: =IF(COUNT(C27:G27)=5,SUM(C27:G27),"") | I27: Falla 3 de 12 pasos: el TON se resetea en cada scan y nunca vence; uso no idiomatico. | J27: Reset incondicional del temporizador bloquea la mezcla; paro repetido en cada estado. | K27: Comentario de inicializacion enganoso y paro duplicado en cada rama. | L27: Tiempo declarado como variable TIME, aunque el paro esta duplicado por estado. | N27: =IF(COUNT(C27:G27)=5,"Completa","Falta")
A28: I2-8425 | B28: Compila. Pasa los 12 pasos del harness. | C28: 3 | D28: 3 | E28: 3 | F28: 2 | G28: 1 | H28: =IF(COUNT(C28:G28)=5,SUM(C28:G28),"") | I28: IEC: TON bien instanciado y reseteado, CASE con ELSE. | J28: Paro con prioridad, reset del TON y ELSE a reposo seguro; todas las salidas definidas en cada etapa. | K28: Bien seccionado con comentarios de transicion. | L28: T#60S repetido en varias llamadas y salidas duplicadas por etapa. | N28: =IF(COUNT(C28:G28)=5,"Completa","Falta")
A29: I2-6794 | B29: Compila. Falla 3 de 12 pasos del harness (pasos 2,3,9; numerados desde 0). | C29: 0 | D29: 2 | E29: 0 | F29: 2 | G29: 1 | H29: =IF(COUNT(C29:G29)=5,SUM(C29:G29),"") | I29: Falla la mezcla (pasos 2,3,9): el TON se llama una vez y NOT Q pasa a descarga de inmediato; uso no idiomatico. | J29: Logica de mezcla invertida: el motor nunca funciona 60 s. | K29: Nombres y comentarios por estado claros. | L29: Tiempo literal y salidas dispersas. | N29: =IF(COUNT(C29:G29)=5,"Completa","Falta")

Sheet I3
A1: [EVALUACIÓN IA — NO OFICIAL — solo para comparación con la evaluación humana] I3 — Gestión de alarmas con prioridad (Intermedio)
A2: Lee cada respuesta por su código en respuestas/Respuestas_I3.html. Rellena solo las celdas amarillas. Las azules vienen de CODESYS o se calculan solas. La fila EJEMPLO no se analiza.
A4: Código | B4: Resultado en CODESYS (automático) | C4: Corrección funcional (0–3) | D4: Cumplimiento IEC (0–3) | E4: Coherencia lógica (0–3) | F4: Claridad estructural (0–3) | G4: Mantenibilidad (0–3) | H4: Total (0–15) | I4: Justificación: corrección funcional / IEC | J4: Justificación: coherencia | K4: Justificación: claridad | L4: Justificación: mantenibilidad | M4: Observaciones | N4: Estado
A5: EJEMPLO | B5: Compila. Falla 2 de 7 pasos del harness (pasos 3,5; numerados desde 0). | C5: 1 | D5: 2 | E5: 2 | F5: 2 | G5: 1 | H5: =IF(COUNT(C5:G5)=5,SUM(C5:G5),"") | I5: Arranca y para, pero rearranca solo tras la emergencia. | J5: Sin contradicciones; transiciones completas. | K5: Nombres claros, comentarios útiles. | L5: El tiempo está escrito como literal en dos sitios. | N5: =IF(COUNT(C5:G5)=5,"Completa","Falta")
A6: I3-8823 | B6: Compila. Pasa los 10 pasos del harness. | C6: 3 | D6: 3 | E6: 2 | F6: 2 | G6: 2 | H6: =IF(COUNT(C6:G6)=5,SUM(C6:G6),"") | I6: IEC: FB con E/S bien declaradas y enclavamientos IF/ELSIF en ST estandar. | J6: Set con prioridad sobre reset y ack condicionado a causa ausente (guarda NOT alm redundante); ack por nivel, un ack mantenido anula la retencion. | K6: Secciones comentadas que explican la regla de reconocimiento; nombres claros, sin modularizacion adicional. | L6: Logica compacta y localizada, pero triplicada por alarma sin estructura extensible (arreglo o FB de enclavamiento). | N6: =IF(COUNT(C6:G6)=5,"Completa","Falta")
A7: I3-1249 | B7: Compila. Pasa los 10 pasos del harness. | C7: 3 | D7: 3 | E7: 2 | F7: 2 | G7: 2 | H7: =IF(COUNT(C7:G7)=5,SUM(C7:G7),"") | I7: IEC: FB con E/S bien declaradas y enclavamientos IF/ELSIF en ST estandar. | J7: Set con prioridad sobre reset y ack condicionado a causa ausente (guarda NOT alm redundante); ack por nivel, un ack mantenido anula la retencion. | K7: Secciones comentadas que explican la regla de reconocimiento; nombres claros, sin modularizacion adicional. | L7: Logica compacta y localizada, pero triplicada por alarma sin estructura extensible (arreglo o FB de enclavamiento). | N7: =IF(COUNT(C7:G7)=5,"Completa","Falta")
A8: I3-2429 | B8: Compila. Pasa los 10 pasos del harness. | C8: 3 | D8: 3 | E8: 2 | F8: 2 | G8: 2 | H8: =IF(COUNT(C8:G8)=5,SUM(C8:G8),"") | I8: IEC: FB con E/S bien declaradas y set/reset con IF en ST estandar. | J8: Set y reset separados con la condicion de causa ausente; ack por nivel, un ack mantenido anula la retencion. | K8: Secciones comentadas (retencion, sirena, codigo) y nombres descriptivos; sin modularizacion adicional. | L8: Logica compacta y localizada, pero triplicada por alarma sin estructura extensible (arreglo o FB de enclavamiento). | N8: =IF(COUNT(C8:G8)=5,"Completa","Falta")
A9: I3-2584 | B9: Compila. Pasa los 10 pasos del harness. | C9: 3 | D9: 3 | E9: 2 | F9: 2 | G9: 2 | H9: =IF(COUNT(C9:G9)=5,SUM(C9:G9),"") | I9: IEC: FB con E/S bien declaradas y enclavamiento por ecuacion booleana, ST estandar. | J9: Enclavamiento con set dominante correcto y prioridad bien resuelta; ack por nivel, un ack mantenido anula la retencion. | K9: Secciones comentadas que explican la regla de reconocimiento; nombres claros, sin modularizacion adicional. | L9: Logica compacta y localizada, pero triplicada por alarma sin estructura extensible (arreglo o FB de enclavamiento). | N9: =IF(COUNT(C9:G9)=5,"Completa","Falta")
A10: I3-9331 | B10: Compila. Pasa los 10 pasos del harness. | C10: 3 | D10: 3 | E10: 2 | F10: 2 | G10: 2 | H10: =IF(COUNT(C10:G10)=5,SUM(C10:G10),"") | I10: IEC: FB con E/S bien declaradas y enclavamientos IF/ELSIF en ST estandar. | J10: Set con prioridad sobre reset y ack condicionado a causa ausente (guarda NOT alm redundante); ack por nivel, un ack mantenido anula la retencion. | K10: Secciones comentadas (retencion, sirena, codigo) y nombres descriptivos; sin modularizacion adicional. | L10: Logica compacta y localizada, pero triplicada por alarma sin estructura extensible (arreglo o FB de enclavamiento). | N10: =IF(COUNT(C10:G10)=5,"Completa","Falta")
A11: I3-6376 | B11: Compila. Falla 2 de 10 pasos del harness (pasos 2,3; numerados desde 0). | C11: 1 | D11: 3 | E11: 1 | F11: 1 | G11: 1 | H11: =IF(COUNT(C11:G11)=5,SUM(C11:G11),"") | I11: Prioridad y sirena correctas en el caso nominal, pero falla la retencion y el ack con causa presente (pasos 2,3); ST estandar con E/S bien declaradas. | J11: No hay memoria: retAlm copia alm y el ack borra aun con la causa presente, contrario a la regla pedida. | K11: Comentario 'Retencion de alarmas' describe una retencion que no existe. | L11: Sirena repetida en cada rama y logica triplicada sin estructura extensible. | N11: =IF(COUNT(C11:G11)=5,"Completa","Falta")
A12: I3-8129 | B12: Compila. Pasa los 10 pasos del harness. | C12: 3 | D12: 3 | E12: 2 | F12: 2 | G12: 2 | H12: =IF(COUNT(C12:G12)=5,SUM(C12:G12),"") | I12: IEC: FB con E/S bien declaradas y enclavamiento por ecuacion booleana, ST estandar. | J12: Enclavamiento con set dominante correcto y prioridad bien resuelta; ack por nivel, un ack mantenido anula la retencion. | K12: Secciones comentadas que explican la regla de reconocimiento; nombres claros, sin modularizacion adicional. | L12: Logica compacta y localizada, pero triplicada por alarma sin estructura extensible (arreglo o FB de enclavamiento). | N12: =IF(COUNT(C12:G12)=5,"Completa","Falta")
A13: I3-2453 | B13: Compila. Pasa los 10 pasos del harness. | C13: 3 | D13: 3 | E13: 2 | F13: 2 | G13: 2 | H13: =IF(COUNT(C13:G13)=5,SUM(C13:G13),"") | I13: IEC: FB con E/S bien declaradas y enclavamientos IF/ELSIF en ST estandar. | J13: Set dominante y reset en ELSIF (implica causa ausente) correctos; ack por nivel, un ack mantenido anula la retencion. | K13: Secciones comentadas que explican la regla de reconocimiento; nombres claros, sin modularizacion adicional. | L13: Logica compacta y localizada, pero triplicada por alarma sin estructura extensible (arreglo o FB de enclavamiento). | N13: =IF(COUNT(C13:G13)=5,"Completa","Falta")
A14: I3-5104 | B14: Compila. Pasa los 10 pasos del harness. | C14: 3 | D14: 3 | E14: 2 | F14: 2 | G14: 2 | H14: =IF(COUNT(C14:G14)=5,SUM(C14:G14),"") | I14: IEC: FB con E/S bien declaradas y set/reset con IF en ST estandar. | J14: Set y reset separados con la condicion de causa ausente; ack por nivel, un ack mantenido anula la retencion. | K14: Secciones comentadas (retencion, sirena, codigo) y nombres descriptivos; sin modularizacion adicional. | L14: Cambios localizados, aunque la logica se triplica por alarma y la sirena se repite en cada rama de prioridad. | N14: =IF(COUNT(C14:G14)=5,"Completa","Falta")
A15: I3-3183 | B15: Compila. Pasa los 10 pasos del harness. | C15: 3 | D15: 3 | E15: 2 | F15: 2 | G15: 2 | H15: =IF(COUNT(C15:G15)=5,SUM(C15:G15),"") | I15: IEC: FB con E/S bien declaradas y set/reset con IF en ST estandar. | J15: Set y reset separados con la condicion de causa ausente; ack por nivel, un ack mantenido anula la retencion. | K15: Secciones comentadas (retencion, sirena, codigo) y nombres descriptivos; sin modularizacion adicional. | L15: Logica compacta y localizada, pero triplicada por alarma sin estructura extensible (arreglo o FB de enclavamiento). | N15: =IF(COUNT(C15:G15)=5,"Completa","Falta")
A16: I3-8600 | B16: Compila. Pasa los 10 pasos del harness. | C16: 3 | D16: 3 | E16: 2 | F16: 2 | G16: 2 | H16: =IF(COUNT(C16:G16)=5,SUM(C16:G16),"") | I16: IEC: FB con E/S bien declaradas y enclavamientos IF/ELSIF en ST estandar. | J16: Set con prioridad sobre reset y ack condicionado a causa ausente (guarda NOT alm redundante); ack por nivel, un ack mantenido anula la retencion. | K16: Secciones comentadas (retencion, sirena, codigo) y nombres descriptivos; sin modularizacion adicional. | L16: Logica compacta y localizada, pero triplicada por alarma sin estructura extensible (arreglo o FB de enclavamiento). | N16: =IF(COUNT(C16:G16)=5,"Completa","Falta")
... A29: I3-4818 | B29: Compila. Pasa los 10 pasos del harness. | C29: 3 | D29: 3 | E29: 2 | F29: 2 | G29: 2 | H29: =IF(COUNT(C29:G29)=5,SUM(C29:G29),"") | I29: IEC: FB con E/S bien declaradas y enclavamientos IF/ELSIF en ST estandar. | J29: Set con prioridad sobre reset y ack condicionado a causa ausente (guarda NOT alm redundante); ack por nivel, un ack mantenido anula la retencion. | K29: Secciones comentadas que explican la regla de reconocimiento; nombres claros, sin modularizacion adicional. | L29: Logica compacta y localizada, pero triplicada por alarma sin estructura extensible (arreglo o FB de enclavamiento). | N29: =IF(COUNT(C29:G29)=5,"Completa","Falta")

Sheet I4
A1: [EVALUACIÓN IA — NO OFICIAL — solo para comparación con la evaluación humana] I4 — Arranque estrella-triángulo (Intermedio)
A2: Lee cada respuesta por su código en respuestas/Respuestas_I4.html. Rellena solo las celdas amarillas. Las azules vienen de CODESYS o se calculan solas. La fila EJEMPLO no se analiza.
A4: Código | B4: Resultado en CODESYS (automático) | C4: Corrección funcional (0–3) | D4: Cumplimiento IEC (0–3) | E4: Coherencia lógica (0–3) | F4: Claridad estructural (0–3) | G4: Mantenibilidad (0–3) | H4: Total (0–15) | I4: Justificación: corrección funcional / IEC | J4: Justificación: coherencia | K4: Justificación: claridad | L4: Justificación: mantenibilidad | M4: Observaciones | N4: Estado
A5: EJEMPLO | B5: Compila. Falla 2 de 7 pasos del harness (pasos 3,5; numerados desde 0). | C5: 1 | D5: 2 | E5: 2 | F5: 2 | G5: 1 | H5: =IF(COUNT(C5:G5)=5,SUM(C5:G5),"") | I5: Arranca y para, pero rearranca solo tras la emergencia. | J5: Sin contradicciones; transiciones completas. | K5: Nombres claros, comentarios útiles. | L5: El tiempo está escrito como literal en dos sitios. | N5: =IF(COUNT(C5:G5)=5,"Completa","Falta")
A6: I4-2611 | B6: Compila. Pasa los 6 pasos del harness. | C6: 3 | D6: 3 | E6: 3 | F6: 2 | G6: 1 | H6: =IF(COUNT(C6:G6)=5,SUM(C6:G6),"") | I6: Pasa todo; TON bien instanciados y TIME correctos, idiomático. | J6: Paro prioritario, estado ELSE seguro, enclavamiento final kY/kD y temporizadores reseteados en reposo. | K6: Estados documentados y secciones claras, pero estados como INT mágicos. | L6: Literales T#8S/T#100MS repetidos en varios estados y números de estado sin constantes. | N6: =IF(COUNT(C6:G6)=5,"Completa","Falta")
A7: I4-7007 | B7: Compila sola, pero no se pudo simular: declara las entradas donde el harness no puede escribirlas ('btnMarcha' no es ninguna entrada de 'FB_ESTRELLATRIANGULO'). | C7: 0 | D7: 1 | E7: 0 | F7: 1 | G7: 1 | H7: =IF(COUNT(C7:G7)=5,SUM(C7:G7),"") | I7: Entradas/salidas declaradas en VAR (interfaz no conforme); además el TON se llama con IN:=FALSE en cada scan y nunca vence, así que no sale de estrella. | J7: Temporizadores reseteados cada ciclo: el estado 1 queda muerto; además exige mantener btnMarcha. | K7: Comentarios presentes pero E/S mezcladas en VAR rompen la estructura del FB. | L7: Literales y estados mágicos; la lógica de reset está duplicada. | N7: =IF(COUNT(C7:G7)=5,"Completa","Falta")
A8: I4-5661 | B8: Compila. Falla 2 de 6 pasos del harness (pasos 1,3; numerados desde 0). | C8: 0 | D8: 2 | E8: 1 | F8: 2 | G8: 1 | H8: =IF(COUNT(C8:G8)=5,SUM(C8:G8),"") | I8: Falla la fase estrella y el tiempo muerto (pasos 1,3): uso de TP llamado una sola vez hace que la transición sea casi inmediata; declaraciones correctas pero uso no idiomático de temporizadores. | J8: TP con llamada condicional da Q obsoleto y salta las temporizaciones; exige mantener btnMarcha. | K8: Estados documentados y comentarios útiles. | L8: Números de estado mágicos sin constantes. | N8: =IF(COUNT(C8:G8)=5,"Completa","Falta")
A9: I4-1792 | B9: Compila. Pasa los 6 pasos del harness. | C9: 3 | D9: 3 | E9: 3 | F9: 2 | G9: 1 | H9: =IF(COUNT(C9:G9)=5,SUM(C9:G9),"") | I9: Pasa todo; TON correctamente usados y reseteados, idiomático. | J9: Paro evaluado en cada estado, estado por defecto seguro, salidas definidas en cada estado. | K9: Secciones y estados bien comentados; estados INT sin nombres simbólicos. | L9: Literales de tiempo repetidos y estados numéricos mágicos. | N9: =IF(COUNT(C9:G9)=5,"Completa","Falta")
A10: I4-7740 | B10: Compila. Falla 3 de 6 pasos del harness (pasos 2,3,4; numerados desde 0). | C10: 0 | D10: 2 | E10: 0 | F10: 1 | G10: 1 | H10: =IF(COUNT(C10:G10)=5,SUM(C10:G10),"") | I10: No sale de estrella ni para fuera del estado 3 (pasos 2,3,4): el TON se resetea cada scan; compila con tipos correctos pero llamadas condicionales al FB. | J10: Temporizador reseteado en cada ciclo deja el estado 1 muerto y el paro solo actúa en el estado 3. | K10: Comentario 'Inicialización' incorrecto: se ejecuta en cada scan. | L10: Literales y estados mágicos dispersos. | N10: =IF(COUNT(C10:G10)=5,"Completa","Falta")
A11: I4-3109 | B11: Compila. Falla 3 de 6 pasos del harness (pasos 2,3,5; numerados desde 0). | C11: 0 | D11: 2 | E11: 0 | F11: 2 | G11: 1 | H11: =IF(COUNT(C11:G11)=5,SUM(C11:G11),"") | I11: Falla transición a triángulo y rearranque (pasos 2,3,5): el TON solo se invoca en el estado 0 y nunca actualiza Q. | J11: Temporizador no se vuelve a llamar: el estado 1 es un estado muerto; exige mantener btnMarcha. | K11: Nombres y comentarios razonables. | L11: Estados mágicos; sin parámetros. | N11: =IF(COUNT(C11:G11)=5,"Completa","Falta")
A12: I4-4531 | B12: Compila. Pasa los 6 pasos del harness. | C12: 3 | D12: 3 | E12: 3 | F12: 3 | G12: 2 | H12: =IF(COUNT(C12:G12)=5,SUM(C12:G12),"") | I12: Pasa todo; TON llamados incondicionalmente, idiomático. | J12: Enclavamiento mutuo explícito kY/kD, paro con prioridad, sin estados muertos. | K12: Secciones numeradas y comentarios que explican el porqué de cada enclavamiento. | L12: Cada literal aparece una sola vez y la lógica es compacta; tiempos no expuestos como parámetros. | N12: =IF(COUNT(C12:G12)=5,"Completa","Falta")
A13: I4-6607 | B13: Compila. Falla 3 de 6 pasos del harness (pasos 2,3,5; numerados desde 0). | C13: 0 | D13: 2 | E13: 0 | F13: 2 | G13: 1 | H13: =IF(COUNT(C13:G13)=5,SUM(C13:G13),"") | I13: Falla triángulo y rearranque (pasos 2,3,5): TON invocado solo en el estado 0, Q nunca se actualiza. | J13: Estado 1 muerto por temporizador no evaluado. | K13: Nombres y comentarios correctos y ordenados. | L13: Estados numéricos mágicos sin constantes. | N13: =IF(COUNT(C13:G13)=5,"Completa","Falta")
A14: I4-6264 | B14: Compila. Falla 3 de 6 pasos del harness (pasos 2,3,5; numerados desde 0). | C14: 0 | D14: 2 | E14: 0 | F14: 2 | G14: 1 | H14: =IF(COUNT(C14:G14)=5,SUM(C14:G14),"") | I14: Falla triángulo y rearranque (pasos 2,3,5): TON invocado solo en el estado 0, nunca vence. | J14: Estado 1 muerto por temporizador no evaluado. | K14: Nombres y comentarios correctos y ordenados. | L14: Estados numéricos mágicos sin constantes. | N14: =IF(COUNT(C14:G14)=5,"Completa","Falta")
A15: I4-2405 | B15: Compila. Pasa los 6 pasos del harness. | C15: 3 | D15: 3 | E15: 2 | F15: 3 | G15: 2 | H15: =IF(COUNT(C15:G15)=5,SUM(C15:G15),"") | I15: Pasa todo; enclavamiento marcha/paro y TON en cascada, idiomático. | J15: Coherente y con paro prioritario; la exclusión kY/kD es solo estructural, sin interlock explícito. | K15: Secciones claras y nota de seguridad que explica por qué no hay solape. | L15: Literales únicos y lógica sin duplicación; tiempos no parametrizados. | N15: =IF(COUNT(C15:G15)=5,"Completa","Falta")
A16: I4-2644 | B16: Compila. Pasa los 6 pasos del harness. | C16: 3 | D16: 3 | E16: 2 | F16: 3 | G16: 2 | H16: =IF(COUNT(C16:G16)=5,SUM(C16:G16),"") | I16: Pasa todo; idiomático. | J16: Coherente y con paro prioritario; exclusión kY/kD solo por construcción, sin interlock explícito. | K16: Secciones claras y nota que justifica la separación mínima. | L16: Literales únicos, sin duplicación; tiempos no parametrizados. | N16: =IF(COUNT(C16:G16)=5,"Completa","Falta")
A17: I4-1547 | B17: Compila sola, pero no se pudo simular: declara las entradas donde el harness no puede escribirlas ('btnMarcha' no es ninguna entrada de 'FB_ESTRELLATRIANGULO'). | C17: 0 | D17: 1 | E17: 0 | F17: 1 | G17: 1 | H17: =IF(COUNT(C17:G17)=5,SUM(C17:G17),"") | I17: E/S declaradas en VAR (interfaz no conforme); el TON se resetea cada scan y nunca vence. | J17: Temporizadores reseteados en cada ciclo: estado 1 muerto; exige mantener btnMarcha. | K17: Comentarios presentes pero E/S en VAR rompen la interfaz del FB. | L17: Literales y estados mágicos. | N17: =IF(COUNT(C17:G17)=5,"Completa","Falta")
A18: I4-6164 | B18: No compila (2 errores). | C18: 0 | D18: 0 | E18: 1 | F18: 2 | G18: 2 | H18: =IF(COUNT(C18:G18)=5,SUM(C18:G18),"") | J18: Uso de TP con llamada única hace la temporización inefectiva y exige mantener btnMarcha; enclavamiento final presente. | K18: Intenta estados con nombre y comentarios útiles. | L18: Estados con nombres simbólicos (aunque con sintaxis CONST inválida). | N18: =IF(COUNT(C18:G18)=5,"Completa","Falta")
A19: I4-8729 | B19: Compila. Falla 2 de 6 pasos del harness (pasos 2,3; numerados desde 0). | C19: 0 | D19: 2 | E19: 0 | F19: 1 | G19: 1 | H19: =IF(COUNT(C19:G19)=5,SUM(C19:G19),"") | I19: No sale de estrella (pasos 2,3): los TON se resetean en cada scan; incluye un temporizador declarado y sin uso. | J19: Temporizador reseteado cada ciclo deja el estado 1 muerto; timerDelta sin uso. | K19: Bloque de paro copiado en cada estado y comentario de inicialización engañoso. | L19: Lógica de paro duplicada cuatro veces y estados mágicos. | N19: =IF(COUNT(C19:G19)=5,"Completa","Falta")
A20: I4-6563 | B20: Compila. Pasa los 6 pasos del harness. | C20: 3 | D20: 3 | E20: 3 | F20: 2 | G20: 2 | H20: =IF(COUNT(C20:G20)=5,SUM(C20:G20),"") | I20: Pasa todo; idiomático. | J20: Paro prioritario y enclavamiento mutuo explícito en kY y kD. | K20: Compacto y comentado, aunque usa la propia salida kM como memoria. | L20: Literales únicos, sin duplicación. | N20: =IF(COUNT(C20:G20)=5,"Completa","Falta")
A21: I4-4147 | B21: Compila. Pasa los 6 pasos del harness. | C21: 3 | D21: 3 | E21: 3 | F21: 3 | G21: 2 | H21: =IF(COUNT(C21:G21)=5,SUM(C21:G21),"") | I21: Pasa todo; idiomático. | J21: Paro prioritario y kD enclavado con NOT kY; sin estados muertos. | K21: Secciones y comentarios que explican cada salida y la no simultaneidad. | L21: Literales únicos y sin duplicación; tiempos no parametrizados. | N21: =IF(COUNT(C21:G21)=5,"Completa","Falta")
A22: I4-3062 | B22: Compila. Falla 2 de 6 pasos del harness (pasos 1,3; numerados desde 0). | C22: 0 | D22: 2 | E22: 0 | F22: 1 | G22: 1 | H22: =IF(COUNT(C22:G22)=5,SUM(C22:G22),"") | I22: Falla fase estrella y tiempo muerto (pasos 1,3): TP invocado una vez da transiciones inmediatas. | J22: btnParo en ELSIF tras btnMarcha: con ambos pulsados en reposo arranca; TP mal usado. | K22: Pseudo-estados con IF sueltos; estructura poco clara. | L22: Estados mágicos y literales sin parametrizar. | N22: =IF(COUNT(C22:G22)=5,"Completa","Falta")
A23: I4-2763 | B23: Compila. Falla 1 de 6 pasos del harness (pasos 5; numerados desde 0). | C23: 1 | D23: 2 | E23: 1 | F23: 2 | G23: 1 | H23: =IF(COUNT(C23:G23)=5,SUM(C23:G23),"") | I23: Funciona en el caso nominal pero falla el rearranque (paso 5): asigna .IN := FALSE sin llamar al TON, que no se resetea y salta a triángulo. | J23: Reset de temporizador ineficaz deja Q obsoleto en el rearranque; comentario del estado 2 contradictorio. | K23: Estados documentados y secciones claras. | L23: Literales repetidos y estados numéricos mágicos. | N23: =IF(COUNT(C23:G23)=5,"Completa","Falta")
A24: I4-8365 | B24: Compila. Pasa los 6 pasos del harness. | C24: 3 | D24: 3 | E24: 3 | F24: 2 | G24: 2 | H24: =IF(COUNT(C24:G24)=5,SUM(C24:G24),"") | I24: Pasa todo; idiomático. | J24: Paro prioritario y enclavamiento mutuo explícito. | K24: Correcto y legible pero con comentarios mínimos. | L24: Literales únicos, sin duplicación. | N24: =IF(COUNT(C24:G24)=5,"Completa","Falta")
A25: I4-2920 | B25: Compila. Pasa los 6 pasos del harness. | C25: 3 | D25: 3 | E25: 3 | F25: 3 | G25: 2 | H25: =IF(COUNT(C25:G25)=5,SUM(C25:G25),"") | I25: Pasa todo; idiomático. | J25: Paro prioritario, enclavamiento mutuo explícito, sin estados muertos. | K25: Nombres con prefijos de tipo y comentarios que explican el porqué de cada enclavamiento. | L25: Literales únicos, sin duplicación; tiempos no parametrizados. | N25: =IF(COUNT(C25:G25)=5,"Completa","Falta")
A26: I4-7806 | B26: Compila. Falla 3 de 6 pasos del harness (pasos 2,3,5; numerados desde 0). | C26: 0 | D26: 2 | E26: 0 | F26: 2 | G26: 1 | H26: =IF(COUNT(C26:G26)=5,SUM(C26:G26),"") | I26: Falla triángulo y rearranque (pasos 2,3,5): TON invocado solo en el estado 0 y Q nunca se actualiza. | J26: Estado 1 muerto por temporizador no evaluado. | K26: Comentarios abundantes y nombres claros. | L26: Estados mágicos sin constantes. | N26: =IF(COUNT(C26:G26)=5,"Completa","Falta")
A27: I4-7176 | B27: No compila (2 errores). | C27: 0 | D27: 0 | E27: 0 | F27: 2 | G27: 2 | H27: =IF(COUNT(C27:G27)=5,SUM(C27:G27),"") | J27: El TON solo se invoca al arrancar, por lo que el estado de estrella nunca termina. | K27: Estados con nombre simbólico y comentarios útiles. | L27: Estados nombrados (aunque con sintaxis CONST inválida). | N27: =IF(COUNT(C27:G27)=5,"Completa","Falta")
A28: I4-8454 | B28: Compila. Pasa los 6 pasos del harness. | C28: 3 | D28: 3 | E28: 3 | F28: 2 | G28: 2 | H28: =IF(COUNT(C28:G28)=5,SUM(C28:G28),"") | I28: Pasa todo; idiomático. | J28: Paro prioritario y enclavamiento mutuo explícito. | K28: Legible pero con comentarios mínimos. | L28: Literales únicos, sin duplicación. | N28: =IF(COUNT(C28:G28)=5,"Completa","Falta")
A29: I4-1208 | B29: Compila. Pasa los 6 pasos del harness. | C29: 3 | D29: 3 | E29: 3 | F29: 3 | G29: 2 | H29: =IF(COUNT(C29:G29)=5,SUM(C29:G29),"") | I29: Pasa todo; idiomático. | J29: Paro prioritario y enclavamiento mutuo explícito. | K29: Secciones numeradas y comentarios que explican el porqué. | L29: Literales únicos, sin duplicación; tiempos no parametrizados. | N29: =IF(COUNT(C29:G29)=5,"Completa","Falta")

Sheet I5
A1: [EVALUACIÓN IA — NO OFICIAL — solo para comparación con la evaluación humana] I5 — Banda con clasificación por sensores (Intermedio)
A2: Lee cada respuesta por su código en respuestas/Respuestas_I5.html. Rellena solo las celdas amarillas. Las azules vienen de CODESYS o se calculan solas. La fila EJEMPLO no se analiza.
A4: Código | B4: Resultado en CODESYS (automático) | C4: Corrección funcional (0–3) | D4: Cumplimiento IEC (0–3) | E4: Coherencia lógica (0–3) | F4: Claridad estructural (0–3) | G4: Mantenibilidad (0–3) | H4: Total (0–15) | I4: Justificación: corrección funcional / IEC | J4: Justificación: coherencia | K4: Justificación: claridad | L4: Justificación: mantenibilidad | M4: Observaciones | N4: Estado
A5: EJEMPLO | B5: Compila. Falla 2 de 7 pasos del harness (pasos 3,5; numerados desde 0). | C5: 1 | D5: 2 | E5: 2 | F5: 2 | G5: 1 | H5: =IF(COUNT(C5:G5)=5,SUM(C5:G5),"") | I5: Arranca y para, pero rearranca solo tras la emergencia. | J5: Sin contradicciones; transiciones completas. | K5: Nombres claros, comentarios útiles. | L5: El tiempo está escrito como literal en dos sitios. | N5: =IF(COUNT(C5:G5)=5,"Completa","Falta")
A6: I5-9795 | B6: Compila. Pasa los 7 pasos del harness. | C6: 3 | D6: 3 | E6: 0 | F6: 1 | G6: 1 | H6: =IF(COUNT(C6:G6)=5,SUM(C6:G6),"") | I6: Pasa todo; R_TRIG, TON y TP bien instanciados, idiomático. | J6: Las dos condiciones de limpieza de bPiezaAlta nunca se cumplen (exigen tRetardo.Q falso con IN activo): tras la primera pieza alta el desviador no vuelve a dispararse. | K6: Comentarios que afirman limpiar la bandera cuando el código no lo hace. | L6: Lógica de limpieza redundante y muerta que dificulta modificar el FB. | N6: =IF(COUNT(C6:G6)=5,"Completa","Falta")
A7: I5-6031 | B7: Compila. Pasa los 7 pasos del harness. | C7: 3 | D7: 3 | E7: 2 | F7: 2 | G7: 2 | H7: =IF(COUNT(C7:G7)=5,SUM(C7:G7),"") | I7: Pasa todo; R_TRIG + TON + TP, idiomático. | J7: Coherente y con flanco único; una segunda pieza alta dentro de los 2 s no reinicia el retardo. | K7: Nombres descriptivos y comentarios útiles con el porqué del flanco. | L7: Literales en un único sitio y sin duplicación; tiempos no parametrizados. | N7: =IF(COUNT(C7:G7)=5,"Completa","Falta")
A8: I5-2725 | B8: No compila (4 errores). | C8: 0 | D8: 0 | E8: 0 | F8: 1 | G8: 1 | H8: =IF(COUNT(C8:G8)=5,SUM(C8:G8),"") | J8: Temporizadores reseteados en cada scan nunca vencen; la altura se evalúa a los 2 s y no en la detección. | K8: Comentario de 'inicialización' engañoso y flujo confuso. | L8: Lógica de temporización dispersa en varias ramas. | N8: =IF(COUNT(C8:G8)=5,"Completa","Falta")
A9: I5-5960 | B9: Compila. Pasa los 7 pasos del harness. | C9: 3 | D9: 3 | E9: 2 | F9: 3 | G9: 2 | H9: =IF(COUNT(C9:G9)=5,SUM(C9:G9),"") | I9: Pasa todo; idiomático. | J9: Coherente; segunda pieza alta dentro del retardo no se reprograma. | K9: Secciones numeradas y comentarios que explican el porqué de cada paso. | L9: Literales únicos y sin duplicación; tiempos no parametrizados. | N9: =IF(COUNT(C9:G9)=5,"Completa","Falta")
A10: I5-5429 | B10: Compila. Pasa los 7 pasos del harness. | C10: 3 | D10: 2 | E10: 2 | F10: 2 | G10: 2 | H10: =IF(COUNT(C10:G10)=5,SUM(C10:G10),"") | I10: Pasa todo; compila con tipos correctos pero usa un TON leyendo .IN AND NOT .Q como pulso en lugar de TP. | J10: Coherente; piezas altas solapadas se fusionan en un solo ciclo de desvío. | K10: Secciones con cabeceras y comentarios claros. | L10: Literales únicos y sin duplicación. | N10: =IF(COUNT(C10:G10)=5,"Completa","Falta")
A11: I5-7024 | B11: Compila. Falla 3 de 7 pasos del harness (pasos 3,4,5; numerados desde 0). | C11: 0 | D11: 2 | E11: 1 | F11: 2 | G11: 1 | H11: =IF(COUNT(C11:G11)=5,SUM(C11:G11),"") | I11: Cuenta las altas solo al terminar el pistón y el desvío no ocurre en la ventana (pasos 3,4,5); asigna .IN de los TON fuera de la llamada. | J11: Asignaciones a .IN sin efecto y bandera bContado redundante; conteo de altas desplazado. | K11: Secciones numeradas y comentarios descriptivos. | L11: Conteo repartido en dos lugares y resets ineficaces dificultan cambios. | N11: =IF(COUNT(C11:G11)=5,"Completa","Falta")
A12: I5-3559 | B12: Compila. Falla 6 de 7 pasos del harness (pasos 1,2,3,4,5,6; numerados desde 0). | C12: 0 | D12: 2 | E12: 0 | F12: 1 | G12: 1 | H12: =IF(COUNT(C12:G12)=5,SUM(C12:G12),"") | I12: Falla casi todo (pasos 1-6): el TON se llama una sola vez y nunca vence, y el conteo se hace tras el retardo. | J12: Temporizador no reevaluado: el retardo nunca termina y nada se cuenta. | K12: Comentario 'inicialización' erróneo y lógica del pistón confusa. | L12: Lógica rehecha en ramas condicionales; requiere reescritura. | N12: =IF(COUNT(C12:G12)=5,"Completa","Falta")
A13: I5-2602 | B13: Compila. Falla 6 de 7 pasos del harness (pasos 1,2,3,4,5,6; numerados desde 0). | C13: 0 | D13: 2 | E13: 0 | F13: 2 | G13: 1 | H13: =IF(COUNT(C13:G13)=5,SUM(C13:G13),"") | I13: Falla pasos 1-6: sin detección de flanco cuenta en cada scan y el TON solo se evalúa mientras hay presencia. | J13: Conteo por nivel y temporizador evaluado condicionalmente: contradictorio con el enunciado. | K13: Nombres y comentarios claros. | L13: Diseño base erróneo que exige rehacer la lógica. | N13: =IF(COUNT(C13:G13)=5,"Completa","Falta")
A14: I5-3769 | B14: Compila. Falla 6 de 7 pasos del harness (pasos 1,2,3,4,5,6; numerados desde 0). | C14: 0 | D14: 2 | E14: 0 | F14: 2 | G14: 1 | H14: =IF(COUNT(C14:G14)=5,SUM(C14:G14),"") | I14: Falla pasos 1-6: conteo por nivel en cada scan y TON llamado solo con presencia. | J14: Conteo repetido por scan y temporizadores que no avanzan sin presencia. | K14: Nombres y comentarios claros. | L14: Diseño base erróneo que exige rehacer la lógica. | N14: =IF(COUNT(C14:G14)=5,"Completa","Falta")
A15: I5-4146 | B15: Compila. Falla 4 de 7 pasos del harness (pasos 3,4,5,6; numerados desde 0). | C15: 0 | D15: 2 | E15: 0 | F15: 1 | G15: 1 | H15: =IF(COUNT(C15:G15)=5,SUM(C15:G15),"") | I15: Falla las piezas altas (pasos 3-6): TON reseteados al inicio de cada scan, el pistón se activa sin retardo y nAltas se cuenta al final. | J15: Temporizadores nunca vencen y el pistón queda activo indefinidamente. | K15: Comentario de inicialización incorrecto y banda asignada dos veces. | L15: Llamadas a temporizadores repetidas en varias ramas. | N15: =IF(COUNT(C15:G15)=5,"Completa","Falta")
A16: I5-8743 | B16: Compila. Pasa los 7 pasos del harness. | C16: 3 | D16: 3 | E16: 2 | F16: 3 | G16: 2 | H16: =IF(COUNT(C16:G16)=5,SUM(C16:G16),"") | I16: Pasa todo; idiomático. | J16: Coherente; segunda pieza alta dentro del retardo no se reprograma. | K16: Secciones numeradas y comentarios con el porqué. | L16: Literales únicos y sin duplicación; tiempos no parametrizados. | N16: =IF(COUNT(C16:G16)=5,"Completa","Falta")
A17: I5-3551 | B17: Compila. Falla 7 de 7 pasos del harness (pasos 0,1,2,3,4,5,6; numerados desde 0). | C17: 0 | D17: 2 | E17: 0 | F17: 1 | G17: 1 | H17: =IF(COUNT(C17:G17)=5,SUM(C17:G17),"") | I17: Falla todos los pasos: nBajas se incrementa en cada scan y los TP se llaman condicionalmente. | J17: La rama ELSE cuenta una pieza baja en cada ciclo; la altura se lee a los 2 s. | K17: Comentarios que no corresponden al comportamiento real. | L17: Diseño erróneo que exige reescritura. | N17: =IF(COUNT(C17:G17)=5,"Completa","Falta")
A18: I5-3570 | B18: No compila (4 errores). | C18: 0 | D18: 0 | E18: 0 | F18: 1 | G18: 1 | H18: =IF(COUNT(C18:G18)=5,SUM(C18:G18),"") | J18: Temporizadores reseteados cuando cae la presencia, por lo que el retardo se pierde; altura evaluada tarde. | K18: Nombres crípticos timer1/timer2. | L18: Llamadas a temporizadores dispersas y literales en llamadas separadas. | N18: =IF(COUNT(C18:G18)=5,"Completa","Falta")
A19: I5-9566 | B19: Compila. Falla 4 de 7 pasos del harness (pasos 3,4,5,6; numerados desde 0). | C19: 0 | D19: 2 | E19: 0 | F19: 2 | G19: 1 | H19: =IF(COUNT(C19:G19)=5,SUM(C19:G19),"") | I19: Falla las piezas altas (pasos 3-6): el TON de retardo se llama una sola vez y nunca vence. | J19: Temporizador no reevaluado deja el desvío sin ejecutarse y nAltas sin contar. | K19: Nombres y comentarios claros. | L19: Lógica condicional de temporizadores que requiere rehacerse. | N19: =IF(COUNT(C19:G19)=5,"Completa","Falta")
A20: I5-2807 | B20: Compila. Falla 6 de 7 pasos del harness (pasos 1,2,3,4,5,6; numerados desde 0). | C20: 0 | D20: 2 | E20: 0 | F20: 2 | G20: 1 | H20: =IF(COUNT(C20:G20)=5,SUM(C20:G20),"") | I20: Falla pasos 1-6: el TP de 2 s activa el pistón de inmediato y para todas las piezas. | J20: El pistón se activa también con piezas bajas y antes del retardo; TP usado al revés. | K20: Nombres y comentarios razonables. | L20: Diseño de temporización erróneo que exige rehacerlo. | N20: =IF(COUNT(C20:G20)=5,"Completa","Falta")
A21: I5-9964 | B21: Compila. Falla 6 de 7 pasos del harness (pasos 1,2,3,4,5,6; numerados desde 0). | C21: 0 | D21: 1 | E21: 0 | F21: 1 | G21: 1 | H21: =IF(COUNT(C21:G21)=5,SUM(C21:G21),"") | I21: nAltas y nBajas declarados en VAR en lugar de VAR_OUTPUT (interfaz no conforme); el TON se llama una vez y el estado 1 nunca termina. | J21: Estado 1 muerto por temporizador no reevaluado; altura leída a los 2 s. | K21: Nombres crípticos timer1/timer2 y E/S fuera de su sección. | L21: Estados mágicos y temporizadores dispersos. | N21: =IF(COUNT(C21:G21)=5,"Completa","Falta")
A22: I5-4776 | B22: Compila. Pasa los 7 pasos del harness. | C22: 3 | D22: 3 | E22: 2 | F22: 2 | G22: 2 | H22: =IF(COUNT(C22:G22)=5,SUM(C22:G22),"") | I22: Pasa todo; R_TRIG, TP y F_TRIG bien combinados, idiomático. | J22: Coherente; el TP no es redisparable, una segunda pieza alta dentro de 2 s se pierde. | K22: Comentarios claros y breves. | L22: Literales únicos y sin duplicación. | N22: =IF(COUNT(C22:G22)=5,"Completa","Falta")
A23: I5-8715 | B23: Compila. Falla 1 de 7 pasos del harness (pasos 5; numerados desde 0). | C23: 0 | D23: 2 | E23: 0 | F23: 1 | G23: 2 | H23: =IF(COUNT(C23:G23)=5,SUM(C23:G23),"") | I23: El pistón nunca se activa (paso 5): el TON de retardo se resetea en el mismo scan antes de disparar el del pistón; llamadas múltiples por scan. | J23: El reset inmediato de tRetardo anula la condición que debía arrancar tPiston: contradicción que deja sin desvío. | K23: Buena estructura pero la nota sobre el ciclo de tRetardo.Q es incorrecta. | L23: Literales únicos; el fallo es localizado. | N23: =IF(COUNT(C23:G23)=5,"Completa","Falta")
A24: I5-6743 | B24: Compila. Pasa los 7 pasos del harness. | C24: 3 | D24: 3 | E24: 2 | F24: 2 | G24: 2 | H24: =IF(COUNT(C24:G24)=5,SUM(C24:G24),"") | I24: Pasa todo; idiomático. | J24: Coherente; el TP de retardo no se redispara con piezas altas solapadas. | K24: Nombres descriptivos y comentarios útiles. | L24: Literales únicos y sin duplicación. | N24: =IF(COUNT(C24:G24)=5,"Completa","Falta")
A25: I5-6738 | B25: Compila. Pasa los 7 pasos del harness. | C25: 3 | D25: 3 | E25: 1 | F25: 2 | G25: 2 | H25: =IF(COUNT(C25:G25)=5,SUM(C25:G25),"") | I25: Pasa todo; idiomático. | J25: Una pieza baja que llegue durante el retardo pone bEsAlta a FALSE y cancela el desvío de la pieza alta previa. | K25: Comentarios claros por bloque. | L25: Literales únicos y sin duplicación. | N25: =IF(COUNT(C25:G25)=5,"Completa","Falta")
A26: I5-6315 | B26: Compila. Pasa los 7 pasos del harness. | C26: 3 | D26: 3 | E26: 2 | F26: 2 | G26: 2 | H26: =IF(COUNT(C26:G26)=5,SUM(C26:G26),"") | I26: Pasa todo; idiomático. | J26: Coherente; la bandera se limpia al terminar el pulso, aunque no gestiona piezas altas solapadas. | K26: Comentarios útiles, algo redundantes en la limpieza. | L26: Literales únicos y sin duplicación. | N26: =IF(COUNT(C26:G26)=5,"Completa","Falta")
A27: I5-3665 | B27: Compila. Pasa los 7 pasos del harness. | C27: 3 | D27: 3 | E27: 2 | F27: 2 | G27: 2 | H27: =IF(COUNT(C27:G27)=5,SUM(C27:G27),"") | I27: Pasa todo; idiomático. | J27: Coherente; el TP de retardo no se redispara con piezas altas solapadas. | K27: Nombres y comentarios claros. | L27: Literales únicos y sin duplicación. | N27: =IF(COUNT(C27:G27)=5,"Completa","Falta")
A28: I5-2293 | B28: Compila. Falla 6 de 7 pasos del harness (pasos 1,2,3,4,5,6; numerados desde 0). | C28: 0 | D28: 2 | E28: 0 | F28: 2 | G28: 1 | H28: =IF(COUNT(C28:G28)=5,SUM(C28:G28),"") | I28: Falla pasos 1-6: conteo por nivel en cada scan y TON evaluado solo con presencia. | J28: Conteo repetido por scan y temporizador que no avanza sin presencia. | K28: Nombres y comentarios claros. | L28: Diseño base erróneo que exige reescritura. | N28: =IF(COUNT(C28:G28)=5,"Completa","Falta")
A29: I5-8675 | B29: Compila. Falla 7 de 7 pasos del harness (pasos 0,1,2,3,4,5,6; numerados desde 0). | C29: 0 | D29: 2 | E29: 0 | F29: 1 | G29: 1 | H29: =IF(COUNT(C29:G29)=5,SUM(C29:G29),"") | I29: Falla todos los pasos: nBajas se incrementa en cada scan y TP llamados condicionalmente. | J29: La rama ELSE cuenta piezas bajas cada ciclo; altura leída a los 2 s. | K29: Comentarios que no reflejan el comportamiento. | L29: Diseño erróneo que exige reescritura. | N29: =IF(COUNT(C29:G29)=5,"Completa","Falta")

Sheet I6
A1: [EVALUACIÓN IA — NO OFICIAL — solo para comparación con la evaluación humana] I6 — Escalado analógico con histéresis (Intermedio)
A2: Lee cada respuesta por su código en respuestas/Respuestas_I6.html. Rellena solo las celdas amarillas. Las azules vienen de CODESYS o se calculan solas. La fila EJEMPLO no se analiza.
A4: Código | B4: Resultado en CODESYS (automático) | C4: Corrección funcional (0–3) | D4: Cumplimiento IEC (0–3) | E4: Coherencia lógica (0–3) | F4: Claridad estructural (0–3) | G4: Mantenibilidad (0–3) | H4: Total (0–15) | I4: Justificación: corrección funcional / IEC | J4: Justificación: coherencia | K4: Justificación: claridad | L4: Justificación: mantenibilidad | M4: Observaciones | N4: Estado
A5: EJEMPLO | B5: Compila. Falla 2 de 7 pasos del harness (pasos 3,5; numerados desde 0). | C5: 1 | D5: 2 | E5: 2 | F5: 2 | G5: 1 | H5: =IF(COUNT(C5:G5)=5,SUM(C5:G5),"") | I5: Arranca y para, pero rearranca solo tras la emergencia. | J5: Sin contradicciones; transiciones completas. | K5: Nombres claros, comentarios útiles. | L5: El tiempo está escrito como literal en dos sitios. | N5: =IF(COUNT(C5:G5)=5,"Completa","Falta")
A6: I6-6450 | B6: Compila. Pasa los 8 pasos del harness. | C6: 3 | D6: 3 | E6: 3 | F6: 2 | G6: 1 | H6: =IF(COUNT(C6:G6)=5,SUM(C6:G6),"") | I6: Pasa todo; conversión explícita INT_TO_REAL y tipos correctos, idiomático. | J6: Alarma con prioridad sobre la histéresis y estado conservado en la banda. | K6: Breve, con comentarios útiles por bloque. | L6: Rango y umbrales como literales mágicos en el código. | N6: =IF(COUNT(C6:G6)=5,"Completa","Falta")
A7: I6-3905 | B7: Compila. Pasa los 8 pasos del harness. | C7: 3 | D7: 3 | E7: 3 | F7: 2 | G7: 1 | H7: =IF(COUNT(C7:G7)=5,SUM(C7:G7),"") | I7: Pasa todo; conversión explícita INT_TO_REAL y tipos correctos, idiomático. | J7: Alarma prioritaria y histéresis correcta sin redundancias. | K7: Comentarios útiles por bloque. | L7: Rango y umbrales como literales. | N7: =IF(COUNT(C7:G7)=5,"Completa","Falta")
A8: I6-1333 | B8: Compila. Pasa los 8 pasos del harness. | C8: 3 | D8: 2 | E8: 1 | F8: 2 | G8: 1 | H8: =IF(COUNT(C8:G8)=5,SUM(C8:G8),"") | I8: Pasa todo; compila con tipos correctos pero depende de conversión implícita INT→REAL en la aritmética. | J8: Histéresis mediante copia redundante enfriadorPrev y variable tempCPrev sin uso. | K8: Nombres descriptivos y comentarios claros, con variables sobrantes. | L8: Factor 276.48 derivado y umbrales literales. | N8: =IF(COUNT(C8:G8)=5,"Completa","Falta")
A9: I6-1644 | B9: No compila (7 errores). | C9: 0 | D9: 0 | E9: 1 | F9: 2 | G9: 1 | H9: =IF(COUNT(C9:G9)=5,SUM(C9:G9),"") | J9: Lógica correcta pero con redundancias: 'enfriador := enfriador' y variable tempC_prev declarada sin uso. | K9: Comentarios y nombres adecuados. | L9: Constantes de escala y umbrales como literales. | N9: =IF(COUNT(C9:G9)=5,"Completa","Falta")
A10: I6-4554 | B10: Compila. Pasa los 8 pasos del harness. | C10: 3 | D10: 3 | E10: 3 | F10: 3 | G10: 1 | H10: =IF(COUNT(C10:G10)=5,SUM(C10:G10),"") | I10: Pasa todo; conversión explícita INT_TO_REAL y tipos correctos, idiomático. | J10: Alarma prioritaria y histéresis correcta. | K10: Secciones numeradas y nota que explica por qué se conserva el estado. | L10: Rango y umbrales como literales. | N10: =IF(COUNT(C10:G10)=5,"Completa","Falta")
A11: I6-4640 | B11: Compila. Pasa los 8 pasos del harness. | C11: 3 | D11: 3 | E11: 3 | F11: 3 | G11: 1 | H11: =IF(COUNT(C11:G11)=5,SUM(C11:G11),"") | I11: Pasa todo; conversión explícita INT_TO_REAL y tipos correctos, idiomático. | J11: Alarma apaga el enfriador y la histéresis conserva estado; sin contradicciones. | K11: Comentarios que explican la fórmula y el porqué del apagado de seguridad. | L11: Rango y umbrales como literales. | N11: =IF(COUNT(C11:G11)=5,"Completa","Falta")
A12: I6-5227 | B12: Compila. Pasa los 8 pasos del harness. | C12: 3 | D12: 2 | E12: 3 | F12: 2 | G12: 2 | H12: =IF(COUNT(C12:G12)=5,SUM(C12:G12),"") | I12: Pasa todo; compila con tipos correctos pero depende de conversión implícita INT→REAL en la aritmética. | J12: Alarma aplicada al final sobrescribe al enfriador; histéresis correcta. | K12: Nombres descriptivos (mezcla inglés/español) y comentarios útiles. | L12: Rango, escala y umbrales declarados como variables; no son entradas del FB. | N12: =IF(COUNT(C12:G12)=5,"Completa","Falta")
A13: I6-1990 | B13: Compila. Pasa los 8 pasos del harness. | C13: 3 | D13: 2 | E13: 3 | F13: 2 | G13: 2 | H13: =IF(COUNT(C13:G13)=5,SUM(C13:G13),"") | I13: Pasa todo; compila con tipos correctos pero depende de conversión implícita INT→REAL en la aritmética. | J13: Alarma prioritaria y histéresis correcta. | K13: Nombres descriptivos y comentarios útiles. | L13: Parámetros declarados como variables; no expuestos como entradas. | N13: =IF(COUNT(C13:G13)=5,"Completa","Falta")
A14: I6-8944 | B14: Compila. Pasa los 8 pasos del harness. | C14: 3 | D14: 3 | E14: 3 | F14: 3 | G14: 1 | H14: =IF(COUNT(C14:G14)=5,SUM(C14:G14),"") | I14: Pasa todo; conversión explícita INT_TO_REAL y tipos correctos, idiomático. | J14: Alarma prioritaria y histéresis correcta. | K14: Secciones numeradas y comentarios con el porqué de seguridad. | L14: Rango y umbrales como literales. | N14: =IF(COUNT(C14:G14)=5,"Completa","Falta")
A15: I6-2466 | B15: Compila. Pasa los 8 pasos del harness. | C15: 3 | D15: 3 | E15: 3 | F15: 3 | G15: 2 | H15: =IF(COUNT(C15:G15)=5,SUM(C15:G15),"") | I15: Pasa todo; conversión explícita INT_TO_REAL y tipos correctos, idiomático. | J15: Alarma prioritaria, tempC definido en fallo y histéresis correcta. | K15: Secciones, fórmula documentada y comentarios con el porqué. | L15: VAR CONSTANT para rango y umbrales; la fórmula omite los offsets declarados y no hay parámetros de entrada. | N15: =IF(COUNT(C15:G15)=5,"Completa","Falta")
A16: I6-7405 | B16: Compila. Pasa los 8 pasos del harness. | C16: 3 | D16: 3 | E16: 3 | F16: 2 | G16: 1 | H16: =IF(COUNT(C16:G16)=5,SUM(C16:G16),"") | I16: Pasa todo; conversión explícita INT_TO_REAL y tipos correctos, idiomático. | J16: Alarma prioritaria y histéresis correcta. | K16: Comentarios útiles por rama. | L16: Rango y umbrales como literales. | N16: =IF(COUNT(C16:G16)=5,"Completa","Falta")
A17: I6-4763 | B17: Compila. Pasa los 8 pasos del harness. | C17: 3 | D17: 3 | E17: 3 | F17: 3 | G17: 2 | H17: =IF(COUNT(C17:G17)=5,SUM(C17:G17),"") | I17: Pasa todo; conversión explícita INT_TO_REAL y tipos correctos, idiomático. | J17: Alarma con salida anticipada, tempC definido en fallo, histéresis correcta. | K17: Secciones bien delimitadas y fórmula documentada. | L17: VAR CONSTANT y escalado general con offsets; sin parámetros de entrada. | N17: =IF(COUNT(C17:G17)=5,"Completa","Falta")
A18: I6-2631 | B18: No compila (7 errores). | C18: 0 | D18: 0 | E18: 1 | F18: 2 | G18: 1 | H18: =IF(COUNT(C18:G18)=5,SUM(C18:G18),"") | J18: Lógica correcta pero con redundancias: 'enfriador := enfriador' y variable tempC_prev declarada sin uso. | K18: Comentarios y nombres adecuados. | L18: Literales mágicos en escala y umbrales. | N18: =IF(COUNT(C18:G18)=5,"Completa","Falta")
A19: I6-5219 | B19: Compila. Pasa los 8 pasos del harness. | C19: 3 | D19: 2 | E19: 1 | F19: 2 | G19: 1 | H19: =IF(COUNT(C19:G19)=5,SUM(C19:G19),"") | I19: Pasa todo; compila con tipos correctos pero depende de conversión implícita INT→REAL en la aritmética. | J19: El apagado por alarma depende indirectamente de tempC:=0; copia redundante enfriadorPrev y tempCPrev sin uso. | K19: Nombres y comentarios claros con variables sobrantes. | L19: Literales mágicos en escala y umbrales. | N19: =IF(COUNT(C19:G19)=5,"Completa","Falta")
A20: I6-8502 | B20: Compila. Pasa los 8 pasos del harness. | C20: 3 | D20: 3 | E20: 3 | F20: 3 | G20: 1 | H20: =IF(COUNT(C20:G20)=5,SUM(C20:G20),"") | I20: Pasa todo; conversión explícita INT_TO_REAL y tipos correctos, idiomático. | J20: Alarma prioritaria y histéresis correcta. | K20: Secciones numeradas y comentarios con el porqué. | L20: Rango y umbrales como literales. | N20: =IF(COUNT(C20:G20)=5,"Completa","Falta")
A21: I6-1774 | B21: No compila (12 errores). | C21: 0 | D21: 0 | E21: 1 | F21: 2 | G21: 1 | H21: =IF(COUNT(C21:G21)=5,SUM(C21:G21),"") | J21: Lógica correcta pero con redundancias: 'enfriador := enfriador' y variable tempC_prev declarada sin uso. | K21: Comentarios útiles, aunque con bloque BEGIN ajeno a ST. | L21: Solo el factor de escala intenta ser constante; umbrales y rango literales. | N21: =IF(COUNT(C21:G21)=5,"Completa","Falta")
A22: I6-7940 | B22: Compila. Pasa los 8 pasos del harness. | C22: 3 | D22: 3 | E22: 3 | F22: 3 | G22: 1 | H22: =IF(COUNT(C22:G22)=5,SUM(C22:G22),"") | I22: Pasa todo; conversión explícita INT_TO_REAL y tipos correctos, idiomático. | J22: Alarma prioritaria y histéresis correcta. | K22: Comentarios que explican fórmula, umbrales y apagado de seguridad. | L22: Rango y umbrales como literales. | N22: =IF(COUNT(C22:G22)=5,"Completa","Falta")
A23: I6-9872 | B23: No compila (7 errores). | C23: 0 | D23: 0 | E23: 1 | F23: 2 | G23: 1 | H23: =IF(COUNT(C23:G23)=5,SUM(C23:G23),"") | J23: Lógica correcta pero con redundancias: 'enfriador := enfriador' y variable tempC_prev declarada sin uso. | K23: Comentarios y nombres adecuados. | L23: Literales mágicos en escala y umbrales. | N23: =IF(COUNT(C23:G23)=5,"Completa","Falta")
A24: I6-7606 | B24: Compila. Pasa los 8 pasos del harness. | C24: 3 | D24: 3 | E24: 3 | F24: 3 | G24: 2 | H24: =IF(COUNT(C24:G24)=5,SUM(C24:G24),"") | I24: Pasa todo; conversión explícita INT_TO_REAL y tipos correctos, idiomático. | J24: Alarma prioritaria, tempC definido en fallo, histéresis correcta. | K24: Secciones bien delimitadas y fórmula documentada. | L24: VAR CONSTANT para rango y umbrales; sin parámetros de entrada. | N24: =IF(COUNT(C24:G24)=5,"Completa","Falta")
A25: I6-9273 | B25: Compila. Pasa los 8 pasos del harness. | C25: 3 | D25: 2 | E25: 1 | F25: 2 | G25: 1 | H25: =IF(COUNT(C25:G25)=5,SUM(C25:G25),"") | I25: Pasa todo; compila con tipos correctos pero depende de conversión implícita INT→REAL en la aritmética. | J25: Histéresis con copia redundante enfriadorPrev y tempCPrev sin uso. | K25: Nombres y comentarios claros con variables sobrantes. | L25: Factor 276.48 derivado y umbrales literales. | N25: =IF(COUNT(C25:G25)=5,"Completa","Falta")
A26: I6-9365 | B26: No compila (7 errores). | C26: 0 | D26: 0 | E26: 1 | F26: 2 | G26: 1 | H26: =IF(COUNT(C26:G26)=5,SUM(C26:G26),"") | J26: Lógica correcta pero con redundancias: 'enfriador := enfriador' y variable tempC_prev declarada sin uso. | K26: Comentarios y nombres adecuados. | L26: Literales mágicos en escala y umbrales. | N26: =IF(COUNT(C26:G26)=5,"Completa","Falta")
A27: I6-4205 | B27: No compila (7 errores). | C27: 0 | D27: 0 | E27: 1 | F27: 2 | G27: 1 | H27: =IF(COUNT(C27:G27)=5,SUM(C27:G27),"") | J27: Lógica correcta pero con redundancias: 'enfriador := enfriador' y variable tempC_prev declarada sin uso. | K27: Comentarios y nombres adecuados. | L27: Literales mágicos en escala y umbrales. | N27: =IF(COUNT(C27:G27)=5,"Completa","Falta")
A28: I6-1860 | B28: Compila. Falla 1 de 8 pasos del harness (pasos 3; numerados desde 0). | C28: 1 | D28: 2 | E28: 1 | F28: 2 | G28: 1 | H28: =IF(COUNT(C28:G28)=5,SUM(C28:G28),"") | I28: Funciona en el caso nominal y la histéresis, pero la alarma no apaga el enfriador (paso 3); compila con conversión implícita INT→REAL. | J28: Falta el enclavamiento alarma→enfriador (con raw > 27648 incluso puede encenderlo) y la variable histeresis no se usa. | K28: Nombres y comentarios razonables. | L28: Escala parametrizada pero umbrales literales y parámetro histeresis sin usar. | N28: =IF(COUNT(C28:G28)=5,"Completa","Falta")
A29: I6-9306 | B29: Compila. Pasa los 8 pasos del harness. | C29: 3 | D29: 3 | E29: 3 | F29: 3 | G29: 2 | H29: =IF(COUNT(C29:G29)=5,SUM(C29:G29),"") | I29: Pasa todo; conversión explícita INT_TO_REAL y tipos correctos, idiomático. | J29: Alarma prioritaria, tempC definido en fallo, histéresis correcta. | K29: Secciones delimitadas y comentarios con fórmula y porqué. | L29: VAR CONSTANT para rango y umbrales; sin parámetros de entrada. | N29: =IF(COUNT(C29:G29)=5,"Completa","Falta")

Sheet I7
A1: [EVALUACIÓN IA — NO OFICIAL — solo para comparación con la evaluación humana] I7 — Bombas dúplex con alternancia (Intermedio)
A2: Lee cada respuesta por su código en respuestas/Respuestas_I7.html. Rellena solo las celdas amarillas. Las azules vienen de CODESYS o se calculan solas. La fila EJEMPLO no se analiza.
A4: Código | B4: Resultado en CODESYS (automático) | C4: Corrección funcional (0–3) | D4: Cumplimiento IEC (0–3) | E4: Coherencia lógica (0–3) | F4: Claridad estructural (0–3) | G4: Mantenibilidad (0–3) | H4: Total (0–15) | I4: Justificación: corrección funcional / IEC | J4: Justificación: coherencia | K4: Justificación: claridad | L4: Justificación: mantenibilidad | M4: Observaciones | N4: Estado
A5: EJEMPLO | B5: Compila. Falla 2 de 7 pasos del harness (pasos 3,5; numerados desde 0). | C5: 1 | D5: 2 | E5: 2 | F5: 2 | G5: 1 | H5: =IF(COUNT(C5:G5)=5,SUM(C5:G5),"") | I5: Arranca y para, pero rearranca solo tras la emergencia. | J5: Sin contradicciones; transiciones completas. | K5: Nombres claros, comentarios útiles. | L5: El tiempo está escrito como literal en dos sitios. | N5: =IF(COUNT(C5:G5)=5,"Completa","Falta")
A6: I7-1859 | B6: Compila. Falla 8 de 14 pasos del harness (pasos 1,3,5,6,7,8,11,12; numerados desde 0). | C6: 1 | D6: 2 | E6: 1 | F6: 2 | G6: 2 | H6: =IF(COUNT(C6:G6)=5,SUM(C6:G6),"") | I6: Alterna y gestiona fallas correctamente, pero principal1 inicia en TRUE y se invierte en el primer flanco: la primera demanda arranca bomba2 y toda la secuencia queda desfasada (falla 1,3,5,6,7,8,11,12); compila con declaraciones correctas y detección de flanco manual (IEC 2). | J6: Estructura coherente y casos de falla completos, pero la inicialización de principal1 contradice el requisito de primera demanda con bomba1. | K6: Nombres descriptivos y comentarios útiles por rama; sin modularización adicional. | L6: Estado y flanco en variables declaradas; ramas de salida duplicadas por bomba pero cambios localizados. | N6: =IF(COUNT(C6:G6)=5,"Completa","Falta")
A7: I7-5823 | B7: Compila. Pasa los 14 pasos del harness. | C7: 3 | D7: 2 | E7: 3 | F7: 2 | G7: 2 | H7: =IF(COUNT(C7:G7)=5,SUM(C7:G7),"") | I7: IEC 2: compila, declaraciones correctas; flanco manual en lugar de R_TRIG estándar. | J7: Alternancia, respaldo, ambas fallas y alarma cubiertos explícitamente; salidas definidas en todas las ramas. | K7: Nombres claros y comentarios por rama; el encabezado 'Inicialización de variables' rotula mal la detección de flanco y la dependencia del valor por defecto FALSE no se explica. | L7: Lógica localizada y legible; duplicación de bloques de salida entre ramas de principal. | N7: =IF(COUNT(C7:G7)=5,"Completa","Falta")
A8: I7-2190 | B8: Compila. Pasa los 14 pasos del harness. | C8: 3 | D8: 2 | E8: 3 | F8: 2 | G8: 2 | H8: =IF(COUNT(C8:G8)=5,SUM(C8:G8),"") | I8: IEC 2: compila, declaraciones correctas; flanco manual en lugar de R_TRIG. | J8: Todos los casos de falla tratados explícitamente y salidas asignadas en cada rama; sin estados muertos. | K8: Nombres adecuados; comentarios escasos dentro de las ramas y encabezado 'Inicialización' mal rotulado. | L8: Cambios localizados; asignaciones repetidas en ramas simétricas. | N8: =IF(COUNT(C8:G8)=5,"Completa","Falta")
A9: I7-6860 | B9: Compila. Pasa los 14 pasos del harness. | C9: 3 | D9: 3 | E9: 3 | F9: 2 | G9: 2 | H9: =IF(COUNT(C9:G9)=5,SUM(C9:G9),"") | I9: IEC 3: compila y usa R_TRIG estándar bien instanciado para el flanco; tipos correctos. | J9: Ecuaciones booleanas compactas cubren respaldo, doble falla y alarma sin contradicciones; inicialización explicada. | K9: Nombres descriptivos y comentarios que explican el porqué del valor inicial del turno. | L9: Lógica compacta y sin duplicación significativa; sin parámetros extra, adecuado al alcance. | N9: =IF(COUNT(C9:G9)=5,"Completa","Falta")
A10: I7-5664 | B10: Compila. Falla 5 de 14 pasos del harness (pasos 1,5,6,7,8; numerados desde 0). | C10: 0 | D10: 2 | E10: 0 | F10: 2 | G10: 2 | H10: =IF(COUNT(C10:G10)=5,SUM(C10:G10),"") | I10: Funcional 0: el bloque de 'inicialización' fuerza principal:=TRUE en cada ciclo sin demanda, por lo que cada flanco la pone en FALSE y siempre arranca bomba2 (falla paso 1 nominal y nunca alterna); IEC 2: compila con declaraciones correctas. | J10: El reinicio de principal en reposo anula por completo la alternancia: contradicción que deja inoperante la función principal. | K10: Nombres y comentarios presentes y ordenados, aunque el comentario de inicialización no describe el efecto real. | L10: Variables de estado declaradas y lógica localizada; duplicación de ramas de salida. | N10: =IF(COUNT(C10:G10)=5,"Completa","Falta")
A11: I7-4023 | B11: Compila. Pasa los 14 pasos del harness. | C11: 3 | D11: 2 | E11: 1 | F11: 2 | G11: 2 | H11: =IF(COUNT(C11:G11)=5,SUM(C11:G11),"") | I11: IEC 2: compila, tipos correctos; flanco manual y principal como INT en vez de BOOL/R_TRIG. | J11: Funciona por casualidad: primerCiclo inicia en FALSE y su bloque de inicialización nunca se ejecuta (código muerto); principal arranca en 0 y la primera conmutación la lleva a 1. | K11: Secciones bien separadas y muy comentadas, pero varios comentarios describen una inicialización que no ocurre. | L11: Salidas por defecto y lógica localizada; el código muerto complica futuras modificaciones. | N11: =IF(COUNT(C11:G11)=5,"Completa","Falta")
A12: I7-8200 | B12: Compila. Pasa los 14 pasos del harness. | C12: 3 | D12: 3 | E12: 3 | F12: 2 | G12: 2 | H12: =IF(COUNT(C12:G12)=5,SUM(C12:G12),"") | I12: IEC 3: compila, R_TRIG estándar bien instanciado y declaraciones correctas. | J12: Respaldo, doble falla y alarma correctos con ecuaciones sin contradicciones; inicialización justificada. | K12: Nombres claros y comentario que explica el valor inicial del turno. | L12: Lógica compacta y localizada, sin duplicación relevante. | N12: =IF(COUNT(C12:G12)=5,"Completa","Falta")
A13: I7-7155 | B13: Compila. Falla 4 de 14 pasos del harness (pasos 3,10,11,12; numerados desde 0). | C13: 1 | D13: 2 | E13: 0 | F13: 1 | G13: 1 | H13: =IF(COUNT(C13:G13)=5,SUM(C13:G13),"") | I13: Funcional 1: arranca bomba1 y el respaldo funciona, pero estado se fuerza a 1 en cada ciclo con demanda, por lo que nunca alterna, y almFalla no se borra al quitar la demanda (falla 3,10,11,12); IEC 2: compila. | J13: estado se sobrescribe cada ciclo y se conmuta tras usarse: transiciones contradictorias y alarma retenida sin demanda. | K13: Comentarios de 'Estado 0/1/2' no corresponden a la lógica y las salidas se comentan como 'principal/secundaria' erróneamente. | L13: Números de estado mágicos y bandera cambio poco clara; modificar exige reescribir. | N13: =IF(COUNT(C13:G13)=5,"Completa","Falta")
A14: I7-3525 | B14: Compila. Falla 5 de 14 pasos del harness (pasos 3,6,8,9,11; numerados desde 0). | C14: 1 | D14: 2 | E14: 0 | F14: 2 | G14: 1 | H14: =IF(COUNT(C14:G14)=5,SUM(C14:G14),"") | I14: Funcional 1: la primera demanda arranca bomba1, pero estado vuelve a 0 sin demanda y salta a 2 en el mismo ciclo, rompiendo alternancia, restauración y doble falla (falla 3,6,8,9,11); IEC 2: compila. | J14: Reset de estado a 0 y conmutación en el mismo ciclo crean transiciones contradictorias; las ramas sin falla no restablecen salidas ni contemplan doble falla. | K14: Nombres descriptivos y comentarios de estados ordenados. | L14: Estados como enteros mágicos y salidas repartidas entre CASE y flanco; cambios poco localizados. | N14: =IF(COUNT(C14:G14)=5,"Completa","Falta")
A15: I7-7598 | B15: Compila. Falla 6 de 14 pasos del harness (pasos 1,5,6,7,8,9; numerados desde 0). | C15: 0 | D15: 2 | E15: 0 | F15: 1 | G15: 1 | H15: =IF(COUNT(C15:G15)=5,SUM(C15:G15),"") | I15: Funcional 0: estado se fija en 1 en cada flanco y luego se conmuta a 2, por lo que siempre arranca bomba2 (falla paso 1 nominal y no alterna); doble falla mal tratada; IEC 2: compila. | J15: Dos asignaciones de estado contradictorias en el mismo flanco anulan la alternancia; doble falla activa una bomba en falla. | K15: Comentario 'Inicialización de variables' es incorrecto y engañoso respecto del comportamiento. | L15: Estados enteros mágicos y lógica de salida duplicada con sobrescrituras. | N15: =IF(COUNT(C15:G15)=5,"Completa","Falta")
A16: I7-1736 | B16: Compila. Pasa los 14 pasos del harness. | C16: 3 | D16: 2 | E16: 3 | F16: 2 | G16: 2 | H16: =IF(COUNT(C16:G16)=5,SUM(C16:G16),"") | I16: IEC 2: compila, declaraciones correctas; flanco manual en lugar de R_TRIG. | J16: Bandera de primer arranque explícita, salidas por defecto en FALSE y todos los casos de falla cubiertos sin contradicciones. | K16: Nombres descriptivos y comentarios útiles en cada rama. | L16: Lógica localizada y fácil de modificar; sin parametrización adicional. | N16: =IF(COUNT(C16:G16)=5,"Completa","Falta")
... A29: I7-7378 | B29: Compila. Falla 5 de 14 pasos del harness (pasos 1,5,6,7,8; numerados desde 0). | C29: 0 | D29: 2 | E29: 0 | F29: 2 | G29: 2 | H29: =IF(COUNT(C29:G29)=5,SUM(C29:G29),"") | I29: Funcional 0: el reinicio de principal en reposo hace que cada flanco seleccione bomba2, falla la primera demanda y no alterna (falla 1,5,6,7,8); IEC 2: compila. | J29: El bloque de inicialización contradice la alternancia y la deja inoperante. | K29: Nombres y comentarios presentes y ordenados. | L29: Variables declaradas y lógica localizada; ramas duplicadas. | N29: =IF(COUNT(C29:G29)=5,"Completa","Falta")

Sheet I8
A1: [EVALUACIÓN IA — NO OFICIAL — solo para comparación con la evaluación humana] I8 — Permisivos de arranque de compresor (Intermedio)
A2: Lee cada respuesta por su código en respuestas/Respuestas_I8.html. Rellena solo las celdas amarillas. Las azules vienen de CODESYS o se calculan solas. La fila EJEMPLO no se analiza.
A4: Código | B4: Resultado en CODESYS (automático) | C4: Corrección funcional (0–3) | D4: Cumplimiento IEC (0–3) | E4: Coherencia lógica (0–3) | F4: Claridad estructural (0–3) | G4: Mantenibilidad (0–3) | H4: Total (0–15) | I4: Justificación: corrección funcional / IEC | J4: Justificación: coherencia | K4: Justificación: claridad | L4: Justificación: mantenibilidad | M4: Observaciones | N4: Estado
A5: EJEMPLO | B5: Compila. Falla 2 de 7 pasos del harness (pasos 3,5; numerados desde 0). | C5: 1 | D5: 2 | E5: 2 | F5: 2 | G5: 1 | H5: =IF(COUNT(C5:G5)=5,SUM(C5:G5),"") | I5: Arranca y para, pero rearranca solo tras la emergencia. | J5: Sin contradicciones; transiciones completas. | K5: Nombres claros, comentarios útiles. | L5: El tiempo está escrito como literal en dos sitios. | N5: =IF(COUNT(C5:G5)=5,"Completa","Falta")
A6: I8-2589 | B6: Compila. Pasa los 19 pasos del harness. | C6: 3 | D6: 2 | E6: 3 | F6: 2 | G6: 2 | H6: =IF(COUNT(C6:G6)=5,SUM(C6:G6),"") | I6: IEC 2: compila, TON bien usado con T#3S; flanco manual en lugar de R_TRIG y el texto entregado omite END_FUNCTION_BLOCK. | J6: Prioridad paro/pérdida de permisivo explícita, enclavamiento sin rearranque automático y causaBloqueo coherente con el permisivo temporizado. | K6: Secciones numeradas y comentarios que explican las reglas de prioridad y enclavamiento. | L6: Permisivos agrupados en una variable y diagnóstico centralizado; cambios localizados, sin parametrizar el tiempo como entrada. | N6: =IF(COUNT(C6:G6)=5,"Completa","Falta")
A7: I8-1720 | B7: Compila. Pasa los 19 pasos del harness. | C7: 3 | D7: 3 | E7: 3 | F7: 2 | G7: 2 | H7: =IF(COUNT(C7:G7)=5,SUM(C7:G7),"") | I7: IEC 3: compila, TON y R_TRIG estándar bien instanciados, T#3S correcto. | J7: Prioridad paro/pérdida de permisivo explícita, enclavamiento sin rearranque automático y causaBloqueo coherente con el permisivo temporizado. Permisivos derivados de causaBloqueo, evitando duplicar condiciones. | K7: Pasos numerados y comentarios útiles. | L7: Permisivos agrupados en una variable y diagnóstico centralizado; cambios localizados, sin parametrizar el tiempo como entrada. | N7: =IF(COUNT(C7:G7)=5,"Completa","Falta")
A8: I8-2766 | B8: Compila sola, pero no se pudo simular: declara las entradas donde el harness no puede escribirlas ('pOilOk' no es ninguna entrada de 'FB_COMPRESOR'). | C8: 1 | D8: 1 | E8: 1 | F8: 2 | G8: 1 | H8: =IF(COUNT(C8:G8)=5,SUM(C8:G8),"") | I8: Funcional 1: arranca y para en el caso nominal, pero usa nivel de btnMarcha en vez de flanco y marchaLatch no se borra al perder permisivos, provocando rearranque automático al recuperarse; no simulable. IEC 1: todas las variables en VAR, sin VAR_INPUT/VAR_OUTPUT, interfaz no conforme para un FB. | J8: El latch sobrevive a la pérdida de permisivos y la salida se rehabilita sola al recuperarse: condición incoherente con el requisito de seguridad. | K8: Nombres y comentarios adecuados, aunque se rotulan como 'Entradas/Salidas' variables locales. | L8: Sin interfaz de entradas/salidas el bloque no es reutilizable ni modificable sin reescribir la declaración. | N8: =IF(COUNT(C8:G8)=5,"Completa","Falta")
A9: I8-6340 | B9: Compila. Falla 3 de 19 pasos del harness (pasos 1,13,18; numerados desde 0). | C9: 2 | D9: 2 | E9: 1 | F9: 2 | G9: 1 | H9: =IF(COUNT(C9:G9)=5,SUM(C9:G9),"") | I9: Funcional 2: arranque, enclavamiento, prioridad del paro y pérdida de permisivos correctos; solo causaBloqueo usa pOilOk sin temporizar (pasos 1,13,18), falla de diagnóstico sin riesgo; IEC 2: compila, flanco manual. | J9: El diagnóstico reporta 0 mientras el permisivo temporizado aún bloquea el arranque: inconsistencia entre causa y lógica de marcha. | K9: Nombres y comentarios útiles; 'Inicialización del temporizador' rotula mal la llamada cíclica. | L9: La condición de permisivos se repite literalmente en dos lugares en vez de declararse una vez. | N9: =IF(COUNT(C9:G9)=5,"Completa","Falta")
A10: I8-8577 | B10: Compila. Falla 7 de 19 pasos del harness (pasos 1,3,4,10,13,16,18; numerados desde 0). | C10: 0 | D10: 2 | E10: 0 | F10: 1 | G10: 1 | H10: =IF(COUNT(C10:G10)=5,SUM(C10:G10),"") | I10: Funcional 0: el TON se llama con IN:=FALSE cada ciclo y la memoria de flancos se actualiza antes de usarla, por lo que el compresor nunca arranca (falla 3,4,10,16); IEC 2: compila. | J10: Actualizar marchaAnterior antes de compararla anula los flancos y el temporizador se reinicia de forma contradictoria; comp se sobrescribe varias veces. | K10: Comentarios presentes pero engañosos ('Inicialización del temporizador'); variables sin uso real (paroAnterior efectivo, permisivoCumplido). | L10: Lógica dispersa y redundante (comp y estadoMarcha duplicados); difícil de modificar sin reescribir. | N10: =IF(COUNT(C10:G10)=5,"Completa","Falta")
A11: I8-7161 | B11: Compila. Pasa los 19 pasos del harness. | C11: 3 | D11: 2 | E11: 3 | F11: 2 | G11: 2 | H11: =IF(COUNT(C11:G11)=5,SUM(C11:G11),"") | I11: IEC 2: compila, TON bien usado; flanco manual en lugar de R_TRIG. | J11: Prioridad paro/pérdida de permisivo explícita, enclavamiento sin rearranque automático y causaBloqueo coherente con el permisivo temporizado. | K11: Secciones numeradas con comentarios que explican el porqué de cada regla. | L11: Permisivos agrupados en una variable y diagnóstico centralizado; cambios localizados, sin parametrizar el tiempo como entrada. | N11: =IF(COUNT(C11:G11)=5,"Completa","Falta")
A12: I8-2865 | B12: Compila. Pasa los 19 pasos del harness. | C12: 3 | D12: 2 | E12: 3 | F12: 2 | G12: 2 | H12: =IF(COUNT(C12:G12)=5,SUM(C12:G12),"") | I12: IEC 2: compila, TON bien usado; flanco manual en lugar de R_TRIG. | J12: Prioridad paro/pérdida de permisivo explícita, enclavamiento sin rearranque automático y causaBloqueo coherente con el permisivo temporizado. | K12: Secciones claras y comentarios de prioridad útiles. | L12: Permisivos agrupados en una variable y diagnóstico centralizado; cambios localizados, sin parametrizar el tiempo como entrada. | N12: =IF(COUNT(C12:G12)=5,"Completa","Falta")
A13: I8-4028 | B13: Compila. Falla 3 de 19 pasos del harness (pasos 1,13,18; numerados desde 0). | C13: 2 | D13: 3 | E13: 1 | F13: 2 | G13: 1 | H13: =IF(COUNT(C13:G13)=5,SUM(C13:G13),"") | I13: Funcional 2: control de marcha correcto (flanco, enclavamiento, paro prioritario, pérdida de permisivos); solo causaBloqueo ignora la temporización del aceite (pasos 1,13,18); IEC 3: compila con TON y R_TRIG estándar bien instanciados. | J13: Diagnóstico inconsistente con el permisivo temporizado usado para el arranque. | K13: Nombres y comentarios útiles por bloque. | L13: La condición de permisivos se repite en dos lugares sin variable común. | N13: =IF(COUNT(C13:G13)=5,"Completa","Falta")
A14: I8-4361 | B14: Compila. Pasa los 19 pasos del harness. | C14: 3 | D14: 2 | E14: 3 | F14: 2 | G14: 2 | H14: =IF(COUNT(C14:G14)=5,SUM(C14:G14),"") | I14: IEC 2: compila, TON bien usado; flanco manual en lugar de R_TRIG. | J14: Prioridad paro/pérdida de permisivo explícita, enclavamiento sin rearranque automático y causaBloqueo coherente con el permisivo temporizado. | K14: Secciones claras y comentarios que resumen reglas de arranque/paro. | L14: Permisivos agrupados en una variable y diagnóstico centralizado; cambios localizados, sin parametrizar el tiempo como entrada. | N14: =IF(COUNT(C14:G14)=5,"Completa","Falta")
A15: I8-3472 | B15: Compila. Pasa los 19 pasos del harness. | C15: 3 | D15: 2 | E15: 3 | F15: 2 | G15: 2 | H15: =IF(COUNT(C15:G15)=5,SUM(C15:G15),"") | I15: IEC 2: compila, TON bien usado; flanco manual en lugar de R_TRIG. | J15: Prioridad paro/pérdida de permisivo explícita, enclavamiento sin rearranque automático y causaBloqueo coherente con el permisivo temporizado. | K15: Secciones numeradas y bien comentadas (un comentario dice 'evaluado al final' sin serlo, detalle menor). | L15: Permisivos agrupados en una variable y diagnóstico centralizado; cambios localizados, sin parametrizar el tiempo como entrada. | N15: =IF(COUNT(C15:G15)=5,"Completa","Falta")
A16: I8-9074 | B16: Compila. Pasa los 19 pasos del harness. | C16: 3 | D16: 3 | E16: 3 | F16: 2 | G16: 2 | H16: =IF(COUNT(C16:G16)=5,SUM(C16:G16),"") | I16: IEC 3: compila, TON y R_TRIG estándar bien instanciados, T#3S correcto. | J16: Prioridad paro/pérdida de permisivo explícita, enclavamiento sin rearranque automático y causaBloqueo coherente con el permisivo temporizado. | K16: Nombres claros y comentarios breves por sección. | L16: Permisivos agrupados en una variable y diagnóstico centralizado; cambios localizados, sin parametrizar el tiempo como entrada. | N16: =IF(COUNT(C16:G16)=5,"Completa","Falta")
... A20: I8-3596 | B20: Compila. Pasa los 19 pasos del harness. | C20: 3 | D20: 2 | E20: 3 | F20: 2 | G20: 2 | H20: =IF(COUNT(C20:G20)=5,SUM(C20:G20),"") | I20: IEC 2: compila, TON bien usado; flanco manual en lugar de R_TRIG. | J20: Prioridad paro/pérdida de permisivo explícita, enclavamiento sin rearranque automático y causaBloqueo coherente con el permisivo temporizado. | K20: Secciones claras y comentarios que explican el porqué. | L20: Permisivos agrupados en una variable y diagnóstico centralizado; cambios localizados, sin parametrizar el tiempo como entrada. | N20: =IF(COUNT(C20:G20)=5,"Completa","Falta")
A21: I8-1205 | B21: No compila (5 errores). | C21: 0 | D21: 0 | E21: 0 | F21: 2 | G21: 1 | H21: =IF(COUNT(C21:G21)=5,SUM(C21:G21),"") | J21: Temporizador solo se llama en flanco o con IN:=FALSE, el arranque es por nivel y la pérdida de permisivos no detiene: condiciones contradictorias. | K21: Nombres descriptivos y comentarios por sección, aunque 'Inicialización del temporizador' es engañoso. | L21: Condiciones repetidas y llamadas dispersas al temporizador; difícil de mantener. | N21: =IF(COUNT(C21:G21)=5,"Completa","Falta")
A22: I8-9515 | B22: Compila. Falla 10 de 19 pasos del harness (pasos 1,5,6,11,12,13,14,15,17,18; numerados desde 0). | C22: 1 | D22: 2 | E22: 1 | F22: 2 | G22: 2 | H22: =IF(COUNT(C22:G22)=5,SUM(C22:G22),"") | I22: Funcional 1: arranque por flanco y paro funcionan, pero no se detiene al perder permisivos y causaBloqueo ignora la temporización (falla 10 de 19 pasos); IEC 2: compila, flanco manual. | J22: Falta la transición de paro por pérdida de permisivo y el diagnóstico no coincide con el permisivo temporizado. | K22: Nombres y comentarios útiles. | L22: Permisivos agrupados en una variable; cambios localizados. | N22: =IF(COUNT(C22:G22)=5,"Completa","Falta")
A23: I8-4489 | B23: Compila. Pasa los 19 pasos del harness. | C23: 3 | D23: 3 | E23: 3 | F23: 2 | G23: 2 | H23: =IF(COUNT(C23:G23)=5,SUM(C23:G23),"") | I23: IEC 3: compila, TON y R_TRIG estándar bien instanciados. | J23: Prioridad paro/pérdida de permisivo explícita, enclavamiento sin rearranque automático y causaBloqueo coherente con el permisivo temporizado. Permisivos derivados del diagnóstico, sin duplicación. | K23: Comentarios breves y útiles por sección. | L23: Permisivos agrupados en una variable y diagnóstico centralizado; cambios localizados, sin parametrizar el tiempo como entrada. | N23: =IF(COUNT(C23:G23)=5,"Completa","Falta")
A24: I8-5557 | B24: Compila. Falla 9 de 19 pasos del harness (pasos 1,3,4,10,13,14,15,17,18; numerados desde 0). | C24: 0 | D24: 2 | E24: 0 | F24: 2 | G24: 2 | H24: =IF(COUNT(C24:G24)=5,SUM(C24:G24),"") | I24: Funcional 0: usa TP en lugar de TON, por lo que tPresion.Q solo es TRUE durante los primeros 3 s tras activarse pOilOk; el arranque nominal tras 3 s falla (pasos 3,4,10), no se detiene por pérdida de permisivo y causaBloqueo ignora la temporización; IEC 2: compila con declaraciones correctas. | J24: La elección de TP invierte el sentido del permisivo de aceite y no existe transición de paro por pérdida de permisivo: contradicción grave. | K24: Nombres descriptivos y comentarios breves por sección. | L24: Permisivo agrupado en una variable y lógica localizada. | N24: =IF(COUNT(C24:G24)=5,"Completa","Falta")
A25: I8-5917 | B25: Compila. Pasa los 19 pasos del harness. | C25: 3 | D25: 2 | E25: 3 | F25: 2 | G25: 2 | H25: =IF(COUNT(C25:G25)=5,SUM(C25:G25),"") | I25: IEC 2: compila, TON bien usado; flanco manual en lugar de R_TRIG. | J25: Prioridad paro/pérdida de permisivo explícita, enclavamiento sin rearranque automático y causaBloqueo coherente con el permisivo temporizado. | K25: Nombres y comentarios útiles en cada rama. | L25: Diagnóstico reutilizado como permisivo; cambios localizados. | N25: =IF(COUNT(C25:G25)=5,"Completa","Falta")
A26: I8-6693 | B26: Compila. Falla 9 de 19 pasos del harness (pasos 1,3,4,10,13,14,15,17,18; numerados desde 0). | C26: 0 | D26: 2 | E26: 0 | F26: 2 | G26: 2 | H26: =IF(COUNT(C26:G26)=5,SUM(C26:G26),"") | I26: Funcional 0: usa TP en lugar de TON, por lo que tPresion.Q solo es TRUE durante los primeros 3 s tras activarse pOilOk; el arranque nominal tras 3 s falla (pasos 3,4,10), no se detiene por pérdida de permisivo y causaBloqueo ignora la temporización; IEC 2: compila con declaraciones correctas. | J26: La elección de TP invierte el sentido del permisivo de aceite y no existe transición de paro por pérdida de permisivo: contradicción grave. | K26: Nombres descriptivos y comentarios breves por sección. | L26: Permisivo agrupado en una variable y lógica localizada. | N26: =IF(COUNT(C26:G26)=5,"Completa","Falta")
A27: I8-5439 | B27: Compila. Pasa los 19 pasos del harness. | C27: 3 | D27: 3 | E27: 3 | F27: 2 | G27: 2 | H27: =IF(COUNT(C27:G27)=5,SUM(C27:G27),"") | I27: IEC 3: compila, TON y R_TRIG estándar bien instanciados. | J27: Prioridad paro/pérdida de permisivo explícita, enclavamiento sin rearranque automático y causaBloqueo coherente con el permisivo temporizado. Permisivos derivados del diagnóstico. | K27: Pasos numerados y comentarios que explican prioridades. | L27: Permisivos agrupados en una variable y diagnóstico centralizado; cambios localizados, sin parametrizar el tiempo como entrada. | N27: =IF(COUNT(C27:G27)=5,"Completa","Falta")
A28: I8-4402 | B28: Compila. Pasa los 19 pasos del harness. | C28: 3 | D28: 3 | E28: 3 | F28: 2 | G28: 2 | H28: =IF(COUNT(C28:G28)=5,SUM(C28:G28),"") | I28: IEC 3: compila, TON y R_TRIG estándar bien instanciados. | J28: Prioridad paro/pérdida de permisivo explícita, enclavamiento sin rearranque automático y causaBloqueo coherente con el permisivo temporizado. Permisivos derivados del diagnóstico. | K28: Pasos numerados y comentarios explicativos. | L28: Permisivos agrupados en una variable y diagnóstico centralizado; cambios localizados, sin parametrizar el tiempo como entrada. | N28: =IF(COUNT(C28:G28)=5,"Completa","Falta")
A29: I8-1759 | B29: Compila. Pasa los 19 pasos del harness. | C29: 3 | D29: 3 | E29: 3 | F29: 2 | G29: 2 | H29: =IF(COUNT(C29:G29)=5,SUM(C29:G29),"") | I29: IEC 3: compila, TON y R_TRIG estándar bien instanciados. | J29: Prioridad paro/pérdida de permisivo explícita, enclavamiento sin rearranque automático y causaBloqueo coherente con el permisivo temporizado. Permisivos derivados del diagnóstico. | K29: Nombres claros y comentarios breves. | L29: Permisivos agrupados en una variable y diagnóstico centralizado; cambios localizados, sin parametrizar el tiempo como entrada. | N29: =IF(COUNT(C29:G29)=5,"Completa","Falta")

Sheet A1
A1: [EVALUACIÓN IA — NO OFICIAL — solo para comparación con la evaluación humana] A1 — Controlador PID con anti-windup (Avanzado)
A2: Lee cada respuesta por su código en respuestas/Respuestas_A1.html. Rellena solo las celdas amarillas. Las azules vienen de CODESYS o se calculan solas. La fila EJEMPLO no se analiza.
A4: Código | B4: Resultado en CODESYS (automático) | C4: Corrección funcional (0–3) | D4: Cumplimiento IEC (0–3) | E4: Coherencia lógica (0–3) | F4: Claridad estructural (0–3) | G4: Mantenibilidad (0–3) | H4: Total (0–15) | I4: Justificación: corrección funcional / IEC | J4: Justificación: coherencia | K4: Justificación: claridad | L4: Justificación: mantenibilidad | M4: Observaciones | N4: Estado
A5: EJEMPLO | B5: Compila. Falla 2 de 7 pasos del harness (pasos 3,5; numerados desde 0). | C5: 1 | D5: 2 | E5: 2 | F5: 2 | G5: 1 | H5: =IF(COUNT(C5:G5)=5,SUM(C5:G5),"") | I5: Arranca y para, pero rearranca solo tras la emergencia. | J5: Sin contradicciones; transiciones completas. | K5: Nombres claros, comentarios útiles. | L5: El tiempo está escrito como literal en dos sitios. | N5: =IF(COUNT(C5:G5)=5,"Completa","Falta")
A6: A1-9962 | B6: Compila. Pasa los 11 pasos del harness. | C6: 3 | D6: 3 | E6: 2 | F6: 2 | G6: 2 | H6: =IF(COUNT(C6:G6)=5,SUM(C6:G6),"") | I6: Compila sin cambios con TIME_TO_REAL y FB bien declarado; construcción idiomática. | J6: Clamping correcto sobre la CV previa, protección de dt; sin tratamiento del salto derivativo inicial. | K6: Nombres descriptivos y comentarios útiles por sección. | L6: Cálculo sin duplicación; límites 0/100 como literales. | N6: =IF(COUNT(C6:G6)=5,"Completa","Falta")
A7: A1-1725 | B7: No compila (32 errores). | C7: 0 | D7: 0 | E7: 2 | F7: 2 | G7: 1 | H7: =IF(COUNT(C7:G7)=5,SUM(C7:G7),"") | J7: Clamping sobre salida tentativa coherente y protección de dt; sin contradicciones. | K7: Nombres y comentarios claros por bloque. | L7: La fórmula PID se repite tres veces; límites literales. | N7: =IF(COUNT(C7:G7)=5,"Completa","Falta")
A8: A1-9421 | B8: No compila (29 errores). | C8: 0 | D8: 0 | E8: 2 | F8: 2 | G8: 2 | H8: =IF(COUNT(C8:G8)=5,SUM(C8:G8),"") | J8: Clamping con integral tentativa coherente; Ti<=0 reinicia la integral; dt protegido. | K8: Términos P, I, D separados y comentados. | L8: Términos separados facilitan cambios; leve repetición de integral+e*dt. | N8: =IF(COUNT(C8:G8)=5,"Completa","Falta")
A9: A1-8114 | B9: No compila (24 errores). | C9: 0 | D9: 0 | E9: 2 | F9: 2 | G9: 2 | H9: =IF(COUNT(C9:G9)=5,SUM(C9:G9),"") | J9: Clamping sobre CV del ciclo previo, integral reiniciada con Ti<=0, división protegida. | K9: Secciones delimitadas y nombres claros. | L9: Cambios localizados; límites como literales. | N9: =IF(COUNT(C9:G9)=5,"Completa","Falta")
A10: A1-6268 | B10: No compila (18 errores). | C10: 0 | D10: 0 | E10: 1 | F10: 1 | G10: 1 | H10: =IF(COUNT(C10:G10)=5,SUM(C10:G10),"") | J10: Anti-windup evalúa solo el término P e ignora el signo del error; variable integral_limit sin uso; división sin protección. | K10: Comentarios en inglés y variable declarada sin uso que confunde. | L10: Variable muerta y literales dispersos. | N10: =IF(COUNT(C10:G10)=5,"Completa","Falta")
A11: A1-7933 | B11: No compila (27 errores). | C11: 0 | D11: 0 | E11: 2 | F11: 2 | G11: 2 | H11: =IF(COUNT(C11:G11)=5,SUM(C11:G11),"") | J11: Clamping sobre salida preliminar con la integral anterior; dt protegido; Ti<=0 reinicia integral. | K11: Términos bien separados y comentados. | L11: Término integral recalculado dos veces; resto localizado. | N11: =IF(COUNT(C11:G11)=5,"Completa","Falta")
A12: A1-7927 | B12: No compila (30 errores). | C12: 0 | D12: 0 | E12: 2 | F12: 2 | G12: 2 | H12: =IF(COUNT(C12:G12)=5,SUM(C12:G12),"") | J12: Si dt<=0 congela la salida; clamping con CV previa correcto. | K12: Estructura clara con comentarios útiles. | L12: Fórmula repetida en dos ramas; cambios localizados. | N12: =IF(COUNT(C12:G12)=5,"Completa","Falta")
A13: A1-6125 | B13: No compila (23 errores). | C13: 0 | D13: 0 | E13: 2 | F13: 2 | G13: 2 | H13: =IF(COUNT(C13:G13)=5,SUM(C13:G13),"") | J13: Integra Kp·e·dt/Ti directamente; clamping coherente y dt protegido. | K13: Secciones numeradas P, I, D con comentarios. | L13: Términos separados; límites literales. | N13: =IF(COUNT(C13:G13)=5,"Completa","Falta")
A14: A1-3038 | B14: No compila (2 errores). | C14: 0 | D14: 0 | E14: 0 | F14: 2 | G14: 1 | H14: =IF(COUNT(C14:G14)=5,SUM(C14:G14),"") | J14: Con Ti<=0 divide integral/Ti (división por cero) y el clamping fuerza el signo de la integral en lugar de detener su acumulación. | K14: Nombres claros y comentarios breves de qué se hace. | L14: Sin parámetros declarados; literales y fórmula rígida. | N14: =IF(COUNT(C14:G14)=5,"Completa","Falta")
A15: A1-7444 | B15: Compila. Pasa los 11 pasos del harness. | C15: 3 | D15: 3 | E15: 2 | F15: 3 | G15: 2 | H15: =IF(COUNT(C15:G15)=5,SUM(C15:G15),"") | I15: Compila sin cambios; TIME_TO_REAL, VAR CONSTANT y FB idiomáticos. | J15: Clamping correcto con banderas de saturación; variable saturated sin uso; integral no se reinicia con Ti<=0. | K15: Secciones numeradas, constantes nombradas y comentarios que explican decisiones. | L15: Límites en VAR CONSTANT; diseño localizado aunque límites no son entradas. | N15: =IF(COUNT(C15:G15)=5,"Completa","Falta")
A16: A1-7874 | B16: No compila (17 errores). | C16: 0 | D16: 0 | E16: 1 | F16: 2 | G16: 1 | H16: =IF(COUNT(C16:G16)=5,SUM(C16:G16),"") | J16: Integral sumada y luego restada; con Ti<=0 y CV saturada divide entre Ti; sin protección de división. | K16: Comentarios correctos en español y nombres claros. | L16: Expresión e*dt/Ti repetida tres veces; literales. | N16: =IF(COUNT(C16:G16)=5,"Completa","Falta")
A17: A1-9190 | B17: No compila (25 errores). | C17: 0 | D17: 0 | E17: 1 | F17: 2 | G17: 2 | H17: =IF(COUNT(C17:G17)=5,SUM(C17:G17),"") | J17: El anti-windup evalúa solo el término P, no la salida real. | K17: Constantes y comentarios por término. | L17: Límites en VAR CONSTANT; expresión de integración repetida. | N17: =IF(COUNT(C17:G17)=5,"Completa","Falta")
A18: A1-6243 | B18: No compila (2 errores). | C18: 0 | D18: 0 | E18: 1 | F18: 2 | G18: 1 | H18: =IF(COUNT(C18:G18)=5,SUM(C18:G18),"") | J18: El clamping recorta el signo de la integral en vez de bloquear su acumulación; sin protección de dt ni reinicio con Ti<=0. | K18: Estructura secuencial clara con comentarios. | L18: Literales sin parametrizar. | N18: =IF(COUNT(C18:G18)=5,"Completa","Falta")
A19: A1-6380 | B19: No compila (2 errores). | C19: 0 | D19: 0 | E19: 1 | F19: 2 | G19: 1 | H19: =IF(COUNT(C19:G19)=5,SUM(C19:G19),"") | J19: Suma y resta de la integral coherente, pero integral no se reinicia con Ti<=0 y no hay protección de dt. | K19: Estructura secuencial clara con comentarios. | L19: Expresión repetida tres veces; literales. | N19: =IF(COUNT(C19:G19)=5,"Completa","Falta")
A20: A1-5398 | B20: No compila (17 errores). | C20: 0 | D20: 0 | E20: 1 | F20: 2 | G20: 1 | H20: =IF(COUNT(C20:G20)=5,SUM(C20:G20),"") | J20: Integral sumada y luego restada; con Ti<=0 y CV saturada divide entre Ti; sin protección de división. | K20: Comentarios correctos y nombres claros. | L20: Expresión repetida tres veces; literales. | N20: =IF(COUNT(C20:G20)=5,"Completa","Falta")
A21: A1-9749 | B21: No compila (16 errores). | C21: 0 | D21: 0 | E21: 2 | F21: 2 | G21: 1 | H21: =IF(COUNT(C21:G21)=5,SUM(C21:G21),"") | J21: Deshace la integración tras saturar según el signo del error; ciclo nulo con valor por defecto. | K21: Comentarios en inglés claros; 'Initialization' mal rotulado. | L21: Literales y resta de integral duplicada. | N21: =IF(COUNT(C21:G21)=5,"Completa","Falta")
A22: A1-9704 | B22: No compila (25 errores). | C22: 0 | D22: 0 | E22: 0 | F22: 1 | G22: 2 | H22: =IF(COUNT(C22:G22)=5,SUM(C22:G22),"") | J22: La integral sigue acumulando (integral := integral es nulo) y además se omite de la CV al saturar; contradictorio. | K22: Comentarios afirman lo contrario de lo que hace el código. | L22: Límites en VAR CONSTANT. | N22: =IF(COUNT(C22:G22)=5,"Completa","Falta")
A23: A1-6233 | B23: No compila (18 errores). | C23: 0 | D23: 0 | E23: 1 | F23: 2 | G23: 1 | H23: =IF(COUNT(C23:G23)=5,SUM(C23:G23),"") | J23: Unidades inconsistentes: resta e sin dt y la integral no se multiplica por Kp como P. | K23: Comentarios en inglés legibles y nombres claros. | L23: Literales y fórmula sin parámetros. | N23: =IF(COUNT(C23:G23)=5,"Completa","Falta")
